Workbook
Name Company_Name: #REF!
Name Net_Profit: #REF!
Name RowTitleRegion1..C3: #REF!
Name RowTitleRegion1..C3.3: #REF!
Name RowTitleRegion1..C3.4: #REF!
Name RowTitleRegion1..C3.5: #REF!
Name RowTitleRegion1..C4: #REF!
Name RowTitleRegion2..H20: #REF!
Name Sales_Revenue: SUMIFS(#REF!,#REF!,"Sales Revenue")
Name Title1: #REF!
Name Title2: #REF!
Name Title3: #REF!
Name Title4: #REF!
Name Title5: #REF!
Name Title6: #REF!
Name Total_Cost_Sales: #REF!
Name Total_General_and_Administrative: #REF!
Name Total_Gross_Profit: #REF!
Name Total_Income_Operations: #REF!
Name Total_Operating_Expenses: #REF!
Name Total_Other_Expenses: #REF!
Name Total_Other_Income: #REF!
Name Total_Research_and_Development: #REF!
Name Total_Sales_and_Marketing: #REF!
Name Total_Sales_Revenue: #REF!
Name Total_Taxes: #REF!
Name Workbook_Dates: #REF!
Name Workbook_Title: #REF!

Sheet MODEL>>

Sheet Outputs
J2: =Control!D2 -> Basic Financial Model
J3: =MID(CELL("filename",A1),FIND("]",CELL("filename",A1))+1,255) -> Outputs
J4: =Control!D4 -> Financial Scenario: Base Case
J5: Calendar Year | N5: =N13 -> CY26 | O5: =O13 -> CY26 | P5: =P13 -> CY26 | Q5: =Q13 -> CY26 | R5: =R13 -> CY26 | S5: =S13 -> CY26 | T5: =T13 -> CY27 | U5: =U13 -> CY27 | ... KI5: =KI13 -> CY49
J6: Financial Year | N6: =N14 -> FY27 | O6: =O14 -> FY27 | P6: =P14 -> FY27 | Q6: =Q14 -> FY27 | R6: =R14 -> FY27 | S6: =S14 -> FY27 | T6: =T14 -> FY27 | U6: =U14 -> FY27 | ... KI6: =KI14 -> FY50
B7: Sum Project | C7: Sum Loan | D7: Average | E7: Max | F7: Min | G7: Ref | H7: Units | J7: Date | N7: =TEXT(N12,"mmm-yy") -> Jul-26 | O7: =TEXT(O12,"mmm-yy") -> Aug-26 | P7: =TEXT(P12,"mmm-yy") -> Sep-26 | Q7: =TEXT(Q12,"mmm-yy") -> Oct-26 | R7: =TEXT(R12,"mmm-yy") -> Nov-26 | S7: =TEXT(S12,"mmm-yy") -> Dec-26 | T7: =TEXT(T12,"mmm-yy") -> Jan-27 | U7: =TEXT(U12,"mmm-yy") -> Feb-27 | ... KI7: =TEXT(KI12,"mmm-yy") -> Dec-49
J9: Periods
E11: =MAX(N11:KI11) -> 54758 | F11: =MIN(N11:KI11) -> 46204 | H11: Date | M11: Start of period | N11: =DATE(2026,7,1) -> 46204 | O11: =N12+1 -> 46235 | P11: =O12+1 -> 46266 | Q11: =P12+1 -> 46296 | R11: =Q12+1 -> 46327 | S11: =R12+1 -> 46357 | T11: =S12+1 -> 46388 | U11: =T12+1 -> 46419 | V11: =U12+1 -> 46447 | ... KI11: =KH12+1 -> 54758
E12: =MAX(N12:KI12) -> 54788 | F12: =MIN(N12:KI12) -> 46234 | H12: Date | M12: End of period | N12: =EOMONTH(N11,0) -> 46234 | O12: =EOMONTH(O11,0) -> 46265 | P12: =EOMONTH(P11,0) -> 46295 | Q12: =EOMONTH(Q11,0) -> 46326 | R12: =EOMONTH(R11,0) -> 46356 | S12: =EOMONTH(S11,0) -> 46387 | T12: =EOMONTH(T11,0) -> 46418 | U12: =EOMONTH(U11,0) -> 46446 | ... KI12: =EOMONTH(KI11,0) -> 54788
H13: Date | M13: Calendar year | N13: ="CY"&RIGHT(YEAR(N11),2) -> CY26 | O13: ="CY"&RIGHT(YEAR(O11),2) -> CY26 | P13: ="CY"&RIGHT(YEAR(P11),2) -> CY26 | Q13: ="CY"&RIGHT(YEAR(Q11),2) -> CY26 | R13: ="CY"&RIGHT(YEAR(R11),2) -> CY26 | S13: ="CY"&RIGHT(YEAR(S11),2) -> CY26 | T13: ="CY"&RIGHT(YEAR(T11),2) -> CY27 | U13: ="CY"&RIGHT(YEAR(U11),2) -> CY27 | ... KI13: ="CY"&RIGHT(YEAR(KI11),2) -> CY49
H14: Date | M14: Financial Year | N14: ="FY"&IF(MONTH(N11)>6,RIGHT(YEAR(N11)+1,2),RIGHT(YEAR(N11),2)) -> FY27 | O14: ="FY"&IF(MONTH(O11)>6,RIGHT(YEAR(O11)+1,2),RIGHT(YEAR(O11),2)) -> FY27 | P14: ="FY"&IF(MONTH(P11)>6,RIGHT(YEAR(P11)+1,2),RIGHT(YEAR(P11),2)) -> FY27 | Q14: ="FY"&IF(MONTH(Q11)>6,RIGHT(YEAR(Q11)+1,2),RIGHT(YEAR(Q11),2)) -> FY27 | R14: ="FY"&IF(MONTH(R11)>6,RIGHT(YEAR(R11)+1,2),RIGHT(YEAR(R11),2)) -> FY27 | S14: ="FY"&IF(MONTH(S11)>6,RIGHT(YEAR(S11)+1,2),RIGHT(YEAR(S11),2)) -> FY27 | T14: ="FY"&IF(MONTH(T11)>6,RIGHT(YEAR(T11)+1,2),RIGHT(YEAR(T11),2)) -> FY27 | U14: ="FY"&IF(MONTH(U11)>6,RIGHT(YEAR(U11)+1,2),RIGHT(YEAR(U11),2)) -> FY27 | ... KI14: ="FY"&IF(MONTH(KI11)>6,RIGHT(YEAR(KI11)+1,2),RIGHT(YEAR(KI11),2)) -> FY50
H15: Days | M15: Days in Period | N15: =N12-N11+1 -> 31 | O15: =O12-O11+1 -> 31 | P15: =P12-P11+1 -> 30 | Q15: =Q12-Q11+1 -> 31 | R15: =R12-R11+1 -> 30 | S15: =S12-S11+1 -> 31 | T15: =T12-T11+1 -> 31 | U15: =U12-U11+1 -> 28 | ... KI15: =KI12-KI11+1 -> 31
H16: % pa | M16: Inflation index
J18: Financial Statements
K20: Income Statement - Inputs
L22: Volumes and Prices
H23: M Ltrs | M23: Sales Volume | N23: =Inputs!K24 -> 41 | O23: =Inputs!L24 -> 37 | P23: =Inputs!M24 -> 51 | Q23: =Inputs!N24 -> 74 | R23: =Inputs!O24 -> 36 | S23: =Inputs!P24 -> 33 | T23: =Inputs!Q24 -> 43 | U23: =Inputs!R24 -> 48 | ... KI23: =Inputs!KF24 -> 53
H24: USD/Ltr, real | M24: Sales Price | N24: =Inputs!K40 -> 2.35 | O24: =Inputs!L40 -> 2.35 | P24: =Inputs!M40 -> 2.35 | Q24: =Inputs!N40 -> 2.35 | R24: =Inputs!O40 -> 2.35 | S24: =Inputs!P40 -> 2.35 | T24: =Inputs!Q40 -> 2.3 | U24: =Inputs!R40 -> 2.3 | ... KI24: =Inputs!KF40 -> 2.25
H25: USD/Ltr, real | M25: Unit Cost | N25: =Inputs!K56 -> -0.28887274 | O25: =Inputs!L56 -> -0.26384952 | P25: =Inputs!M56 -> -0.36179302 | Q25: =Inputs!N56 -> -0.51930819 | R25: =Inputs!O56 -> -0.25707948 | S25: =Inputs!P56 -> -0.23743734 | T25: =Inputs!Q56 -> -0.30209971 | U25: =Inputs!R56 -> -0.33805637 | ... KI25: =Inputs!KF56 -> -0.37564673
H26: USDm, real | M26: Variable Costs | N26: =N23*N25 -> -11.843782 | O26: =O23*O25 -> -9.7624321 | P26: =P23*P25 -> -18.451444 | Q26: =Q23*Q25 -> -38.428806 | R26: =R23*R25 -> -9.2548614 | S26: =S23*S25 -> -7.8354324 | T26: =T23*T25 -> -12.990287 | U26: =U23*U25 -> -16.226706 | ... KI26: =KI23*KI25 -> -19.909277
H27: USDm, real | M27: Fixed Costs | N27: =Inputs!K72 -> -2.5 | O27: =Inputs!L72 -> -2.5 | P27: =Inputs!M72 -> -2.5 | Q27: =Inputs!N72 -> -2.5 | R27: =Inputs!O72 -> -2.5 | S27: =Inputs!P72 -> -2.5 | T27: =Inputs!Q72 -> -2.5 | U27: =Inputs!R72 -> -2.5 | ... KI27: =Inputs!KF72 -> -2.5
K29: Income Statement - to CFADS
L31: EBITDA
H32: USDm, real | M32: Revenue | N32: =N23*N24 -> 96.35 | O32: =O23*O24 -> 86.95 | P32: =P23*P24 -> 119.85 | Q32: =Q23*Q24 -> 173.9 | R32: =R23*R24 -> 84.6 | S32: =S23*S24 -> 77.55 | T32: =T23*T24 -> 98.9 | U32: =U23*U24 -> 110.4 | ... KI32: =KI23*KI24 -> 119.25
H33: USDm, real | M33: COGS | N33: =SUM(N26:N27) -> -14.343782 | O33: =SUM(O26:O27) -> -12.262432 | P33: =SUM(P26:P27) -> -20.951444 | Q33: =SUM(Q26:Q27) -> -40.928806 | R33: =SUM(R26:R27) -> -11.754861 | S33: =SUM(S26:S27) -> -10.335432 | T33: =SUM(T26:T27) -> -15.490287 | U33: =SUM(U26:U27) -> -18.726706 | ... KI33: =SUM(KI26:KI27) -> -22.409277
H34: USDm, real | M34: Total Income | N34: =SUM(N32:N33) -> 82.006218 | O34: =SUM(O32:O33) -> 74.687568 | P34: =SUM(P32:P33) -> 98.898556 | Q34: =SUM(Q32:Q33) -> 132.97119 | R34: =SUM(R32:R33) -> 72.845139 | S34: =SUM(S32:S33) -> 67.214568 | T34: =SUM(T32:T33) -> 83.409713 | U34: =SUM(U32:U33) -> 91.673294 | ... KI34: =SUM(KI32:KI33) -> 96.840723
H35: USDm, real | M35: SG&A | N35: =Inputs!K88 -> -2.625 | O35: =Inputs!L88 -> -2.625 | P35: =Inputs!M88 -> -2.625 | Q35: =Inputs!N88 -> -2.625 | R35: =Inputs!O88 -> -2.625 | S35: =Inputs!P88 -> -2.625 | T35: =Inputs!Q88 -> -2.625 | U35: =Inputs!R88 -> -2.625 | ... KI35: =Inputs!KF88 -> -2.625
H36: USDm, real | M36: Other | N36: =Inputs!K104 -> -2.1 | O36: =Inputs!L104 -> -2.1 | P36: =Inputs!M104 -> -2.1 | Q36: =Inputs!N104 -> -2.1 | R36: =Inputs!O104 -> -2.1 | S36: =Inputs!P104 -> -2.1 | T36: =Inputs!Q104 -> -2.1 | U36: =Inputs!R104 -> -2.1 | ... KI36: =Inputs!KF104 -> -2.1
H37: USDm, real | M37: Cash EBITDA | N37: =SUM(N34:N36) -> 77.281218 | O37: =SUM(O34:O36) -> 69.962568 | P37: =SUM(P34:P36) -> 94.173556 | Q37: =SUM(Q34:Q36) -> 128.24619 | R37: =SUM(R34:R36) -> 68.120139 | S37: =SUM(S34:S36) -> 62.489568 | T37: =SUM(T34:T36) -> 78.684713 | U37: =SUM(U34:U36) -> 86.948294 | ... KI37: =SUM(KI34:KI36) -> 92.115723
H38: USDm, real | M38: Capex | N38: =-Inputs!K120 -> -1 | O38: =-Inputs!L120 -> -1 | P38: =-Inputs!M120 -> -1 | Q38: =-Inputs!N120 -> -1 | R38: =-Inputs!O120 -> -1 | S38: =-Inputs!P120 -> -1 | T38: =-Inputs!Q120 -> -1 | U38: =-Inputs!R120 -> -1 | ... KI38: =-Inputs!KF120 -> -1
G39: =Control!H135 -> 0.3 | H39: USDm, real | M39: Tax (est.) | N39: =MIN(-N37*$G39,0) -> -23.184365 | O39: =MIN(-O37*$G39,0) -> -20.98877 | P39: =MIN(-P37*$G39,0) -> -28.252067 | Q39: =MIN(-Q37*$G39,0) -> -38.473858 | R39: =MIN(-R37*$G39,0) -> -20.436042 | S39: =MIN(-S37*$G39,0) -> -18.74687 | T39: =MIN(-T37*$G39,0) -> -23.605414 | U39: =MIN(-U37*$G39,0) -> -26.084488 | ... KI39: =MIN(-KI37*$G39,0) -> -27.634717
H40: USDm, real | M40: CFADS | N40: =SUM(N37:N39) -> 53.096852 | O40: =SUM(O37:O39) -> 47.973798 | P40: =SUM(P37:P39) -> 64.921489 | Q40: =SUM(Q37:Q39) -> 88.772336 | R40: =SUM(R37:R39) -> 46.684097 | S40: =SUM(S37:S39) -> 42.742697 | T40: =SUM(T37:T39) -> 54.079299 | U40: =SUM(U37:U39) -> 59.863806 | ... KI40: =SUM(KI37:KI39) -> 63.481006
K42: Cash Flow Statement
L44: Cash Flow Statement
H45: USDm, real | M45: Operating Cash Flows | N45: =N40 -> 53.096852 | O45: =O40 -> 47.973798 | P45: =P40 -> 64.921489 | Q45: =Q40 -> 88.772336 | R45: =R40 -> 46.684097 | S45: =S40 -> 42.742697 | T45: =T40 -> 54.079299 | U45: =U40 -> 59.863806 | ... KI45: =KI40 -> 63.481006
H46: USDm, real | M46: Investing Cash Flows | N46: =N38 -> -1 | O46: =O38 -> -1 | P46: =P38 -> -1 | Q46: =Q38 -> -1 | R46: =R38 -> -1 | S46: =S38 -> -1 | T46: =T38 -> -1 | U46: =U38 -> -1 | ... KI46: =KI38 -> -1
H47: USDm, real | M47: Financing Cash Flows | N47: =N81+N82+N110+N111+N112 -> 0 | O47: =O81+O82+O110+O111+O112 -> 0 | P47: =P81+P82+P110+P111+P112 -> 0 | Q47: =Q81+Q82+Q110+Q111+Q112 -> 0 | R47: =R81+R82+R110+R111+R112 -> 0 | S47: =S81+S82+S110+S111+S112 -> -35 | T47: =T81+T82+T110+T111+T112 -> 40 | U47: =U81+U82+U110+U111+U112 -> 0 | ... KI47: =KI81+KI82+KI110+KI111+KI112 -> 0
H48: USDm, real | M48: Opening Cash Balance | N48: 159.90315 | O48: =N50 -> 212 | P48: =O50 -> 258.9738 | Q48: =P50 -> 322.89529 | R48: =Q50 -> 410.66762 | S48: =R50 -> 456.35172 | T48: =S50 -> 463.09442 | U48: =T50 -> 556.17372 | V48: =U50 -> 615.03752 | ... KI48: =KH50 -> 19177.03
H49: USDm, real | M49: Net Cash Flow | N49: =SUM(N45:N47) -> 52.096852 | O49: =SUM(O45:O47) -> 46.973798 | P49: =SUM(P45:P47) -> 63.921489 | Q49: =SUM(Q45:Q47) -> 87.772336 | R49: =SUM(R45:R47) -> 45.684097 | S49: =SUM(S45:S47) -> 6.7426973 | T49: =SUM(T45:T47) -> 93.079299 | U49: =SUM(U45:U47) -> 58.863806 | ... KI49: =SUM(KI45:KI47) -> 62.481006
H50: USDm, real | M50: Closing Cash Balance | N50: =SUM(N48:N49) -> 212 | O50: =SUM(O48:O49) -> 258.9738 | P50: =SUM(P48:P49) -> 322.89529 | Q50: =SUM(Q48:Q49) -> 410.66762 | R50: =SUM(R48:R49) -> 456.35172 | S50: =SUM(S48:S49) -> 463.09442 | T50: =SUM(T48:T49) -> 556.17372 | U50: =SUM(U48:U49) -> 615.03752 | ... KI50: =SUM(KI48:KI49) -> 19239.511
K52: Balance Sheet
L54: Balance Sheet
H55: USDm, real | M55: Cash | N55: =Control!H115 -> 212 | O55: =O50 -> 258.9738 | P55: =P50 -> 322.89529 | Q55: =Q50 -> 410.66762 | R55: =R50 -> 456.35172 | S55: =S50 -> 463.09442 | T55: =T50 -> 556.17372 | U55: =U50 -> 615.03752 | V55: =V50 -> 681.71406 | ... KI55: =KI50 -> 19239.511
H56: USDm, real | M56: PPE | N56: =Control!H142 -> 1250 | O56: =N56-O38 -> 1251 | P56: =O56-P38 -> 1252 | Q56: =P56-Q38 -> 1253 | R56: =Q56-R38 -> 1254 | S56: =R56-S38 -> 1255 | T56: =S56-T38 -> 1256 | U56: =T56-U38 -> 1257 | V56: =U56-V38 -> 1258 | ... KI56: =KH56-KI38 -> 1531
H57: USDm, real | M57: Other Assets | N57: =Control!H143 -> 117 | O57: =N57 -> 117 | P57: =O57 -> 117 | Q57: =P57 -> 117 | R57: =Q57 -> 117 | S57: =R57 -> 117 | T57: =S57 -> 117 | U57: =T57 -> 117 | V57: =U57 -> 117 | ... KI57: =KH57 -> 117
H58: USDm, real | M58: Total Assets | N58: =SUM(N55:N57) -> 1579 | O58: =SUM(O55:O57) -> 1626.9738 | P58: =SUM(P55:P57) -> 1691.8953 | Q58: =SUM(Q55:Q57) -> 1780.6676 | R58: =SUM(R55:R57) -> 1827.3517 | S58: =SUM(S55:S57) -> 1835.0944 | T58: =SUM(T55:T57) -> 1929.1737 | U58: =SUM(U55:U57) -> 1989.0375 | ... KI58: =SUM(KI55:KI57) -> 20887.511
H59: USDm, real | M59: Debt | N59: =N83+N113 -> 245 | O59: =O83+O113 -> 245 | P59: =P83+P113 -> 245 | Q59: =Q83+Q113 -> 245 | R59: =R83+R113 -> 245 | S59: =S83+S113 -> 210 | T59: =T83+T113 -> 250 | U59: =U83+U113 -> 250 | ... KI59: =KI83+KI113 -> 0
H60: USDm, real | M60: Other | N60: =Control!H146 -> 35 | O60: =N60 -> 35 | P60: =O60 -> 35 | Q60: =P60 -> 35 | R60: =Q60 -> 35 | S60: =R60 -> 35 | T60: =S60 -> 35 | U60: =T60 -> 35 | V60: =U60 -> 35 | ... KI60: =KH60 -> 35
H61: USDm, real | M61: Total Liabilities | N61: =SUM(N59:N60) -> 280 | O61: =SUM(O59:O60) -> 280 | P61: =SUM(P59:P60) -> 280 | Q61: =SUM(Q59:Q60) -> 280 | R61: =SUM(R59:R60) -> 280 | S61: =SUM(S59:S60) -> 245 | T61: =SUM(T59:T60) -> 285 | U61: =SUM(U59:U60) -> 285 | ... KI61: =SUM(KI59:KI60) -> 35
H62: USDm, real | M62: Share Holders Equity | N62: =Control!H149 -> 700 | O62: =N62 -> 700 | P62: =O62 -> 700 | Q62: =P62 -> 700 | R62: =Q62 -> 700 | S62: =R62 -> 700 | T62: =S62 -> 700 | U62: =T62 -> 700 | V62: =U62 -> 700 | ... KI62: =KH62 -> 700
H63: USDm, real | M63: Retained Earnings | N63: =Control!H150 -> 599 | O63: =N63+O40 -> 646.9738 | P63: =O63+P40 -> 711.89529 | Q63: =P63+Q40 -> 800.66762 | R63: =Q63+R40 -> 847.35172 | S63: =R63+S40 -> 890.09442 | T63: =S63+T40 -> 944.17372 | U63: =T63+U40 -> 1004.0375 | V63: =U63+V40 -> 1096.7141 | ... KI63: =KH63+KI40 -> 20152.511
H64: USDm, real | M64: Total Equity | N64: =SUM(N62:N63) -> 1299 | O64: =SUM(O62:O63) -> 1346.9738 | P64: =SUM(P62:P63) -> 1411.8953 | Q64: =SUM(Q62:Q63) -> 1500.6676 | R64: =SUM(R62:R63) -> 1547.3517 | S64: =SUM(S62:S63) -> 1590.0944 | T64: =SUM(T62:T63) -> 1644.1737 | U64: =SUM(U62:U63) -> 1704.0375 | ... KI64: =SUM(KI62:KI63) -> 20852.511
M66: Balance Sheet Check | N66: =N58-N61-N64 -> 0 | O66: =O58-O61-O64 -> 0 | P66: =P58-P61-P64 -> 0 | Q66: =Q58-Q61-Q64 -> 0 | R66: =R58-R61-R64 -> 0 | S66: =S58-S61-S64 -> 0 | T66: =T58-T61-T64 -> 0 | U66: =U58-U61-U64 -> 0 | ... KI66: =KI58-KI61-KI64 -> 0
J68: Debt Facility
K70: Existing Facility
L72: Facility Flags
G73: =Control!H39 -> 45565 | H73: 1/0 Flag | M73: Establishment Flag
G74: =MIN(EOMONTH(G102,-1),Control!H41) -> 46387 | H74: 1/0 Flag | M74: Facility Active | N74: =IF(AND(N$12>=$G73,N$12<=$G74),1,0) -> 1 | O74: =IF(AND(O$12>=$G73,O$12<=$G74),1,0) -> 1 | P74: =IF(AND(P$12>=$G73,P$12<=$G74),1,0) -> 1 | Q74: =IF(AND(Q$12>=$G73,Q$12<=$G74),1,0) -> 1 | R74: =IF(AND(R$12>=$G73,R$12<=$G74),1,0) -> 1 | S74: =IF(AND(S$12>=$G73,S$12<=$G74),1,0) -> 1 | T74: =IF(AND(T$12>=$G73,T$12<=$G74),1,0) -> 0 | U74: =IF(AND(U$12>=$G73,U$12<=$G74),1,0) -> 0 | ... KI74: =IF(AND(KI$12>=$G73,KI$12<=$G74),1,0) -> 0
G75: =EOMONTH(G74,1) -> 46418 | H75: 1/0 Flag | M75: Repayment Date | N75: =IF(AND(N$11<=$G75,N$12>=$G75),1,0) -> 0 | O75: =IF(AND(O$11<=$G75,O$12>=$G75),1,0) -> 0 | P75: =IF(AND(P$11<=$G75,P$12>=$G75),1,0) -> 0 | Q75: =IF(AND(Q$11<=$G75,Q$12>=$G75),1,0) -> 0 | R75: =IF(AND(R$11<=$G75,R$12>=$G75),1,0) -> 0 | S75: =IF(AND(S$11<=$G75,S$12>=$G75),1,0) -> 0 | T75: =IF(AND(T$11<=$G75,T$12>=$G75),1,0) -> 1 | U75: =IF(AND(U$11<=$G75,U$12>=$G75),1,0) -> 0 | ... KI75: =IF(AND(KI$11<=$G75,KI$12>=$G75),1,0) -> 0
H76: # | M76: Facility Month Counter | N76: =IF(N74=1,YEARFRAC($G73,N$12)*12,0) -> 22 | O76: =IF(O74=1,YEARFRAC($G73,O$12)*12,0) -> 23 | P76: =IF(P74=1,YEARFRAC($G73,P$12)*12,0) -> 24 | Q76: =IF(Q74=1,YEARFRAC($G73,Q$12)*12,0) -> 25 | R76: =IF(R74=1,YEARFRAC($G73,R$12)*12,0) -> 26 | S76: =IF(S74=1,YEARFRAC($G73,S$12)*12,0) -> 27 | T76: =IF(T74=1,YEARFRAC($G73,T$12)*12,0) -> 0 | U76: =IF(U74=1,YEARFRAC($G73,U$12)*12,0) -> 0 | ... KI76: =IF(KI74=1,YEARFRAC($G73,KI$12)*12,0) -> 0
H77: 1/0 Flag | M77: Pay Interest Flag | N77: =IF(MOD(MONTH(N$12),6)=0,1,0) -> 0 | O77: =IF(MOD(MONTH(O$12),6)=0,1,0) -> 0 | P77: =IF(MOD(MONTH(P$12),6)=0,1,0) -> 0 | Q77: =IF(MOD(MONTH(Q$12),6)=0,1,0) -> 0 | R77: =IF(MOD(MONTH(R$12),6)=0,1,0) -> 0 | S77: =IF(MOD(MONTH(S$12),6)=0,1,0) -> 1 | T77: =IF(MOD(MONTH(T$12),6)=0,1,0) -> 0 | U77: =IF(MOD(MONTH(U$12),6)=0,1,0) -> 0 | ... KI77: =IF(MOD(MONTH(KI$12),6)=0,1,0) -> 1
L79: Facility balance
H80: USDm | M80: Opening Balance | N80: =Control!H44 -> 245 | O80: =N83 -> 245 | P80: =O83 -> 245 | Q80: =P83 -> 245 | R80: =Q83 -> 245 | S80: =R83 -> 245 | T80: =S83 -> 210 | U80: =T83 -> 0 | V80: =U83 -> 0 | ... KI80: =KH83 -> 0
H81: USDm | M81: Principal Amortisation | N81: =-IFERROR(INDEX(Control!$H$53:$H$62,MATCH(N76,Control!$G$53:$G$62,0)),0) -> 0 | O81: =-IFERROR(INDEX(Control!$H$53:$H$62,MATCH(O76,Control!$G$53:$G$62,0)),0) -> 0 | P81: =-IFERROR(INDEX(Control!$H$53:$H$62,MATCH(P76,Control!$G$53:$G$62,0)),0) -> 0 | Q81: =-IFERROR(INDEX(Control!$H$53:$H$62,MATCH(Q76,Control!$G$53:$G$62,0)),0) -> 0 | R81: =-IFERROR(INDEX(Control!$H$53:$H$62,MATCH(R76,Control!$G$53:$G$62,0)),0) -> 0 | S81: =-IFERROR(INDEX(Control!$H$53:$H$62,MATCH(S76,Control!$G$53:$G$62,0)),0) -> -35 | T81: =-IFERROR(INDEX(Control!$H$53:$H$62,MATCH(T76,Control!$G$53:$G$62,0)),0) -> 0 | U81: =-IFERROR(INDEX(Control!$H$53:$H$62,MATCH(U76,Control!$G$53:$G$62,0)),0) -> 0 | ... KI81: =-IFERROR(INDEX(Control!$H$53:$H$62,MATCH(KI76,Control!$G$53:$G$62,0)),0) -> 0
H82: USDm | M82: Repayment | N82: =IF(N75,-N80,0) -> 0 | O82: =IF(O75,-O80,0) -> 0 | P82: =IF(P75,-P80,0) -> 0 | Q82: =IF(Q75,-Q80,0) -> 0 | R82: =IF(R75,-R80,0) -> 0 | S82: =IF(S75,-S80,0) -> 0 | T82: =IF(T75,-T80,0) -> -210 | U82: =IF(U75,-U80,0) -> 0 | ... KI82: =IF(KI75,-KI80,0) -> 0
H83: USDm | M83: Closing Balance | N83: =SUM(N80:N82) -> 245 | O83: =SUM(O80:O82) -> 245 | P83: =SUM(P80:P82) -> 245 | Q83: =SUM(Q80:Q82) -> 245 | R83: =SUM(R80:R82) -> 245 | S83: =SUM(S80:S82) -> 210 | T83: =SUM(T80:T82) -> 0 | U83: =SUM(U80:U82) -> 0 | ... KI83: =SUM(KI80:KI82) -> 0
L85: Interest
H86: % pa | M86: SOFR | N86: =Inputs!K$135 -> 0.035 | O86: =Inputs!L$135 -> 0.035 | P86: =Inputs!M$135 -> 0.035 | Q86: =Inputs!N$135 -> 0.035 | R86: =Inputs!O$135 -> 0.035 | S86: =Inputs!P$135 -> 0.035 | T86: =Inputs!Q$135 -> 0.035 | U86: =Inputs!R$135 -> 0.035 | ... KI86: =Inputs!KF$135 -> 0.035
G87: =Control!H43 -> 0.045 | H87: % pa | M87: Margin | N87: =$G87*N74 -> 0.045 | O87: =$G87*O74 -> 0.045 | P87: =$G87*P74 -> 0.045 | Q87: =$G87*Q74 -> 0.045 | R87: =$G87*R74 -> 0.045 | S87: =$G87*S74 -> 0.045 | T87: =$G87*T74 -> 0 | U87: =$G87*U74 -> 0 | ... KI87: =$G87*KI74 -> 0
H88: % pa | M88: All-in interest rate | N88: =SUM(N86:N87)*N74 -> 0.08 | O88: =SUM(O86:O87)*O74 -> 0.08 | P88: =SUM(P86:P87)*P74 -> 0.08 | Q88: =SUM(Q86:Q87)*Q74 -> 0.08 | R88: =SUM(R86:R87)*R74 -> 0.08 | S88: =SUM(S86:S87)*S74 -> 0.08 | T88: =SUM(T86:T87)*T74 -> 0 | U88: =SUM(U86:U87)*U74 -> 0 | ... KI88: =SUM(KI86:KI87)*KI74 -> 0
L90: Interest Payments
H91: USDm | M91: Interest accrued | N91: =-N74*((N$12-N$11+1)/360)*N88*N80 -> -1.6877778 | O91: =-O74*((O$12-O$11+1)/360)*O88*O80 -> -1.6877778 | P91: =-P74*((P$12-P$11+1)/360)*P88*P80 -> -1.6333333 | Q91: =-Q74*((Q$12-Q$11+1)/360)*Q88*Q80 -> -1.6877778 | R91: =-R74*((R$12-R$11+1)/360)*R88*R80 -> -1.6333333 | S91: =-S74*((S$12-S$11+1)/360)*S88*S80 -> -1.6877778 | T91: =-T74*((T$12-T$11+1)/360)*T88*T80 -> 0 | U91: =-U74*((U$12-U$11+1)/360)*U88*U80 -> 0 | ... KI91: =-KI74*((KI$12-KI$11+1)/360)*KI88*KI80 -> 0
H92: USDm | M92: Interest Paid | O92: =IF(O75=1,SUM($N91:O91)-SUM($N92:N92),O74*O77*(SUM($N91:O91)-SUM($N92:N92))) -> 0 | P92: =IF(P75=1,SUM($N91:P91)-SUM($N92:O92),P74*P77*(SUM($N91:P91)-SUM($N92:O92))) -> 0 | Q92: =IF(Q75=1,SUM($N91:Q91)-SUM($N92:P92),Q74*Q77*(SUM($N91:Q91)-SUM($N92:P92))) -> 0 | R92: =IF(R75=1,SUM($N91:R91)-SUM($N92:Q92),R74*R77*(SUM($N91:R91)-SUM($N92:Q92))) -> 0 | S92: =IF(S75=1,SUM($N91:S91)-SUM($N92:R92),S74*S77*(SUM($N91:S91)-SUM($N92:R92))) -> -10.017778 | T92: =IF(T75=1,SUM($N91:T91)-SUM($N92:S92),T74*T77*(SUM($N91:T91)-SUM($N92:S92))) -> 0 | U92: =IF(U75=1,SUM($N91:U91)-SUM($N92:T92),U74*U77*(SUM($N91:U91)-SUM($N92:T92))) -> 0 | V92: =IF(V75=1,SUM($N91:V91)-SUM($N92:U92),V74*V77*(SUM($N91:V91)-SUM($N92:U92))) -> 0 | ... KI92: =IF(KI75=1,SUM($N91:KI91)-SUM($N92:KH92),KI74*KI77*(SUM($N91:KI91)-SUM($N92:KH92))) -> 0
L94: Amortisation of establishment fee
H95: USDm | M95: Opening Balance | N95: =Control!H46 -> 2.5 | O95: =N97 -> 2.3833333 | P95: =O97 -> 2.2666667 | Q95: =P97 -> 2.15 | R95: =Q97 -> 2.0333333 | S95: =R97 -> 1.9166667 | T95: =S97 -> 0 | U95: =T97 -> 0 | V95: =U97 -> 0 | ... KI95: =KH97 -> 0
G96: =Control!H49 -> 0.11666667 | H96: USDm | M96: Amortisation | N96: =-IF(O75=1,N95,N74*$G96) -> -0.11666667 | O96: =-IF(P75=1,O95,O74*$G96) -> -0.11666667 | P96: =-IF(Q75=1,P95,P74*$G96) -> -0.11666667 | Q96: =-IF(R75=1,Q95,Q74*$G96) -> -0.11666667 | R96: =-IF(S75=1,R95,R74*$G96) -> -0.11666667 | S96: =-IF(T75=1,S95,S74*$G96) -> -1.9166667 | T96: =-IF(U75=1,T95,T74*$G96) -> 0 | U96: =-IF(V75=1,U95,U74*$G96) -> 0 | ... KI96: =-IF(KJ75=1,KI95,KI74*$G96) -> 0
H97: USDm | M97: Closing Balance | N97: =SUM(N95:N96) -> 2.3833333 | O97: =SUM(O95:O96) -> 2.2666667 | P97: =SUM(P95:P96) -> 2.15 | Q97: =SUM(Q95:Q96) -> 2.0333333 | R97: =SUM(R95:R96) -> 1.9166667 | S97: =SUM(S95:S96) -> 0 | T97: =SUM(T95:T96) -> 0 | U97: =SUM(U95:U96) -> 0 | ... KI97: =SUM(KI95:KI96) -> 0
K99: New Facility
L101: Facility Flags
G102: =Control!J65 -> 46418 | H102: 1/0 Flag | M102: Establishment Flag | N102: =IF(AND($G102>=N$11,$G102<=N$12),1,0) -> 0 | O102: =IF(AND($G102>=O$11,$G102<=O$12),1,0) -> 0 | P102: =IF(AND($G102>=P$11,$G102<=P$12),1,0) -> 0 | Q102: =IF(AND($G102>=Q$11,$G102<=Q$12),1,0) -> 0 | R102: =IF(AND($G102>=R$11,$G102<=R$12),1,0) -> 0 | S102: =IF(AND($G102>=S$11,$G102<=S$12),1,0) -> 0 | T102: =IF(AND($G102>=T$11,$G102<=T$12),1,0) -> 1 | U102: =IF(AND($G102>=U$11,$G102<=U$12),1,0) -> 0 | ... KI102: =IF(AND($G102>=KI$11,$G102<=KI$12),1,0) -> 0
G103: =Control!J67 -> 48213 | H103: 1/0 Flag | M103: Facility Active | N103: =IF(AND(N$12>=$G102,N$12<=$G103),1,0) -> 0 | O103: =IF(AND(O$12>=$G102,O$12<=$G103),1,0) -> 0 | P103: =IF(AND(P$12>=$G102,P$12<=$G103),1,0) -> 0 | Q103: =IF(AND(Q$12>=$G102,Q$12<=$G103),1,0) -> 0 | R103: =IF(AND(R$12>=$G102,R$12<=$G103),1,0) -> 0 | S103: =IF(AND(S$12>=$G102,S$12<=$G103),1,0) -> 0 | T103: =IF(AND(T$12>=$G102,T$12<=$G103),1,0) -> 1 | U103: =IF(AND(U$12>=$G102,U$12<=$G103),1,0) -> 1 | ... KI103: =IF(AND(KI$12>=$G102,KI$12<=$G103),1,0) -> 0
G104: =Control!H67 -> 48213 | H104: 1/0 Flag | M104: Repayment Date | N104: =IF(AND(N$11<=$G104,N$12>=$G104),1,0) -> 0 | O104: =IF(AND(O$11<=$G104,O$12>=$G104),1,0) -> 0 | P104: =IF(AND(P$11<=$G104,P$12>=$G104),1,0) -> 0 | Q104: =IF(AND(Q$11<=$G104,Q$12>=$G104),1,0) -> 0 | R104: =IF(AND(R$11<=$G104,R$12>=$G104),1,0) -> 0 | S104: =IF(AND(S$11<=$G104,S$12>=$G104),1,0) -> 0 | T104: =IF(AND(T$11<=$G104,T$12>=$G104),1,0) -> 0 | U104: =IF(AND(U$11<=$G104,U$12>=$G104),1,0) -> 0 | ... KI104: =IF(AND(KI$11<=$G104,KI$12>=$G104),1,0) -> 0
H105: # | M105: Facility Month Counter | N105: =IF(N103=1,YEARFRAC($G102,N$12)*12+1,0) -> 0 | O105: =IF(O103=1,YEARFRAC($G102,O$12)*12+1,0) -> 0 | P105: =IF(P103=1,YEARFRAC($G102,P$12)*12+1,0) -> 0 | Q105: =IF(Q103=1,YEARFRAC($G102,Q$12)*12+1,0) -> 0 | R105: =IF(R103=1,YEARFRAC($G102,R$12)*12+1,0) -> 0 | S105: =IF(S103=1,YEARFRAC($G102,S$12)*12+1,0) -> 0 | T105: =IF(T103=1,YEARFRAC($G102,T$12)*12+1,0) -> 1 | U105: =IF(U103=1,YEARFRAC($G102,U$12)*12+1,0) -> 1.9333333 | ... KI105: =IF(KI103=1,YEARFRAC($G102,KI$12)*12+1,0) -> 0
H106: 1/0 Flag | M106: Pay Interest Flag | N106: =IF(MOD(MONTH(N$12),6)=0,1,0) -> 0 | O106: =IF(MOD(MONTH(O$12),6)=0,1,0) -> 0 | P106: =IF(MOD(MONTH(P$12),6)=0,1,0) -> 0 | Q106: =IF(MOD(MONTH(Q$12),6)=0,1,0) -> 0 | R106: =IF(MOD(MONTH(R$12),6)=0,1,0) -> 0 | S106: =IF(MOD(MONTH(S$12),6)=0,1,0) -> 1 | T106: =IF(MOD(MONTH(T$12),6)=0,1,0) -> 0 | U106: =IF(MOD(MONTH(U$12),6)=0,1,0) -> 0 | ... KI106: =IF(MOD(MONTH(KI$12),6)=0,1,0) -> 1
L108: Facility balance
H109: USDm | M109: Opening Balance | N109: =0 -> 0 | O109: =N113 -> 0 | P109: =O113 -> 0 | Q109: =P113 -> 0 | R109: =Q113 -> 0 | S109: =R113 -> 0 | T109: =S113 -> 0 | U109: =T113 -> 250 | V109: =U113 -> 250 | ... KI109: =KH113 -> 0
G110: =Control!H66 -> 250 | H110: USDm | M110: Drawdown | N110: =$G110*N102 -> 0 | O110: =$G110*O102 -> 0 | P110: =$G110*P102 -> 0 | Q110: =$G110*Q102 -> 0 | R110: =$G110*R102 -> 0 | S110: =$G110*S102 -> 0 | T110: =$G110*T102 -> 250 | U110: =$G110*U102 -> 0 | ... KI110: =$G110*KI102 -> 0
H111: USDm | M111: Principal Amortisation | N111: =-IFERROR(INDEX(Control!$H$81:$H$90,MATCH(N105,Control!$G$81:$G$90,0)),0) -> 0 | O111: =-IFERROR(INDEX(Control!$H$81:$H$90,MATCH(O105,Control!$G$81:$G$90,0)),0) -> 0 | P111: =-IFERROR(INDEX(Control!$H$81:$H$90,MATCH(P105,Control!$G$81:$G$90,0)),0) -> 0 | Q111: =-IFERROR(INDEX(Control!$H$81:$H$90,MATCH(Q105,Control!$G$81:$G$90,0)),0) -> 0 | R111: =-IFERROR(INDEX(Control!$H$81:$H$90,MATCH(R105,Control!$G$81:$G$90,0)),0) -> 0 | S111: =-IFERROR(INDEX(Control!$H$81:$H$90,MATCH(S105,Control!$G$81:$G$90,0)),0) -> 0 | T111: =-IFERROR(INDEX(Control!$H$81:$H$90,MATCH(T105,Control!$G$81:$G$90,0)),0) -> 0 | U111: =-IFERROR(INDEX(Control!$H$81:$H$90,MATCH(U105,Control!$G$81:$G$90,0)),0) -> 0 | ... KI111: =-IFERROR(INDEX(Control!$H$81:$H$90,MATCH(KI105,Control!$G$81:$G$90,0)),0) -> 0
H112: USDm | M112: Repayment | N112: =IF(N104,-N109-N111,0) -> 0 | O112: =IF(O104,-O109-O111,0) -> 0 | P112: =IF(P104,-P109-P111,0) -> 0 | Q112: =IF(Q104,-Q109-Q111,0) -> 0 | R112: =IF(R104,-R109-R111,0) -> 0 | S112: =IF(S104,-S109-S111,0) -> 0 | T112: =IF(T104,-T109-T111,0) -> 0 | U112: =IF(U104,-U109-U111,0) -> 0 | ... KI112: =IF(KI104,-KI109-KI111,0) -> 0
H113: USDm | M113: Closing Balance | N113: =SUM(N109:N112) -> 0 | O113: =SUM(O109:O112) -> 0 | P113: =SUM(P109:P112) -> 0 | Q113: =SUM(Q109:Q112) -> 0 | R113: =SUM(R109:R112) -> 0 | S113: =SUM(S109:S112) -> 0 | T113: =SUM(T109:T112) -> 250 | U113: =SUM(U109:U112) -> 250 | ... KI113: =SUM(KI109:KI112) -> 0
L115: Interest
H116: % pa | M116: SOFR | N116: =Inputs!K$135 -> 0.035 | O116: =Inputs!L$135 -> 0.035 | P116: =Inputs!M$135 -> 0.035 | Q116: =Inputs!N$135 -> 0.035 | R116: =Inputs!O$135 -> 0.035 | S116: =Inputs!P$135 -> 0.035 | T116: =Inputs!Q$135 -> 0.035 | U116: =Inputs!R$135 -> 0.035 | ... KI116: =Inputs!KF$135 -> 0.035
G117: =Control!H69 -> 0.0375 | H117: % pa | M117: Margin | N117: =$G117*N103 -> 0 | O117: =$G117*O103 -> 0 | P117: =$G117*P103 -> 0 | Q117: =$G117*Q103 -> 0 | R117: =$G117*R103 -> 0 | S117: =$G117*S103 -> 0 | T117: =$G117*T103 -> 0.0375 | U117: =$G117*U103 -> 0.0375 | ... KI117: =$G117*KI103 -> 0
H118: % pa | M118: All-in interest rate | N118: =SUM(N116:N117)*N103 -> 0 | O118: =SUM(O116:O117)*O103 -> 0 | P118: =SUM(P116:P117)*P103 -> 0 | Q118: =SUM(Q116:Q117)*Q103 -> 0 | R118: =SUM(R116:R117)*R103 -> 0 | S118: =SUM(S116:S117)*S103 -> 0 | T118: =SUM(T116:T117)*T103 -> 0.0725 | U118: =SUM(U116:U117)*U103 -> 0.0725 | ... KI118: =SUM(KI116:KI117)*KI103 -> 0
L120: Interest Payments
H121: USDm | M121: Interest accrued | N121: =-N103*((N$12-N$11+1)/360)*N118*N109 -> 0 | O121: =-O103*((O$12-O$11+1)/360)*O118*O109 -> 0 | P121: =-P103*((P$12-P$11+1)/360)*P118*P109 -> 0 | Q121: =-Q103*((Q$12-Q$11+1)/360)*Q118*Q109 -> 0 | R121: =-R103*((R$12-R$11+1)/360)*R118*R109 -> 0 | S121: =-S103*((S$12-S$11+1)/360)*S118*S109 -> 0 | T121: =-T103*((T$12-T$11+1)/360)*T118*T109 -> 0 | U121: =-U103*((U$12-U$11+1)/360)*U118*U109 -> -1.4097222 | ... KI121: =-KI103*((KI$12-KI$11+1)/360)*KI118*KI109 -> 0
H122: USDm | M122: Interest Paid | O122: =IF(O104=1,SUM($N121:O121)-SUM($N122:N122),O103*O106*(SUM($N121:O121)-SUM($N122:N122))) -> 0 | P122: =IF(P104=1,SUM($N121:P121)-SUM($N122:O122),P103*P106*(SUM($N121:P121)-SUM($N122:O122))) -> 0 | Q122: =IF(Q104=1,SUM($N121:Q121)-SUM($N122:P122),Q103*Q106*(SUM($N121:Q121)-SUM($N122:P122))) -> 0 | R122: =IF(R104=1,SUM($N121:R121)-SUM($N122:Q122),R103*R106*(SUM($N121:R121)-SUM($N122:Q122))) -> 0 | S122: =IF(S104=1,SUM($N121:S121)-SUM($N122:R122),S103*S106*(SUM($N121:S121)-SUM($N122:R122))) -> 0 | T122: =IF(T104=1,SUM($N121:T121)-SUM($N122:S122),T103*T106*(SUM($N121:T121)-SUM($N122:S122))) -> 0 | U122: =IF(U104=1,SUM($N121:U121)-SUM($N122:T122),U103*U106*(SUM($N121:U121)-SUM($N122:T122))) -> 0 | V122: =IF(V104=1,SUM($N121:V121)-SUM($N122:U122),V103*V106*(SUM($N121:V121)-SUM($N122:U122))) -> 0 | ... KI122: =IF(KI104=1,SUM($N121:KI121)-SUM($N122:KH122),KI103*KI106*(SUM($N121:KI121)-SUM($N122:KH122))) -> 0
L124: Amortisation of establishment fee
G125: =Control!H73 -> 1.25 | H125: USDm | M125: Opening Balance | N125: =0 -> 0 | O125: =IF(O102=1,$G125,N127) -> 0 | P125: =IF(P102=1,$G125,O127) -> 0 | Q125: =IF(Q102=1,$G125,P127) -> 0 | R125: =IF(R102=1,$G125,Q127) -> 0 | S125: =IF(S102=1,$G125,R127) -> 0 | T125: =IF(T102=1,$G125,S127) -> 1.25 | U125: =IF(U102=1,$G125,T127) -> 1.2291667 | V125: =IF(V102=1,$G125,U127) -> 1.2083333 | ... KI125: =IF(KI102=1,$G125,KH127) -> 0
G126: =Control!H74 -> 0.020833333 | H126: USDm | M126: Amortisation | N126: =-IF(AND(O104=0,N104=1),N125,$G126*N103) -> 0 | O126: =-IF(AND(P104=0,O104=1),O125,$G126*O103) -> 0 | P126: =-IF(AND(Q104=0,P104=1),P125,$G126*P103) -> 0 | Q126: =-IF(AND(R104=0,Q104=1),Q125,$G126*Q103) -> 0 | R126: =-IF(AND(S104=0,R104=1),R125,$G126*R103) -> 0 | S126: =-IF(AND(T104=0,S104=1),S125,$G126*S103) -> 0 | T126: =-IF(AND(U104=0,T104=1),T125,$G126*T103) -> -0.020833333 | U126: =-IF(AND(V104=0,U104=1),U125,$G126*U103) -> -0.020833333 | ... KI126: =-IF(AND(KJ104=0,KI104=1),KI125,$G126*KI103) -> 0
...

Sheet Inputs
B2: Metrics | G2: =Control!$D$2 -> Basic Financial Model
G3: =MID(CELL("filename",$A$1),FIND("]",CELL("filename",$A$1))+1,255) -> Inputs
G4: =Control!$D$4 -> Financial Scenario: Base Case
G5: Calendar Year | K5: =K13 -> CY26 | L5: =L13 -> CY26 | M5: =M13 -> CY26 | N5: =N13 -> CY26 | O5: =O13 -> CY26 | P5: =P13 -> CY26 | Q5: =Q13 -> CY27 | R5: =R13 -> CY27 | ... KF5: =KF13 -> CY49
G6: Financial Year | K6: =K14 -> FY27 | L6: =L14 -> FY27 | M6: =M14 -> FY27 | N6: =N14 -> FY27 | O6: =O14 -> FY27 | P6: =P14 -> FY27 | Q6: =Q14 -> FY27 | R6: =R14 -> FY27 | ... KF6: =KF14 -> FY50
D7: Ref | E7: Units | G7: Date | K7: =TEXT(K12,"mmm-yy") -> Jul-26 | L7: =TEXT(L12,"mmm-yy") -> Aug-26 | M7: =TEXT(M12,"mmm-yy") -> Sep-26 | N7: =TEXT(N12,"mmm-yy") -> Oct-26 | O7: =TEXT(O12,"mmm-yy") -> Nov-26 | P7: =TEXT(P12,"mmm-yy") -> Dec-26 | Q7: =TEXT(Q12,"mmm-yy") -> Jan-27 | R7: =TEXT(R12,"mmm-yy") -> Feb-27 | ... KF7: =TEXT(KF12,"mmm-yy") -> Dec-49
G9: Periods
E11: Date | J11: Start of period | K11: =DATE(2026,7,1) -> 46204 | L11: =K12+1 -> 46235 | M11: =L12+1 -> 46266 | N11: =M12+1 -> 46296 | O11: =N12+1 -> 46327 | P11: =O12+1 -> 46357 | Q11: =P12+1 -> 46388 | R11: =Q12+1 -> 46419 | S11: =R12+1 -> 46447 | ... KF11: =KE12+1 -> 54758
E12: Date | J12: End of period | K12: =EOMONTH(K11,0) -> 46234 | L12: =EOMONTH(L11,0) -> 46265 | M12: =EOMONTH(M11,0) -> 46295 | N12: =EOMONTH(N11,0) -> 46326 | O12: =EOMONTH(O11,0) -> 46356 | P12: =EOMONTH(P11,0) -> 46387 | Q12: =EOMONTH(Q11,0) -> 46418 | R12: =EOMONTH(R11,0) -> 46446 | ... KF12: =EOMONTH(KF11,0) -> 54788
E13: Date | J13: Calendar year | K13: ="CY"&RIGHT(YEAR(K11),2) -> CY26 | L13: ="CY"&RIGHT(YEAR(L11),2) -> CY26 | M13: ="CY"&RIGHT(YEAR(M11),2) -> CY26 | N13: ="CY"&RIGHT(YEAR(N11),2) -> CY26 | O13: ="CY"&RIGHT(YEAR(O11),2) -> CY26 | P13: ="CY"&RIGHT(YEAR(P11),2) -> CY26 | Q13: ="CY"&RIGHT(YEAR(Q11),2) -> CY27 | R13: ="CY"&RIGHT(YEAR(R11),2) -> CY27 | ... KF13: ="CY"&RIGHT(YEAR(KF11),2) -> CY49
J14: Financial Year | K14: ="FY"&IF(MONTH(K11)>6,RIGHT(YEAR(K11)+1,2),RIGHT(YEAR(K11),2)) -> FY27 | L14: ="FY"&IF(MONTH(L11)>6,RIGHT(YEAR(L11)+1,2),RIGHT(YEAR(L11),2)) -> FY27 | M14: ="FY"&IF(MONTH(M11)>6,RIGHT(YEAR(M11)+1,2),RIGHT(YEAR(M11),2)) -> FY27 | N14: ="FY"&IF(MONTH(N11)>6,RIGHT(YEAR(N11)+1,2),RIGHT(YEAR(N11),2)) -> FY27 | O14: ="FY"&IF(MONTH(O11)>6,RIGHT(YEAR(O11)+1,2),RIGHT(YEAR(O11),2)) -> FY27 | P14: ="FY"&IF(MONTH(P11)>6,RIGHT(YEAR(P11)+1,2),RIGHT(YEAR(P11),2)) -> FY27 | Q14: ="FY"&IF(MONTH(Q11)>6,RIGHT(YEAR(Q11)+1,2),RIGHT(YEAR(Q11),2)) -> FY27 | R14: ="FY"&IF(MONTH(R11)>6,RIGHT(YEAR(R11)+1,2),RIGHT(YEAR(R11),2)) -> FY27 | ... KF14: ="FY"&IF(MONTH(KF11)>6,RIGHT(YEAR(KF11)+1,2),RIGHT(YEAR(KF11),2)) -> FY50
J15: Days in Period | K15: =K12-K11+1 -> 31 | L15: =L12-L11+1 -> 31 | M15: =M12-M11+1 -> 30 | N15: =N12-N11+1 -> 31 | O15: =O12-O11+1 -> 30 | P15: =P12-P11+1 -> 31 | Q15: =Q12-Q11+1 -> 31 | R15: =R12-R11+1 -> 28 | ... KF15: =KF12-KF11+1 -> 31
J16: Inflation index
G18: Inputs
H20: Sales Volume
J22: Chosen case | K22: =Control!H17 -> 1 | L22: {=INDEX(J26:J34,K22)} -> Base case
E23: M Ltrs | J23: Live Price | K23: {=INDEX(K26:K34,$K$22)} -> 41.267535 | L23: {=INDEX(L26:L34,$K$22)} -> 37.692788 | M23: {=INDEX(M26:M34,$K$22)} -> 51.684718 | N23: {=INDEX(N26:N34,$K$22)} -> 74.186884 | O23: {=INDEX(O26:O34,$K$22)} -> 36.72564 | P23: {=INDEX(P26:P34,$K$22)} -> 33.919621 | Q23: {=INDEX(Q26:Q34,$K$22)} -> 43.157101 | R23: {=INDEX(R26:R34,$K$22)} -> 48.293767 | ... KF23: {=INDEX(KF26:KF34,$K$22)} -> 53.663819
D24: 0 | E24: M Ltrs | J24: Bank Adjustment | K24: =INT(K23*(1+$D24)) -> 41 | L24: =INT(L23*(1+$D24)) -> 37 | M24: =INT(M23*(1+$D24)) -> 51 | N24: =INT(N23*(1+$D24)) -> 74 | O24: =INT(O23*(1+$D24)) -> 36 | P24: =INT(P23*(1+$D24)) -> 33 | Q24: =INT(Q23*(1+$D24)) -> 43 | R24: =INT(R23*(1+$D24)) -> 48 | ... KF24: =INT(KF23*(1+$D24)) -> 53
E26: M Ltrs | J26: Base case | K26: 41.267535 | L26: 37.692788 | M26: 51.684718 | N26: 74.186884 | O26: 36.72564 | P26: 33.919621 | Q26: 43.157101 | R26: 48.293767 | S26: 82.842122 | T26: 85.141491 | U26: 71.974816 | V26: 58.511833 | W26: 25.548062 | X26: 79.8058 | Y26: 86.091436 | Z26: 84.709527 | AA26: 69.221061 | AB26: 46.350018 | AC26: 37.957816 | AD26: 64.726348 | AE26: 26.716842 | AF26: 65.34932 | AG26: 29.069379 | AH26: 62.161903 | AI26: 31.902974 | AJ26: 65.734663 | AK26: 63.315313 | AL26: 34.021791 | AM26: 37.781185 | AN26: 35.933026 | AO26: 26.220593 | AP26: 64.310952 | AQ26: 47.31235 | AR26: 52.920734 | AS26: 50.073917 | AT26: 68.161871 | AU26: 81.771783 | AV26: 59.10227 | AW26: 76.179941 | AX26: 64.269497 | AY26: 87.769886 | AZ26: 54.459037 | BA26: 26.065621 | BB26: 70.319737 | BC26: 94.036111 | BD26: 45.475474 | BE26: 61.246484 | BF26: 54.71625 | BG26: 76.004109 | BH26: 97.036793 | BI26: 68.863624 | BJ26: 38.708616 | BK26: 49.36803 | BL26: 56.301251 | BM26: 47.224234 | BN26: 63.6732 | BO26: 72.997663 | BP26: 36.284059 | BQ26: 35.060017 | BR26: 40.501291 | BS26: 42.77548 | BT26: 38.981665 | BU26: 46.281632 | BV26: 81.927311 | BW26: 62.651873 | BX26: 41.494072 | BY26: 49.205618 | BZ26: 40.966013 | CA26: 31.093627 | CB26: 31.353247 | CC26: 29.03934 | CD26: 64.615929 | CE26: 38.43109 | CF26: 53.284931 | CG26: 92.759735 | CH26: 63.836568 | CI26: 63.608659 | CJ26: 62.56472 | CK26: 71.347189 | CL26: 38.873669 | CM26: 76.797941 | CN26: 89.903081 | CO26: 99.399499 | CP26: 66.666319 | CQ26: 76.477056 | CR26: 89.835528 | CS26: 86.489739 | CT26: 30.07481 | CU26: 61.053672 | CV26: 38.391809 | CW26: 76.584208 | CX26: 41.478213 | CY26: 25.519086 | CZ26: 86.352193 | DA26: 25.814181 | DB26: 82.770244 | DC26: 88.902701 | DD26: 62.849927 | DE26: 49.212768 | DF26: 80.982709 | DG26: 89.298874 | DH26: 76.603988 | DI26: 57.812882 | DJ26: 54.369545 | DK26: 72.522673 | DL26: 91.387313 | DM26: 94.34808 | DN26: 75.32872 | DO26: 61.590533 | DP26: 99.6427 | DQ26: 65.027677 | DR26: 37.907065 | DS26: 39.525505 | DT26: 82.183479 | DU26: 98.105068 | DV26: 44.849063 | DW26: 51.008419 | DX26: 52.524385 | DY26: 86.484672 | DZ26: 76.226972 | EA26: 60.369899 | EB26: 79.338851 | EC26: 40.556774 | ED26: 40.006142 | EE26: 65.808272 | EF26: 44.556401 | EG26: 31.543556 | EH26: 42.77288 | EI26: 61.740802 | EJ26: 32.474627 | EK26: 70.649437 | EL26: 61.142257 | EM26: 29.112545 | EN26: 28.792697 | EO26: 65.961412 | EP26: 46.213953 | EQ26: 89.874837 | ER26: 92.000964 | ES26: 90.015899 | ET26: 99.865155 | EU26: 49.693905 | EV26: 68.017457 | EW26: 56.927484 | EX26: 94.067274 | EY26: 31.496048 | EZ26: 32.350435 | FA26: 95.86761 | FB26: 88.14795 | FC26: 81.179839 | FD26: 50.827843 | FE26: 33.579834 | FF26: 40.799418 | FG26: 85.095068 | FH26: 88.757737 | FI26: 32.040163 | FJ26: 71.762632 | FK26: 89.603477 | FL26: 60.765488 | FM26: 96.780579 | FN26: 67.445325 | FO26: 58.536753 | FP26: 85.726749 | FQ26: 96.097587 | FR26: 67.763909 | FS26: 79.819096 | FT26: 69.329578 | FU26: 93.662717 | FV26: 86.4452 | FW26: 53.983094 | FX26: 82.902259 | FY26: 57.388667 | FZ26: 40.461104 | GA26: 28.590955 | GB26: 26.189715 | GC26: 28.138762 | GD26: 86.566888 | GE26: 35.638775 | GF26: 69.607391 | GG26: 38.960087 | GH26: 51.331795 | GI26: 53.847541 | GJ26: 39.83709 | GK26: 79.415026 | GL26: 99.702032 | GM26: 73.415377 | GN26: 82.760584 | GO26: 41.657847 | GP26: 51.877893 | GQ26: 43.595592 | GR26: 51.101118 | GS26: 71.832679 | GT26: 45.956013 | GU26: 64.73087 | GV26: 34.100566 | GW26: 33.211781 | GX26: 46.349875 | GY26: 86.250661 | GZ26: 26.789723 | HA26: 82.862563 | HB26: 87.700206 | HC26: 77.664681 | HD26: 91.142253 | HE26: 78.450715 | HF26: 39.559559 | HG26: 79.271386 | HH26: 35.409256 | HI26: 93.405415 | HJ26: 85.33415 | HK26: 79.543604 | HL26: 79.848819 | HM26: 36.799473 | HN26: 86.051387 | HO26: 44.657523 | HP26: 29.685901 | HQ26: 93.760313 | HR26: 35.073019 | HS26: 98.404983 | HT26: 93.192137 | HU26: 66.971035 | HV26: 95.059449 | HW26: 29.619095 | HX26: 35.250953 | HY26: 58.982214 | HZ26: 43.363037 | IA26: 96.082357 | IB26: 56.714996 | IC26: 86.146774 | ID26: 48.200031 | IE26: 88.048431 | IF26: 72.480213 | IG26: 72.021685 | IH26: 44.927845 | II26: 70.956877 | IJ26: 75.235536 | IK26: 75.485499 | IL26: 91.928441 | IM26: 67.749736 | IN26: 50.85645 | IO26: 61.677234 | IP26: 51.723382 | IQ26: 57.350983 | IR26: 39.236485 | IS26: 65.320543 | IT26: 99.626969 | IU26: 56.203324 | IV26: 86.197107 | IW26: 60.262539 | IX26: 62.805097 | IY26: 30.982835 | IZ26: 85.040176 | JA26: 46.002324 | JB26: 46.681628 | JC26: 49.334346 | JD26: 99.420304 | JE26: 35.021947 | JF26: 87.747193 | JG26: 38.818884 | JH26: 33.721978 | JI26: 70.087283 | JJ26: 93.704641 | JK26: 30.170418 | JL26: 68.092881 | JM26: 25.537814 | JN26: 55.841261 | JO26: 90.965022 | JP26: 37.170169 | JQ26: 89.024833 | JR26: 87.380124 | JS26: 37.738203 | JT26: 88.817531 | JU26: 26.707503 | JV26: 88.610376 | JW26: 57.743227 | JX26: 33.042796 | JY26: 34.901572 | JZ26: 92.783007 | KA26: 95.375749 | KB26: 52.786535 | KC26: 85.086544 | KD26: 66.380424 | KE26: 44.464776 | KF26: 53.663819
E27: M Ltrs | J27: Lender case | K27: 55 | L27: 55 | M27: 55 | N27: 55 | O27: 55 | P27: 55 | Q27: 55 | R27: 55 | S27: 55 | T27: 55 | U27: 55 | V27: 55 | W27: 55 | X27: 55 | Y27: 55 | Z27: 55 | AA27: 55 | AB27: 55 | AC27: 55 | AD27: 55 | AE27: 55 | AF27: 55 | AG27: 55 | AH27: 55 | AI27: 55 | AJ27: 55 | AK27: 55 | AL27: 55 | AM27: 55 | AN27: 55 | AO27: 55 | AP27: 55 | AQ27: 55 | AR27: 55 | AS27: 55 | AT27: 55 | AU27: 55 | AV27: 55 | AW27: 55 | AX27: 55 | AY27: 55 | AZ27: 55 | BA27: 55 | BB27: 55 | BC27: 55 | BD27: 55 | BE27: 55 | BF27: 55 | BG27: 55 | BH27: 55 | BI27: 55 | BJ27: 55 | BK27: 55 | BL27: 55 | BM27: 55 | BN27: 55 | BO27: 55 | BP27: 55 | BQ27: 55 | BR27: 55 | BS27: 55 | BT27: 55 | BU27: 55 | BV27: 55 | BW27: 55 | BX27: 55 | BY27: 55 | BZ27: 55 | CA27: 55 | CB27: 55 | CC27: 55 | CD27: 55 | CE27: 55 | CF27: 55 | CG27: 55 | CH27: 55 | CI27: 55 | CJ27: 55 | CK27: 55 | CL27: 55 | CM27: 55 | CN27: 55 | CO27: 55 | CP27: 55 | CQ27: 55 | CR27: 55 | CS27: 55 | CT27: 55 | CU27: 55 | CV27: 55 | CW27: 55 | CX27: 55 | CY27: 55 | CZ27: 55 | DA27: 55 | DB27: 55 | DC27: 55 | DD27: 55 | DE27: 55 | DF27: 55 | DG27: 55 | DH27: 55 | DI27: 55 | DJ27: 55 | DK27: 55 | DL27: 55 | DM27: 55 | DN27: 55 | DO27: 55 | DP27: 55 | DQ27: 55 | DR27: 55 | DS27: 55 | DT27: 55 | DU27: 55 | DV27: 55 | DW27: 55 | DX27: 55 | DY27: 55 | DZ27: 55 | EA27: 55 | EB27: 55 | EC27: 55 | ED27: 55 | EE27: 55 | EF27: 55 | EG27: 55 | EH27: 55 | EI27: 55 | EJ27: 55 | EK27: 55 | EL27: 55 | EM27: 55 | EN27: 55 | EO27: 55 | EP27: 55 | EQ27: 55 | ER27: 55 | ES27: 55 | ET27: 55 | EU27: 55 | EV27: 55 | EW27: 55 | EX27: 55 | EY27: 55 | EZ27: 55 | FA27: 55 | FB27: 55 | FC27: 55 | FD27: 55 | FE27: 55 | FF27: 55 | FG27: 55 | FH27: 55 | FI27: 55 | FJ27: 55 | FK27: 55 | FL27: 55 | FM27: 55 | FN27: 55 | FO27: 55 | FP27: 55 | FQ27: 55 | FR27: 55 | FS27: 55 | FT27: 55 | FU27: 55 | FV27: 55 | FW27: 55 | FX27: 55 | FY27: 55 | FZ27: 55 | GA27: 55 | GB27: 55 | GC27: 55 | GD27: 55 | GE27: 55 | GF27: 55 | GG27: 55 | GH27: 55 | GI27: 55 | GJ27: 55 | GK27: 55 | GL27: 55 | GM27: 55 | GN27: 55 | GO27: 55 | GP27: 55 | GQ27: 55 | GR27: 55 | GS27: 55 | GT27: 55 | GU27: 55 | GV27: 55 | GW27: 55 | GX27: 55 | GY27: 55 | GZ27: 55 | HA27: 55 | HB27: 55 | HC27: 55 | HD27: 55 | HE27: 55 | HF27: 55 | HG27: 55 | HH27: 55 | HI27: 55 | HJ27: 55 | HK27: 55 | HL27: 55 | HM27: 55 | HN27: 55 | HO27: 55 | HP27: 55 | HQ27: 55 | HR27: 55 | HS27: 55 | HT27: 55 | HU27: 55 | HV27: 55 | HW27: 55 | HX27: 55 | HY27: 55 | HZ27: 55 | IA27: 55 | IB27: 55 | IC27: 55 | ID27: 55 | IE27: 55 | IF27: 55 | IG27: 55 | IH27: 55 | II27: 55 | IJ27: 55 | IK27: 55 | IL27: 55 | IM27: 55 | IN27: 55 | IO27: 55 | IP27: 55 | IQ27: 55 | IR27: 55 | IS27: 55 | IT27: 55 | IU27: 55 | IV27: 55 | IW27: 55 | IX27: 55 | IY27: 55 | IZ27: 55 | JA27: 55 | JB27: 55 | JC27: 55 | JD27: 55 | JE27: 55 | JF27: 55 | JG27: 55 | JH27: 55 | JI27: 55 | JJ27: 55 | JK27: 55 | JL27: 55 | JM27: 55 | JN27: 55 | JO27: 55 | JP27: 55 | JQ27: 55 | JR27: 55 | JS27: 55 | JT27: 55 | JU27: 55 | JV27: 55 | JW27: 55 | JX27: 55 | JY27: 55 | JZ27: 55 | KA27: 55 | KB27: 55 | KC27: 55 | KD27: 55 | KE27: 55 | KF27: 55
E28: M Ltrs | J28: Downside case | K28: 40 | L28: 40 | M28: 40 | N28: 40 | O28: 40 | P28: 40 | Q28: 40 | R28: 40 | S28: 40 | T28: 40 | U28: 40 | V28: 40 | W28: 40 | X28: 40 | Y28: 40 | Z28: 40 | AA28: 40 | AB28: 40 | AC28: 40 | AD28: 40 | AE28: 40 | AF28: 40 | AG28: 40 | AH28: 40 | AI28: 40 | AJ28: 40 | AK28: 40 | AL28: 40 | AM28: 40 | AN28: 40 | AO28: 40 | AP28: 40 | AQ28: 40 | AR28: 40 | AS28: 40 | AT28: 40 | AU28: 40 | AV28: 40 | AW28: 40 | AX28: 40 | AY28: 40 | AZ28: 40 | BA28: 40 | BB28: 40 | BC28: 40 | BD28: 40 | BE28: 40 | BF28: 40 | BG28: 40 | BH28: 40 | BI28: 40 | BJ28: 40 | BK28: 40 | BL28: 40 | BM28: 40 | BN28: 40 | BO28: 40 | BP28: 40 | BQ28: 40 | BR28: 40 | BS28: 40 | BT28: 40 | BU28: 40 | BV28: 40 | BW28: 40 | BX28: 40 | BY28: 40 | BZ28: 40 | CA28: 40 | CB28: 40 | CC28: 40 | CD28: 40 | CE28: 40 | CF28: 40 | CG28: 40 | CH28: 40 | CI28: 40 | CJ28: 40 | CK28: 40 | CL28: 40 | CM28: 40 | CN28: 40 | CO28: 40 | CP28: 40 | CQ28: 40 | CR28: 40 | CS28: 40 | CT28: 40 | CU28: 40 | CV28: 40 | CW28: 40 | CX28: 40 | CY28: 40 | CZ28: 40 | DA28: 40 | DB28: 40 | DC28: 40 | DD28: 40 | DE28: 40 | DF28: 40 | DG28: 40 | DH28: 40 | DI28: 40 | DJ28: 40 | DK28: 40 | DL28: 40 | DM28: 40 | DN28: 40 | DO28: 40 | DP28: 40 | DQ28: 40 | DR28: 40 | DS28: 40 | DT28: 40 | DU28: 40 | DV28: 40 | DW28: 40 | DX28: 40 | DY28: 40 | DZ28: 40 | EA28: 40 | EB28: 40 | EC28: 40 | ED28: 40 | EE28: 40 | EF28: 40 | EG28: 40 | EH28: 40 | EI28: 40 | EJ28: 40 | EK28: 40 | EL28: 40 | EM28: 40 | EN28: 40 | EO28: 40 | EP28: 40 | EQ28: 40 | ER28: 40 | ES28: 40 | ET28: 40 | EU28: 40 | EV28: 40 | EW28: 40 | EX28: 40 | EY28: 40 | EZ28: 40 | FA28: 40 | FB28: 40 | FC28: 40 | FD28: 40 | FE28: 40 | FF28: 40 | FG28: 40 | FH28: 40 | FI28: 40 | FJ28: 40 | FK28: 40 | FL28: 40 | FM28: 40 | FN28: 40 | FO28: 40 | FP28: 40 | FQ28: 40 | FR28: 40 | FS28: 40 | FT28: 40 | FU28: 40 | FV28: 40 | FW28: 40 | FX28: 40 | FY28: 40 | FZ28: 40 | GA28: 40 | GB28: 40 | GC28: 40 | GD28: 40 | GE28: 40 | GF28: 40 | GG28: 40 | GH28: 40 | GI28: 40 | GJ28: 40 | GK28: 40 | GL28: 40 | GM28: 40 | GN28: 40 | GO28: 40 | GP28: 40 | GQ28: 40 | GR28: 40 | GS28: 40 | GT28: 40 | GU28: 40 | GV28: 40 | GW28: 40 | GX28: 40 | GY28: 40 | GZ28: 40 | HA28: 40 | HB28: 40 | HC28: 40 | HD28: 40 | HE28: 40 | HF28: 40 | HG28: 40 | HH28: 40 | HI28: 40 | HJ28: 40 | HK28: 40 | HL28: 40 | HM28: 40 | HN28: 40 | HO28: 40 | HP28: 40 | HQ28: 40 | HR28: 40 | HS28: 40 | HT28: 40 | HU28: 40 | HV28: 40 | HW28: 40 | HX28: 40 | HY28: 40 | HZ28: 40 | IA28: 40 | IB28: 40 | IC28: 40 | ID28: 40 | IE28: 40 | IF28: 40 | IG28: 40 | IH28: 40 | II28: 40 | IJ28: 40 | IK28: 40 | IL28: 40 | IM28: 40 | IN28: 40 | IO28: 40 | IP28: 40 | IQ28: 40 | IR28: 40 | IS28: 40 | IT28: 40 | IU28: 40 | IV28: 40 | IW28: 40 | IX28: 40 | IY28: 40 | IZ28: 40 | JA28: 40 | JB28: 40 | JC28: 40 | JD28: 40 | JE28: 40 | JF28: 40 | JG28: 40 | JH28: 40 | JI28: 40 | JJ28: 40 | JK28: 40 | JL28: 40 | JM28: 40 | JN28: 40 | JO28: 40 | JP28: 40 | JQ28: 40 | JR28: 40 | JS28: 40 | JT28: 40 | JU28: 40 | JV28: 40 | JW28: 40 | JX28: 40 | JY28: 40 | JZ28: 40 | KA28: 40 | KB28: 40 | KC28: 40 | KD28: 40 | KE28: 40 | KF28: 40
E29: M Ltrs | J29: [Spare]
E30: M Ltrs | J30: [Spare]
E31: M Ltrs | J31: [Spare]
E32: M Ltrs | J32: [Spare]
E33: M Ltrs | J33: [Spare]
E34: M Ltrs | J34: [Spare]
H36: Sales Price
J38: Chosen case | K38: =Control!H18 -> 1 | L38: {=INDEX(J42:J50,K38)} -> Base case
E39: USD/Ltr, real | J39: Live Price | K39: {=INDEX(K42:K50,$K$38)} -> 2.35 | L39: {=INDEX(L42:L50,$K$38)} -> 2.35 | M39: {=INDEX(M42:M50,$K$38)} -> 2.35 | N39: {=INDEX(N42:N50,$K$38)} -> 2.35 | O39: {=INDEX(O42:O50,$K$38)} -> 2.35 | P39: {=INDEX(P42:P50,$K$38)} -> 2.35 | Q39: {=INDEX(Q42:Q50,$K$38)} -> 2.3 | R39: {=INDEX(R42:R50,$K$38)} -> 2.3 | ... KF39: {=INDEX(KF42:KF50,$K$38)} -> 2.25
D40: 0 | E40: USD/Ltr, real | J40: Bank Adjustment | K40: =K39*(1+$D40) -> 2.35 | L40: =L39*(1+$D40) -> 2.35 | M40: =M39*(1+$D40) -> 2.35 | N40: =N39*(1+$D40) -> 2.35 | O40: =O39*(1+$D40) -> 2.35 | P40: =P39*(1+$D40) -> 2.35 | Q40: =Q39*(1+$D40) -> 2.3 | R40: =R39*(1+$D40) -> 2.3 | ... KF40: =KF39*(1+$D40) -> 2.25
E42: USD/Ltr, real | J42: Base case | K42: 2.35 | L42: 2.35 | M42: 2.35 | N42: 2.35 | O42: 2.35 | P42: 2.35 | Q42: 2.3 | R42: 2.3 | S42: 2.3 | T42: 2.3 | U42: 2.3 | V42: 2.3 | W42: 2.3 | X42: 2.3 | Y42: 2.25 | Z42: 2.25 | AA42: 2.25 | AB42: 2.25 | AC42: 2.25 | AD42: 2.25 | AE42: 2.25 | AF42: 2.25 | AG42: 2.25 | AH42: 2.25 | AI42: 2.25 | AJ42: 2.25 | AK42: 2.25 | AL42: 2.25 | AM42: 2.25 | AN42: 2.25 | AO42: 2.25 | AP42: 2.25 | AQ42: 2.25 | AR42: 2.25 | AS42: 2.25 | AT42: 2.25 | AU42: 2.25 | AV42: 2.25 | AW42: 2.25 | AX42: 2.25 | AY42: 2.25 | AZ42: 2.25 | BA42: 2.25 | BB42: 2.25 | BC42: 2.25 | BD42: 2.25 | BE42: 2.25 | BF42: 2.25 | BG42: 2.25 | BH42: 2.25 | BI42: 2.25 | BJ42: 2.25 | BK42: 2.25 | BL42: 2.25 | BM42: 2.25 | BN42: 2.25 | BO42: 2.25 | BP42: 2.25 | BQ42: 2.25 | BR42: 2.25 | BS42: 2.25 | BT42: 2.25 | BU42: 2.25 | BV42: 2.25 | BW42: 2.25 | BX42: 2.25 | BY42: 2.25 | BZ42: 2.25 | CA42: 2.25 | CB42: 2.25 | CC42: 2.25 | CD42: 2.25 | CE42: 2.25 | CF42: 2.25 | CG42: 2.25 | CH42: 2.25 | CI42: 2.25 | CJ42: 2.25 | CK42: 2.25 | CL42: 2.25 | CM42: 2.25 | CN42: 2.25 | CO42: 2.25 | CP42: 2.25 | CQ42: 2.25 | CR42: 2.25 | CS42: 2.25 | CT42: 2.25 | CU42: 2.25 | CV42: 2.25 | CW42: 2.25 | CX42: 2.25 | CY42: 2.25 | CZ42: 2.25 | DA42: 2.25 | DB42: 2.25 | DC42: 2.25 | DD42: 2.25 | DE42: 2.25 | DF42: 2.25 | DG42: 2.25 | DH42: 2.25 | DI42: 2.25 | DJ42: 2.25 | DK42: 2.25 | DL42: 2.25 | DM42: 2.25 | DN42: 2.25 | DO42: 2.25 | DP42: 2.25 | DQ42: 2.25 | DR42: 2.25 | DS42: 2.25 | DT42: 2.25 | DU42: 2.25 | DV42: 2.25 | DW42: 2.25 | DX42: 2.25 | DY42: 2.25 | DZ42: 2.25 | EA42: 2.25 | EB42: 2.25 | EC42: 2.25 | ED42: 2.25 | EE42: 2.25 | EF42: 2.25 | EG42: 2.25 | EH42: 2.25 | EI42: 2.25 | EJ42: 2.25 | EK42: 2.25 | EL42: 2.25 | EM42: 2.25 | EN42: 2.25 | EO42: 2.25 | EP42: 2.25 | EQ42: 2.25 | ER42: 2.25 | ES42: 2.25 | ET42: 2.25 | EU42: 2.25 | EV42: 2.25 | EW42: 2.25 | EX42: 2.25 | EY42: 2.25 | EZ42: 2.25 | FA42: 2.25 | FB42: 2.25 | FC42: 2.25 | FD42: 2.25 | FE42: 2.25 | FF42: 2.25 | FG42: 2.25 | FH42: 2.25 | FI42: 2.25 | FJ42: 2.25 | FK42: 2.25 | FL42: 2.25 | FM42: 2.25 | FN42: 2.25 | FO42: 2.25 | FP42: 2.25 | FQ42: 2.25 | FR42: 2.25 | FS42: 2.25 | FT42: 2.25 | FU42: 2.25 | FV42: 2.25 | FW42: 2.25 | FX42: 2.25 | FY42: 2.25 | FZ42: 2.25 | GA42: 2.25 | GB42: 2.25 | GC42: 2.25 | GD42: 2.25 | GE42: 2.25 | GF42: 2.25 | GG42: 2.25 | GH42: 2.25 | GI42: 2.25 | GJ42: 2.25 | GK42: 2.25 | GL42: 2.25 | GM42: 2.25 | GN42: 2.25 | GO42: 2.25 | GP42: 2.25 | GQ42: 2.25 | GR42: 2.25 | GS42: 2.25 | GT42: 2.25 | GU42: 2.25 | GV42: 2.25 | GW42: 2.25 | GX42: 2.25 | GY42: 2.25 | GZ42: 2.25 | HA42: 2.25 | HB42: 2.25 | HC42: 2.25 | HD42: 2.25 | HE42: 2.25 | HF42: 2.25 | HG42: 2.25 | HH42: 2.25 | HI42: 2.25 | HJ42: 2.25 | HK42: 2.25 | HL42: 2.25 | HM42: 2.25 | HN42: 2.25 | HO42: 2.25 | HP42: 2.25 | HQ42: 2.25 | HR42: 2.25 | HS42: 2.25 | HT42: 2.25 | HU42: 2.25 | HV42: 2.25 | HW42: 2.25 | HX42: 2.25 | HY42: 2.25 | HZ42: 2.25 | IA42: 2.25 | IB42: 2.25 | IC42: 2.25 | ID42: 2.25 | IE42: 2.25 | IF42: 2.25 | IG42: 2.25 | IH42: 2.25 | II42: 2.25 | IJ42: 2.25 | IK42: 2.25 | IL42: 2.25 | IM42: 2.25 | IN42: 2.25 | IO42: 2.25 | IP42: 2.25 | IQ42: 2.25 | IR42: 2.25 | IS42: 2.25 | IT42: 2.25 | IU42: 2.25 | IV42: 2.25 | IW42: 2.25 | IX42: 2.25 | IY42: 2.25 | IZ42: 2.25 | JA42: 2.25 | JB42: 2.25 | JC42: 2.25 | JD42: 2.25 | JE42: 2.25 | JF42: 2.25 | JG42: 2.25 | JH42: 2.25 | JI42: 2.25 | JJ42: 2.25 | JK42: 2.25 | JL42: 2.25 | JM42: 2.25 | JN42: 2.25 | JO42: 2.25 | JP42: 2.25 | JQ42: 2.25 | JR42: 2.25 | JS42: 2.25 | JT42: 2.25 | JU42: 2.25 | JV42: 2.25 | JW42: 2.25 | JX42: 2.25 | JY42: 2.25 | JZ42: 2.25 | KA42: 2.25 | KB42: 2.25 | KC42: 2.25 | KD42: 2.25 | KE42: 2.25 | KF42: 2.25
E43: USD/Ltr, real | J43: Lender case | K43: 2.3 | L43: 2.3 | M43: 2.3 | N43: 2.3 | O43: 2.3 | P43: 2.3 | Q43: 2.05 | R43: 2.05 | S43: 2.05 | T43: 2.05 | U43: 2.05 | V43: 2.05 | W43: 2.05 | X43: 2.05 | Y43: 2.05 | Z43: 2.05 | AA43: 2.05 | AB43: 2.05 | AC43: 2.05 | AD43: 2.05 | AE43: 2.05 | AF43: 2.05 | AG43: 2.05 | AH43: 2.05 | AI43: 2.05 | AJ43: 2.05 | AK43: 2.05 | AL43: 2.05 | AM43: 2.05 | AN43: 2.05 | AO43: 2.05 | AP43: 2.05 | AQ43: 2.05 | AR43: 2.05 | AS43: 2.05 | AT43: 2.05 | AU43: 2.05 | AV43: 2.05 | AW43: 2.05 | AX43: 2.05 | AY43: 2.05 | AZ43: 2.05 | BA43: 2.05 | BB43: 2.05 | BC43: 2.05 | BD43: 2.05 | BE43: 2.05 | BF43: 2.05 | BG43: 2.05 | BH43: 2.05 | BI43: 2.05 | BJ43: 2.05 | BK43: 2.05 | BL43: 2.05 | BM43: 2.05 | BN43: 2.05 | BO43: 2.05 | BP43: 2.05 | BQ43: 2.05 | BR43: 2.05 | BS43: 2.05 | BT43: 2.05 | BU43: 2.05 | BV43: 2.05 | BW43: 2.05 | BX43: 2.05 | BY43: 2.05 | BZ43: 2.05 | CA43: 2.05 | CB43: 2.05 | CC43: 2.05 | CD43: 2.05 | CE43: 2.05 | CF43: 2.05 | CG43: 2.05 | CH43: 2.05 | CI43: 2.05 | CJ43: 2.05 | CK43: 2.05 | CL43: 2.05 | CM43: 2.05 | CN43: 2.05 | CO43: 2.05 | CP43: 2.05 | CQ43: 2.05 | CR43: 2.05 | CS43: 2.05 | CT43: 2.05 | CU43: 2.05 | CV43: 2.05 | CW43: 2.05 | CX43: 2.05 | CY43: 2.05 | CZ43: 2.05 | DA43: 2.05 | DB43: 2.05 | DC43: 2.05 | DD43: 2.05 | DE43: 2.05 | DF43: 2.05 | DG43: 2.05 | DH43: 2.05 | DI43: 2.05 | DJ43: 2.05 | DK43: 2.05 | DL43: 2.05 | DM43: 2.05 | DN43: 2.05 | DO43: 2.05 | DP43: 2.05 | DQ43: 2.05 | DR43: 2.05 | DS43: 2.05 | DT43: 2.05 | DU43: 2.05 | DV43: 2.05 | DW43: 2.05 | DX43: 2.05 | DY43: 2.05 | DZ43: 2.05 | EA43: 2.05 | EB43: 2.05 | EC43: 2.05 | ED43: 2.05 | EE43: 2.05 | EF43: 2.05 | EG43: 2.05 | EH43: 2.05 | EI43: 2.05 | EJ43: 2.05 | EK43: 2.05 | EL43: 2.05 | EM43: 2.05 | EN43: 2.05 | EO43: 2.05 | EP43: 2.05 | EQ43: 2.05 | ER43: 2.05 | ES43: 2.05 | ET43: 2.05 | EU43: 2.05 | EV43: 2.05 | EW43: 2.05 | EX43: 2.05 | EY43: 2.05 | EZ43: 2.05 | FA43: 2.05 | FB43: 2.05 | FC43: 2.05 | FD43: 2.05 | FE43: 2.05 | FF43: 2.05 | FG43: 2.05 | FH43: 2.05 | FI43: 2.05 | FJ43: 2.05 | FK43: 2.05 | FL43: 2.05 | FM43: 2.05 | FN43: 2.05 | FO43: 2.05 | FP43: 2.05 | FQ43: 2.05 | FR43: 2.05 | FS43: 2.05 | FT43: 2.05 | FU43: 2.05 | FV43: 2.05 | FW43: 2.05 | FX43: 2.05 | FY43: 2.05 | FZ43: 2.05 | GA43: 2.05 | GB43: 2.05 | GC43: 2.05 | GD43: 2.05 | GE43: 2.05 | GF43: 2.05 | GG43: 2.05 | GH43: 2.05 | GI43: 2.05 | GJ43: 2.05 | GK43: 2.05 | GL43: 2.05 | GM43: 2.05 | GN43: 2.05 | GO43: 2.05 | GP43: 2.05 | GQ43: 2.05 | GR43: 2.05 | GS43: 2.05 | GT43: 2.05 | GU43: 2.05 | GV43: 2.05 | GW43: 2.05 | GX43: 2.05 | GY43: 2.05 | GZ43: 2.05 | HA43: 2.05 | HB43: 2.05 | HC43: 2.05 | HD43: 2.05 | HE43: 2.05 | HF43: 2.05 | HG43: 2.05 | HH43: 2.05 | HI43: 2.05 | HJ43: 2.05 | HK43: 2.05 | HL43: 2.05 | HM43: 2.05 | HN43: 2.05 | HO43: 2.05 | HP43: 2.05 | HQ43: 2.05 | HR43: 2.05 | HS43: 2.05 | HT43: 2.05 | HU43: 2.05 | HV43: 2.05 | HW43: 2.05 | HX43: 2.05 | HY43: 2.05 | HZ43: 2.05 | IA43: 2.05 | IB43: 2.05 | IC43: 2.05 | ID43: 2.05 | IE43: 2.05 | IF43: 2.05 | IG43: 2.05 | IH43: 2.05 | II43: 2.05 | IJ43: 2.05 | IK43: 2.05 | IL43: 2.05 | IM43: 2.05 | IN43: 2.05 | IO43: 2.05 | IP43: 2.05 | IQ43: 2.05 | IR43: 2.05 | IS43: 2.05 | IT43: 2.05 | IU43: 2.05 | IV43: 2.05 | IW43: 2.05 | IX43: 2.05 | IY43: 2.05 | IZ43: 2.05 | JA43: 2.05 | JB43: 2.05 | JC43: 2.05 | JD43: 2.05 | JE43: 2.05 | JF43: 2.05 | JG43: 2.05 | JH43: 2.05 | JI43: 2.05 | JJ43: 2.05 | JK43: 2.05 | JL43: 2.05 | JM43: 2.05 | JN43: 2.05 | JO43: 2.05 | JP43: 2.05 | JQ43: 2.05 | JR43: 2.05 | JS43: 2.05 | JT43: 2.05 | JU43: 2.05 | JV43: 2.05 | JW43: 2.05 | JX43: 2.05 | JY43: 2.05 | JZ43: 2.05 | KA43: 2.05 | KB43: 2.05 | KC43: 2.05 | KD43: 2.05 | KE43: 2.05 | KF43: 2.05
E44: USD/Ltr, real | J44: Downside case | K44: 2.35 | L44: 2.32 | M44: 2.29 | N44: 2.26 | O44: 2.23 | P44: 2.2 | Q44: 2.17 | R44: 2.14 | S44: 2.11 | T44: 2.08 | U44: 2.05 | V44: 2.02 | W44: 2 | X44: 2 | Y44: 2 | Z44: 2 | AA44: 2 | AB44: 2 | AC44: 2 | AD44: 2 | AE44: 2 | AF44: 2 | AG44: 2 | AH44: 2 | AI44: 2 | AJ44: 2 | AK44: 2 | AL44: 2 | AM44: 2 | AN44: 2 | AO44: 2 | AP44: 2 | AQ44: 2 | AR44: 2 | AS44: 2 | AT44: 2 | AU44: 2 | AV44: 2 | AW44: 2 | AX44: 2 | AY44: 2 | AZ44: 2 | BA44: 2 | BB44: 2 | BC44: 2 | BD44: 2 | BE44: 2 | BF44: 2 | BG44: 2 | BH44: 2 | BI44: 2 | BJ44: 2 | BK44: 2 | BL44: 2 | BM44: 2 | BN44: 2 | BO44: 2 | BP44: 2 | BQ44: 2 | BR44: 2 | BS44: 2 | BT44: 2 | BU44: 2 | BV44: 2 | BW44: 2 | BX44: 2 | BY44: 2 | BZ44: 2 | CA44: 2 | CB44: 2 | CC44: 2 | CD44: 2 | CE44: 2 | CF44: 2 | CG44: 2 | CH44: 2 | CI44: 2 | CJ44: 2 | CK44: 2 | CL44: 2 | CM44: 2 | CN44: 2 | CO44: 2 | CP44: 2 | CQ44: 2 | CR44: 2 | CS44: 2 | CT44: 2 | CU44: 2 | CV44: 2 | CW44: 2 | CX44: 2 | CY44: 2 | CZ44: 2 | DA44: 2 | DB44: 2 | DC44: 2 | DD44: 2 | DE44: 2 | DF44: 2 | DG44: 2 | DH44: 2 | DI44: 2 | DJ44: 2 | DK44: 2 | DL44: 2 | DM44: 2 | DN44: 2 | DO44: 2 | DP44: 2 | DQ44: 2 | DR44: 2 | DS44: 2 | DT44: 2 | DU44: 2 | DV44: 2 | DW44: 2 | DX44: 2 | DY44: 2 | DZ44: 2 | EA44: 2 | EB44: 2 | EC44: 2 | ED44: 2 | EE44: 2 | EF44: 2 | EG44: 2 | EH44: 2 | EI44: 2 | EJ44: 2 | EK44: 2 | EL44: 2 | EM44: 2 | EN44: 2 | EO44: 2 | EP44: 2 | EQ44: 2 | ER44: 2 | ES44: 2 | ET44: 2 | EU44: 2 | EV44: 2 | EW44: 2 | EX44: 2 | EY44: 2 | EZ44: 2 | FA44: 2 | FB44: 2 | FC44: 2 | FD44: 2 | FE44: 2 | FF44: 2 | FG44: 2 | FH44: 2 | FI44: 2 | FJ44: 2 | FK44: 2 | FL44: 2 | FM44: 2 | FN44: 2 | FO44: 2 | FP44: 2 | FQ44: 2 | FR44: 2 | FS44: 2 | FT44: 2 | FU44: 2 | FV44: 2 | FW44: 2 | FX44: 2 | FY44: 2 | FZ44: 2 | GA44: 2 | GB44: 2 | GC44: 2 | GD44: 2 | GE44: 2 | GF44: 2 | GG44: 2 | GH44: 2 | GI44: 2 | GJ44: 2 | GK44: 2 | GL44: 2 | GM44: 2 | GN44: 2 | GO44: 2 | GP44: 2 | GQ44: 2 | GR44: 2 | GS44: 2 | GT44: 2 | GU44: 2 | GV44: 2 | GW44: 2 | GX44: 2 | GY44: 2 | GZ44: 2 | HA44: 2 | HB44: 2 | HC44: 2 | HD44: 2 | HE44: 2 | HF44: 2 | HG44: 2 | HH44: 2 | HI44: 2 | HJ44: 2 | HK44: 2 | HL44: 2 | HM44: 2 | HN44: 2 | HO44: 2 | HP44: 2 | HQ44: 2 | HR44: 2 | HS44: 2 | HT44: 2 | HU44: 2 | HV44: 2 | HW44: 2 | HX44: 2 | HY44: 2 | HZ44: 2 | IA44: 2 | IB44: 2 | IC44: 2 | ID44: 2 | IE44: 2 | IF44: 2 | IG44: 2 | IH44: 2 | II44: 2 | IJ44: 2 | IK44: 2 | IL44: 2 | IM44: 2 | IN44: 2 | IO44: 2 | IP44: 2 | IQ44: 2 | IR44: 2 | IS44: 2 | IT44: 2 | IU44: 2 | IV44: 2 | IW44: 2 | IX44: 2 | IY44: 2 | IZ44: 2 | JA44: 2 | JB44: 2 | JC44: 2 | JD44: 2 | JE44: 2 | JF44: 2 | JG44: 2 | JH44: 2 | JI44: 2 | JJ44: 2 | JK44: 2 | JL44: 2 | JM44: 2 | JN44: 2 | JO44: 2 | JP44: 2 | JQ44: 2 | JR44: 2 | JS44: 2 | JT44: 2 | JU44: 2 | JV44: 2 | JW44: 2 | JX44: 2 | JY44: 2 | JZ44: 2 | KA44: 2 | KB44: 2 | KC44: 2 | KD44: 2 | KE44: 2 | KF44: 2
E45: USD/Ltr, real | J45: [Spare]
E46: USD/Ltr, real | J46: [Spare]
E47: USD/Ltr, real | J47: [Spare]
E48: USD/Ltr, real | J48: [Spare]
E49: USD/Ltr, real | J49: [Spare]
E50: USD/Ltr, real | J50: [Spare]
H52: Unit Cost
J54: Chosen case | K54: =Control!H19 -> 1 | L54: {=INDEX(J58:J66,K54)} -> Base case
E55: USD/Ltr, real | J55: Live Price | K55: {=INDEX(K58:K66,$K$54)} -> -0.28887274 | L55: {=INDEX(L58:L66,$K$54)} -> -0.26384952 | M55: {=INDEX(M58:M66,$K$54)} -> -0.36179302 | N55: {=INDEX(N58:N66,$K$54)} -> -0.51930819 | O55: {=INDEX(O58:O66,$K$54)} -> -0.25707948 | P55: {=INDEX(P58:P66,$K$54)} -> -0.23743734 | Q55: {=INDEX(Q58:Q66,$K$54)} -> -0.30209971 | R55: {=INDEX(R58:R66,$K$54)} -> -0.33805637 | ... KF55: {=INDEX(KF58:KF66,$K$54)} -> -0.37564673
D56: 0 | E56: USD/Ltr, real | J56: Bank Adjustment | K56: =K55*(1+$D56) -> -0.28887274 | L56: =L55*(1+$D56) -> -0.26384952 | M56: =M55*(1+$D56) -> -0.36179302 | N56: =N55*(1+$D56) -> -0.51930819 | O56: =O55*(1+$D56) -> -0.25707948 | P56: =P55*(1+$D56) -> -0.23743734 | Q56: =Q55*(1+$D56) -> -0.30209971 | R56: =R55*(1+$D56) -> -0.33805637 | ... KF56: =KF55*(1+$D56) -> -0.37564673
E58: USD/Ltr, real | J58: Base case | K58: -0.28887274 | L58: -0.26384952 | M58: -0.36179302 | N58: -0.51930819 | O58: -0.25707948 | P58: -0.23743734 | Q58: -0.30209971 | R58: -0.33805637 | S58: -0.57989486 | T58: -0.59599044 | U58: -0.50382371 | V58: -0.40958283 | W58: -0.17883644 | X58: -0.5586406 | Y58: -0.60264005 | Z58: -0.59296669 | AA58: -0.48454743 | AB58: -0.32445013 | AC58: -0.26570471 | AD58: -0.45308444 | AE58: -0.1870179 | AF58: -0.45744524 | AG58: -0.20348565 | AH58: -0.43513332 | AI58: -0.22332082 | AJ58: -0.46014264 | AK58: -0.44320719 | AL58: -0.23815254 | AM58: -0.26446829 | AN58: -0.25153118 | AO58: -0.18354415 | AP58: -0.45017666 | AQ58: -0.33118645 | AR58: -0.37044514 | AS58: -0.35051742 | AT58: -0.4771331 | AU58: -0.57240248 | AV58: -0.41371589 | AW58: -0.53325959 | AX58: -0.44988648 | AY58: -0.6143892 | AZ58: -0.38121326 | BA58: -0.18245935 | BB58: -0.49223816 | BC58: -0.65825278 | BD58: -0.31832832 | BE58: -0.42872539 | BF58: -0.38301375 | BG58: -0.53202876 | BH58: -0.67925755 | BI58: -0.48204537 | BJ58: -0.27096031 | BK58: -0.34557621 | BL58: -0.39410876 | BM58: -0.33056964 | BN58: -0.4457124 | BO58: -0.51098364 | BP58: -0.25398842 | BQ58: -0.24542012 | BR58: -0.28350904 | BS58: -0.29942836 | BT58: -0.27287165 | BU58: -0.32397142 | BV58: -0.57349118 | BW58: -0.43856311 | BX58: -0.2904585 | BY58: -0.34443933 | BZ58: -0.28676209 | CA58: -0.21765539 | CB58: -0.21947273 | CC58: -0.20327538 | CD58: -0.4523115 | CE58: -0.26901763 | CF58: -0.37299452 | CG58: -0.64931815 | CH58: -0.44685597 | CI58: -0.44526061 | CJ58: -0.43795304 | CK58: -0.49943032 | CL58: -0.27211568 | CM58: -0.53758559 | CN58: -0.62932157 | CO58: -0.69579649 | CP58: -0.46666424 | CQ58: -0.53533939 | CR58: -0.6288487 | CS58: -0.60542817 | CT58: -0.21052367 | CU58: -0.42737571 | CV58: -0.26874267 | CW58: -0.53608945 | CX58: -0.29034749 | CY58: -0.1786336 | CZ58: -0.60446535 | DA58: -0.18069927 | DB58: -0.57939171 | DC58: -0.6223189 | DD58: -0.43994949 | DE58: -0.34448937 | DF58: -0.56687896 | DG58: -0.62509212 | DH58: -0.53622792 | DI58: -0.40469018 | DJ58: -0.38058681 | DK58: -0.50765871 | DL58: -0.63971119 | DM58: -0.66043656 | DN58: -0.52730104 | DO58: -0.43113373 | DP58: -0.6974989 | DQ58: -0.45519374 | DR58: -0.26534945 | DS58: -0.27667854 | DT58: -0.57528435 | DU58: -0.68673547 | DV58: -0.31394344 | DW58: -0.35705893 | DX58: -0.3676707 | DY58: -0.60539271 | DZ58: -0.53358881 | EA58: -0.42258929 | EB58: -0.55537196 | EC58: -0.28389742 | ED58: -0.280043 | EE58: -0.46065791 | EF58: -0.31189481 | EG58: -0.22080489 | EH58: -0.29941016 | EI58: -0.43218562 | EJ58: -0.22732239 | EK58: -0.49454606 | EL58: -0.4279958 | EM58: -0.20378781 | EN58: -0.20154888 | EO58: -0.46172989 | EP58: -0.32349767 | EQ58: -0.62912386 | ER58: -0.64400675 | ES58: -0.63011129 | ET58: -0.69905608 | EU58: -0.34785733 | EV58: -0.4761222 | EW58: -0.39849239 | EX58: -0.65847092 | EY58: -0.22047234 | EZ58: -0.22645304 | FA58: -0.67107327 | FB58: -0.61703565 | FC58: -0.56825887 | FD58: -0.3557949 | FE58: -0.23505884 | FF58: -0.28559592 | FG58: -0.59566548 | FH58: -0.62130416 | FI58: -0.22428114 | FJ58: -0.50233842 | FK58: -0.62722434 | FL58: -0.42535842 | FM58: -0.67746405 | FN58: -0.47211728 | FO58: -0.40975727 | FP58: -0.60008724 | FQ58: -0.67268311 | FR58: -0.47434736 | FS58: -0.55873367 | FT58: -0.48530704 | FU58: -0.65563902 | FV58: -0.6051164 | FW58: -0.37788166 | FX58: -0.58031581 | FY58: -0.40172067 | FZ58: -0.28322772 | GA58: -0.20013669 | GB58: -0.18332801 | GC58: -0.19697134 | GD58: -0.60596822 | GE58: -0.24947143 | GF58: -0.48725174 | GG58: -0.27272061 | GH58: -0.35932257 | GI58: -0.37693279 | GJ58: -0.27885963 | GK58: -0.55590518 | GL58: -0.69791422 | GM58: -0.51390764 | GN58: -0.57932409 | GO58: -0.29160493 | GP58: -0.36314525 | GQ58: -0.30516914 | GR58: -0.35770783 | GS58: -0.50282875 | GT58: -0.32169209 | GU58: -0.45311609 | GV58: -0.23870396 | GW58: -0.23248247 | GX58: -0.32444913 | GY58: -0.60375462 | GZ58: -0.18752806 | HA58: -0.58003794 | HB58: -0.61390145 | HC58: -0.54365277 | HD58: -0.63799577 | HE58: -0.54915501 | HF58: -0.27691691 | HG58: -0.5548997 | HH58: -0.24786479 | HI58: -0.65383791 | HJ58: -0.59733905 | HK58: -0.55680523 | HL58: -0.55894173 | HM58: -0.25759631 | HN58: -0.60235971 | HO58: -0.31260266 | HP58: -0.20780131 | HQ58: -0.65632219 | HR58: -0.24551113 | HS58: -0.68883488 | HT58: -0.65234496 | HU58: -0.46879724 | HV58: -0.66541615 | HW58: -0.20733366 | HX58: -0.24675667 | HY58: -0.4128755 | HZ58: -0.30354126 | IA58: -0.6725765 | IB58: -0.39700497 | IC58: -0.60302742 | ID58: -0.33740021 | IE58: -0.61633901 | IF58: -0.50736149 | IG58: -0.5041518 | IH58: -0.31449492 | II58: -0.49669814 | IJ58: -0.52664876 | IK58: -0.52839849 | IL58: -0.64349909 | IM58: -0.47424815 | IN58: -0.35599515 | IO58: -0.43174064 | IP58: -0.36206367 | IQ58: -0.40145688 | IR58: -0.2746554 | IS58: -0.4572438 | IT58: -0.69738879 | IU58: -0.39342327 | IV58: -0.60337975 | IW58: -0.42183777 | IX58: -0.43963568 | IY58: -0.21687984 | IZ58: -0.59528123 | JA58: -0.32201626 | JB58: -0.32677139 | JC58: -0.34534042 | JD58: -0.69594213 | JE58: -0.24515363 | JF58: -0.61423035 | JG58: -0.27173219 | JH58: -0.23605384 | JI58: -0.49061098 | JJ58: -0.65593249 | JK58: -0.21119292 | JL58: -0.47665017 | JM58: -0.1787647 | JN58: -0.39088883 | JO58: -0.63675515 | JP58: -0.26019119 | JQ58: -0.62317383 | JR58: -0.61166087 | JS58: -0.26416742 | JT58: -0.62172272 | JU58: -0.18695252 | JV58: -0.62027263 | JW58: -0.40420259 | JX58: -0.23129957 | JY58: -0.24431101 | JZ58: -0.64948105 | KA58: -0.66763024 | KB58: -0.36950575 | KC58: -0.59560581 | KD58: -0.46466297 | KE58: -0.31125343 | KF58: -0.37564673
E59: USD/Ltr, real | J59: Lender case | K59: -0.385 | L59: -0.385 | M59: -0.385 | N59: -0.385 | O59: -0.385 | P59: -0.385 | Q59: -0.385 | R59: -0.385 | S59: -0.385 | T59: -0.385 | U59: -0.385 | V59: -0.385 | W59: -0.385 | X59: -0.385 | Y59: -0.385 | Z59: -0.385 | AA59: -0.385 | AB59: -0.385 | AC59: -0.385 | AD59: -0.385 | AE59: -0.385 | AF59: -0.385 | AG59: -0.385 | AH59: -0.385 | AI59: -0.385 | AJ59: -0.385 | AK59: -0.385 | AL59: -0.385 | AM59: -0.385 | AN59: -0.385 | AO59: -0.385 | AP59: -0.385 | AQ59: -0.385 | AR59: -0.385 | AS59: -0.385 | AT59: -0.385 | AU59: -0.385 | AV59: -0.385 | AW59: -0.385 | AX59: -0.385 | AY59: -0.385 | AZ59: -0.385 | BA59: -0.385 | BB59: -0.385 | BC59: -0.385 | BD59: -0.385 | BE59: -0.385 | BF59: -0.385 | BG59: -0.385 | BH59: -0.385 | BI59: -0.385 | BJ59: -0.385 | BK59: -0.385 | BL59: -0.385 | BM59: -0.385 | BN59: -0.385 | BO59: -0.385 | BP59: -0.385 | BQ59: -0.385 | BR59: -0.385 | BS59: -0.385 | BT59: -0.385 | BU59: -0.385 | BV59: -0.385 | BW59: -0.385 | BX59: -0.385 | BY59: -0.385 | BZ59: -0.385 | CA59: -0.385 | CB59: -0.385 | CC59: -0.385 | CD59: -0.385 | CE59: -0.385 | CF59: -0.385 | CG59: -0.385 | CH59: -0.385 | CI59: -0.385 | CJ59: -0.385 | CK59: -0.385 | CL59: -0.385 | CM59: -0.385 | CN59: -0.385 | CO59: -0.385 | CP59: -0.385 | CQ59: -0.385 | CR59: -0.385 | CS59: -0.385 | CT59: -0.385 | CU59: -0.385 | CV59: -0.385 | CW59: -0.385 | CX59: -0.385 | CY59: -0.385 | CZ59: -0.385 | DA59: -0.385 | DB59: -0.385 | DC59: -0.385 | DD59: -0.385 | DE59: -0.385 | DF59: -0.385 | DG59: -0.385 | DH59: -0.385 | DI59: -0.385 | DJ59: -0.385 | DK59: -0.385 | DL59: -0.385 | DM59: -0.385 | DN59: -0.385 | DO59: -0.385 | DP59: -0.385 | DQ59: -0.385 | DR59: -0.385 | DS59: -0.385 | DT59: -0.385 | DU59: -0.385 | DV59: -0.385 | DW59: -0.385 | DX59: -0.385 | DY59: -0.385 | DZ59: -0.385 | EA59: -0.385 | EB59: -0.385 | EC59: -0.385 | ED59: -0.385 | EE59: -0.385 | EF59: -0.385 | EG59: -0.385 | EH59: -0.385 | EI59: -0.385 | EJ59: -0.385 | EK59: -0.385 | EL59: -0.385 | EM59: -0.385 | EN59: -0.385 | EO59: -0.385 | EP59: -0.385 | EQ59: -0.385 | ER59: -0.385 | ES59: -0.385 | ET59: -0.385 | EU59: -0.385 | EV59: -0.385 | EW59: -0.385 | EX59: -0.385 | EY59: -0.385 | EZ59: -0.385 | FA59: -0.385 | FB59: -0.385 | FC59: -0.385 | FD59: -0.385 | FE59: -0.385 | FF59: -0.385 | FG59: -0.385 | FH59: -0.385 | FI59: -0.385 | FJ59: -0.385 | FK59: -0.385 | FL59: -0.385 | FM59: -0.385 | FN59: -0.385 | FO59: -0.385 | FP59: -0.385 | FQ59: -0.385 | FR59: -0.385 | FS59: -0.385 | FT59: -0.385 | FU59: -0.385 | FV59: -0.385 | FW59: -0.385 | FX59: -0.385 | FY59: -0.385 | FZ59: -0.385 | GA59: -0.385 | GB59: -0.385 | GC59: -0.385 | GD59: -0.385 | GE59: -0.385 | GF59: -0.385 | GG59: -0.385 | GH59: -0.385 | GI59: -0.385 | GJ59: -0.385 | GK59: -0.385 | GL59: -0.385 | GM59: -0.385 | GN59: -0.385 | GO59: -0.385 | GP59: -0.385 | GQ59: -0.385 | GR59: -0.385 | GS59: -0.385 | GT59: -0.385 | GU59: -0.385 | GV59: -0.385 | GW59: -0.385 | GX59: -0.385 | GY59: -0.385 | GZ59: -0.385 | HA59: -0.385 | HB59: -0.385 | HC59: -0.385 | HD59: -0.385 | HE59: -0.385 | HF59: -0.385 | HG59: -0.385 | HH59: -0.385 | HI59: -0.385 | HJ59: -0.385 | HK59: -0.385 | HL59: -0.385 | HM59: -0.385 | HN59: -0.385 | HO59: -0.385 | HP59: -0.385 | HQ59: -0.385 | HR59: -0.385 | HS59: -0.385 | HT59: -0.385 | HU59: -0.385 | HV59: -0.385 | HW59: -0.385 | HX59: -0.385 | HY59: -0.385 | HZ59: -0.385 | IA59: -0.385 | IB59: -0.385 | IC59: -0.385 | ID59: -0.385 | IE59: -0.385 | IF59: -0.385 | IG59: -0.385 | IH59: -0.385 | II59: -0.385 | IJ59: -0.385 | IK59: -0.385 | IL59: -0.385 | IM59: -0.385 | IN59: -0.385 | IO59: -0.385 | IP59: -0.385 | IQ59: -0.385 | IR59: -0.385 | IS59: -0.385 | IT59: -0.385 | IU59: -0.385 | IV59: -0.385 | IW59: -0.385 | IX59: -0.385 | IY59: -0.385 | IZ59: -0.385 | JA59: -0.385 | JB59: -0.385 | JC59: -0.385 | JD59: -0.385 | JE59: -0.385 | JF59: -0.385 | JG59: -0.385 | JH59: -0.385 | JI59: -0.385 | JJ59: -0.385 | JK59: -0.385 | JL59: -0.385 | JM59: -0.385 | JN59: -0.385 | JO59: -0.385 | JP59: -0.385 | JQ59: -0.385 | JR59: -0.385 | JS59: -0.385 | JT59: -0.385 | JU59: -0.385 | JV59: -0.385 | JW59: -0.385 | JX59: -0.385 | JY59: -0.385 | JZ59: -0.385 | KA59: -0.385 | KB59: -0.385 | KC59: -0.385 | KD59: -0.385 | KE59: -0.385 | KF59: -0.385
E60: USD/Ltr, real | J60: Downside case | K60: -0.28 | L60: -0.28 | M60: -0.28 | N60: -0.28 | O60: -0.28 | P60: -0.28 | Q60: -0.28 | R60: -0.28 | S60: -0.28 | T60: -0.28 | U60: -0.28 | V60: -0.28 | W60: -0.28 | X60: -0.28 | Y60: -0.28 | Z60: -0.28 | AA60: -0.28 | AB60: -0.28 | AC60: -0.28 | AD60: -0.28 | AE60: -0.28 | AF60: -0.28 | AG60: -0.28 | AH60: -0.28 | AI60: -0.28 | AJ60: -0.28 | AK60: -0.28 | AL60: -0.28 | AM60: -0.28 | AN60: -0.28 | AO60: -0.28 | AP60: -0.28 | AQ60: -0.28 | AR60: -0.28 | AS60: -0.28 | AT60: -0.28 | AU60: -0.28 | AV60: -0.28 | AW60: -0.28 | AX60: -0.28 | AY60: -0.28 | AZ60: -0.28 | BA60: -0.28 | BB60: -0.28 | BC60: -0.28 | BD60: -0.28 | BE60: -0.28 | BF60: -0.28 | BG60: -0.28 | BH60: -0.28 | BI60: -0.28 | BJ60: -0.28 | BK60: -0.28 | BL60: -0.28 | BM60: -0.28 | BN60: -0.28 | BO60: -0.28 | BP60: -0.28 | BQ60: -0.28 | BR60: -0.28 | BS60: -0.28 | BT60: -0.28 | BU60: -0.28 | BV60: -0.28 | BW60: -0.28 | BX60: -0.28 | BY60: -0.28 | BZ60: -0.28 | CA60: -0.28 | CB60: -0.28 | CC60: -0.28 | CD60: -0.28 | CE60: -0.28 | CF60: -0.28 | CG60: -0.28 | CH60: -0.28 | CI60: -0.28 | CJ60: -0.28 | CK60: -0.28 | CL60: -0.28 | CM60: -0.28 | CN60: -0.28 | CO60: -0.28 | CP60: -0.28 | CQ60: -0.28 | CR60: -0.28 | CS60: -0.28 | CT60: -0.28 | CU60: -0.28 | CV60: -0.28 | CW60: -0.28 | CX60: -0.28 | CY60: -0.28 | CZ60: -0.28 | DA60: -0.28 | DB60: -0.28 | DC60: -0.28 | DD60: -0.28 | DE60: -0.28 | DF60: -0.28 | DG60: -0.28 | DH60: -0.28 | DI60: -0.28 | DJ60: -0.28 | DK60: -0.28 | DL60: -0.28 | DM60: -0.28 | DN60: -0.28 | DO60: -0.28 | DP60: -0.28 | DQ60: -0.28 | DR60: -0.28 | DS60: -0.28 | DT60: -0.28 | DU60: -0.28 | DV60: -0.28 | DW60: -0.28 | DX60: -0.28 | DY60: -0.28 | DZ60: -0.28 | EA60: -0.28 | EB60: -0.28 | EC60: -0.28 | ED60: -0.28 | EE60: -0.28 | EF60: -0.28 | EG60: -0.28 | EH60: -0.28 | EI60: -0.28 | EJ60: -0.28 | EK60: -0.28 | EL60: -0.28 | EM60: -0.28 | EN60: -0.28 | EO60: -0.28 | EP60: -0.28 | EQ60: -0.28 | ER60: -0.28 | ES60: -0.28 | ET60: -0.28 | EU60: -0.28 | EV60: -0.28 | EW60: -0.28 | EX60: -0.28 | EY60: -0.28 | EZ60: -0.28 | FA60: -0.28 | FB60: -0.28 | FC60: -0.28 | FD60: -0.28 | FE60: -0.28 | FF60: -0.28 | FG60: -0.28 | FH60: -0.28 | FI60: -0.28 | FJ60: -0.28 | FK60: -0.28 | FL60: -0.28 | FM60: -0.28 | FN60: -0.28 | FO60: -0.28 | FP60: -0.28 | FQ60: -0.28 | FR60: -0.28 | FS60: -0.28 | FT60: -0.28 | FU60: -0.28 | FV60: -0.28 | FW60: -0.28 | FX60: -0.28 | FY60: -0.28 | FZ60: -0.28 | GA60: -0.28 | GB60: -0.28 | GC60: -0.28 | GD60: -0.28 | GE60: -0.28 | GF60: -0.28 | GG60: -0.28 | GH60: -0.28 | GI60: -0.28 | GJ60: -0.28 | GK60: -0.28 | GL60: -0.28 | GM60: -0.28 | GN60: -0.28 | GO60: -0.28 | GP60: -0.28 | GQ60: -0.28 | GR60: -0.28 | GS60: -0.28 | GT60: -0.28 | GU60: -0.28 | GV60: -0.28 | GW60: -0.28 | GX60: -0.28 | GY60: -0.28 | GZ60: -0.28 | HA60: -0.28 | HB60: -0.28 | HC60: -0.28 | HD60: -0.28 | HE60: -0.28 | HF60: -0.28 | HG60: -0.28 | HH60: -0.28 | HI60: -0.28 | HJ60: -0.28 | HK60: -0.28 | HL60: -0.28 | HM60: -0.28 | HN60: -0.28 | HO60: -0.28 | HP60: -0.28 | HQ60: -0.28 | HR60: -0.28 | HS60: -0.28 | HT60: -0.28 | HU60: -0.28 | HV60: -0.28 | HW60: -0.28 | HX60: -0.28 | HY60: -0.28 | HZ60: -0.28 | IA60: -0.28 | IB60: -0.28 | IC60: -0.28 | ID60: -0.28 | IE60: -0.28 | IF60: -0.28 | IG60: -0.28 | IH60: -0.28 | II60: -0.28 | IJ60: -0.28 | IK60: -0.28 | IL60: -0.28 | IM60: -0.28 | IN60: -0.28 | IO60: -0.28 | IP60: -0.28 | IQ60: -0.28 | IR60: -0.28 | IS60: -0.28 | IT60: -0.28 | IU60: -0.28 | IV60: -0.28 | IW60: -0.28 | IX60: -0.28 | IY60: -0.28 | IZ60: -0.28 | JA60: -0.28 | JB60: -0.28 | JC60: -0.28 | JD60: -0.28 | JE60: -0.28 | JF60: -0.28 | JG60: -0.28 | JH60: -0.28 | JI60: -0.28 | JJ60: -0.28 | JK60: -0.28 | JL60: -0.28 | JM60: -0.28 | JN60: -0.28 | JO60: -0.28 | JP60: -0.28 | JQ60: -0.28 | JR60: -0.28 | JS60: -0.28 | JT60: -0.28 | JU60: -0.28 | JV60: -0.28 | JW60: -0.28 | JX60: -0.28 | JY60: -0.28 | JZ60: -0.28 | KA60: -0.28 | KB60: -0.28 | KC60: -0.28 | KD60: -0.28 | KE60: -0.28 | KF60: -0.28
E61: USD/Ltr, real | J61: [Spare]
E62: USD/Ltr, real | J62: [Spare]
E63: USD/Ltr, real | J63: [Spare]
E64: USD/Ltr, real | J64: [Spare]
E65: USD/Ltr, real | J65: [Spare]
E66: USD/Ltr, real | J66: [Spare]
H68: Fixed Costs
J70: Chosen case | K70: =Control!H20 -> 1 | L70: {=INDEX(J74:J82,K70)} -> Base case
E71: USD, real | J71: Live Price | K71: {=INDEX(K74:K82,$K$70)} -> -2.5 | L71: {=INDEX(L74:L82,$K$70)} -> -2.5 | M71: {=INDEX(M74:M82,$K$70)} -> -2.5 | N71: {=INDEX(N74:N82,$K$70)} -> -2.5 | O71: {=INDEX(O74:O82,$K$70)} -> -2.5 | P71: {=INDEX(P74:P82,$K$70)} -> -2.5 | Q71: {=INDEX(Q74:Q82,$K$70)} -> -2.5 | R71: {=INDEX(R74:R82,$K$70)} -> -2.5 | ... KF71: {=INDEX(KF74:KF82,$K$70)} -> -2.5
D72: 0 | E72: USD, real | J72: Bank Adjustment | K72: =K71*(1+$D72) -> -2.5 | L72: =L71*(1+$D72) -> -2.5 | M72: =M71*(1+$D72) -> -2.5 | N72: =N71*(1+$D72) -> -2.5 | O72: =O71*(1+$D72) -> -2.5 | P72: =P71*(1+$D72) -> -2.5 | Q72: =Q71*(1+$D72) -> -2.5 | R72: =R71*(1+$D72) -> -2.5 | ... KF72: =KF71*(1+$D72) -> -2.5
E74: USD, real | J74: Base case | K74: -2.5 | L74: -2.5 | M74: -2.5 | N74: -2.5 | O74: -2.5 | P74: -2.5 | Q74: -2.5 | R74: -2.5 | S74: -2.5 | T74: -2.5 | U74: -2.5 | V74: -2.5 | W74: -2.5 | X74: -2.5 | Y74: -2.5 | Z74: -2.5 | AA74: -2.5 | AB74: -2.5 | AC74: -2.5 | AD74: -2.5 | AE74: -2.5 | AF74: -2.5 | AG74: -2.5 | AH74: -2.5 | AI74: -2.5 | AJ74: -2.5 | AK74: -2.5 | AL74: -2.5 | AM74: -2.5 | AN74: -2.5 | AO74: -2.5 | AP74: -2.5 | AQ74: -2.5 | AR74: -2.5 | AS74: -2.5 | AT74: -2.5 | AU74: -2.5 | AV74: -2.5 | AW74: -2.5 | AX74: -2.5 | AY74: -2.5 | AZ74: -2.5 | BA74: -2.5 | BB74: -2.5 | BC74: -2.5 | BD74: -2.5 | BE74: -2.5 | BF74: -2.5 | BG74: -2.5 | BH74: -2.5 | BI74: -2.5 | BJ74: -2.5 | BK74: -2.5 | BL74: -2.5 | BM74: -2.5 | BN74: -2.5 | BO74: -2.5 | BP74: -2.5 | BQ74: -2.5 | BR74: -2.5 | BS74: -2.5 | BT74: -2.5 | BU74: -2.5 | BV74: -2.5 | BW74: -2.5 | BX74: -2.5 | BY74: -2.5 | BZ74: -2.5 | CA74: -2.5 | CB74: -2.5 | CC74: -2.5 | CD74: -2.5 | CE74: -2.5 | CF74: -2.5 | CG74: -2.5 | CH74: -2.5 | CI74: -2.5 | CJ74: -2.5 | CK74: -2.5 | CL74: -2.5 | CM74: -2.5 | CN74: -2.5 | CO74: -2.5 | CP74: -2.5 | CQ74: -2.5 | CR74: -2.5 | CS74: -2.5 | CT74: -2.5 | CU74: -2.5 | CV74: -2.5 | CW74: -2.5 | CX74: -2.5 | CY74: -2.5 | CZ74: -2.5 | DA74: -2.5 | DB74: -2.5 | DC74: -2.5 | DD74: -2.5 | DE74: -2.5 | DF74: -2.5 | DG74: -2.5 | DH74: -2.5 | DI74: -2.5 | DJ74: -2.5 | DK74: -2.5 | DL74: -2.5 | DM74: -2.5 | DN74: -2.5 | DO74: -2.5 | DP74: -2.5 | DQ74: -2.5 | DR74: -2.5 | DS74: -2.5 | DT74: -2.5 | DU74: -2.5 | DV74: -2.5 | DW74: -2.5 | DX74: -2.5 | DY74: -2.5 | DZ74: -2.5 | EA74: -2.5 | EB74: -2.5 | EC74: -2.5 | ED74: -2.5 | EE74: -2.5 | EF74: -2.5 | EG74: -2.5 | EH74: -2.5 | EI74: -2.5 | EJ74: -2.5 | EK74: -2.5 | EL74: -2.5 | EM74: -2.5 | EN74: -2.5 | EO74: -2.5 | EP74: -2.5 | EQ74: -2.5 | ER74: -2.5 | ES74: -2.5 | ET74: -2.5 | EU74: -2.5 | EV74: -2.5 | EW74: -2.5 | EX74: -2.5 | EY74: -2.5 | EZ74: -2.5 | FA74: -2.5 | FB74: -2.5 | FC74: -2.5 | FD74: -2.5 | FE74: -2.5 | FF74: -2.5 | FG74: -2.5 | FH74: -2.5 | FI74: -2.5 | FJ74: -2.5 | FK74: -2.5 | FL74: -2.5 | FM74: -2.5 | FN74: -2.5 | FO74: -2.5 | FP74: -2.5 | FQ74: -2.5 | FR74: -2.5 | FS74: -2.5 | FT74: -2.5 | FU74: -2.5 | FV74: -2.5 | FW74: -2.5 | FX74: -2.5 | FY74: -2.5 | FZ74: -2.5 | GA74: -2.5 | GB74: -2.5 | GC74: -2.5 | GD74: -2.5 | GE74: -2.5 | GF74: -2.5 | GG74: -2.5 | GH74: -2.5 | GI74: -2.5 | GJ74: -2.5 | GK74: -2.5 | GL74: -2.5 | GM74: -2.5 | GN74: -2.5 | GO74: -2.5 | GP74: -2.5 | GQ74: -2.5 | GR74: -2.5 | GS74: -2.5 | GT74: -2.5 | GU74: -2.5 | GV74: -2.5 | GW74: -2.5 | GX74: -2.5 | GY74: -2.5 | GZ74: -2.5 | HA74: -2.5 | HB74: -2.5 | HC74: -2.5 | HD74: -2.5 | HE74: -2.5 | HF74: -2.5 | HG74: -2.5 | HH74: -2.5 | HI74: -2.5 | HJ74: -2.5 | HK74: -2.5 | HL74: -2.5 | HM74: -2.5 | HN74: -2.5 | HO74: -2.5 | HP74: -2.5 | HQ74: -2.5 | HR74: -2.5 | HS74: -2.5 | HT74: -2.5 | HU74: -2.5 | HV74: -2.5 | HW74: -2.5 | HX74: -2.5 | HY74: -2.5 | HZ74: -2.5 | IA74: -2.5 | IB74: -2.5 | IC74: -2.5 | ID74: -2.5 | IE74: -2.5 | IF74: -2.5 | IG74: -2.5 | IH74: -2.5 | II74: -2.5 | IJ74: -2.5 | IK74: -2.5 | IL74: -2.5 | IM74: -2.5 | IN74: -2.5 | IO74: -2.5 | IP74: -2.5 | IQ74: -2.5 | IR74: -2.5 | IS74: -2.5 | IT74: -2.5 | IU74: -2.5 | IV74: -2.5 | IW74: -2.5 | IX74: -2.5 | IY74: -2.5 | IZ74: -2.5 | JA74: -2.5 | JB74: -2.5 | JC74: -2.5 | JD74: -2.5 | JE74: -2.5 | JF74: -2.5 | JG74: -2.5 | JH74: -2.5 | JI74: -2.5 | JJ74: -2.5 | JK74: -2.5 | JL74: -2.5 | JM74: -2.5 | JN74: -2.5 | JO74: -2.5 | JP74: -2.5 | JQ74: -2.5 | JR74: -2.5 | JS74: -2.5 | JT74: -2.5 | JU74: -2.5 | JV74: -2.5 | JW74: -2.5 | JX74: -2.5 | JY74: -2.5 | JZ74: -2.5 | KA74: -2.5 | KB74: -2.5 | KC74: -2.5 | KD74: -2.5 | KE74: -2.5 | KF74: -2.5
E75: USD, real | J75: Lender case | K75: -3 | L75: -3 | M75: -3 | N75: -3 | O75: -3 | P75: -3 | Q75: -3 | R75: -3 | S75: -3 | T75: -3 | U75: -3 | V75: -3 | W75: -3 | X75: -3 | Y75: -3 | Z75: -3 | AA75: -3 | AB75: -3 | AC75: -3 | AD75: -3 | AE75: -3 | AF75: -3 | AG75: -3 | AH75: -3 | AI75: -3 | AJ75: -3 | AK75: -3 | AL75: -3 | AM75: -3 | AN75: -3 | AO75: -3 | AP75: -3 | AQ75: -3 | AR75: -3 | AS75: -3 | AT75: -3 | AU75: -3 | AV75: -3 | AW75: -3 | AX75: -3 | AY75: -3 | AZ75: -3 | BA75: -3 | BB75: -3 | BC75: -3 | BD75: -3 | BE75: -3 | BF75: -3 | BG75: -3 | BH75: -3 | BI75: -3 | BJ75: -3 | BK75: -3 | BL75: -3 | BM75: -3 | BN75: -3 | BO75: -3 | BP75: -3 | BQ75: -3 | BR75: -3 | BS75: -3 | BT75: -3 | BU75: -3 | BV75: -3 | BW75: -3 | BX75: -3 | BY75: -3 | BZ75: -3 | CA75: -3 | CB75: -3 | CC75: -3 | CD75: -3 | CE75: -3 | CF75: -3 | CG75: -3 | CH75: -3 | CI75: -3 | CJ75: -3 | CK75: -3 | CL75: -3 | CM75: -3 | CN75: -3 | CO75: -3 | CP75: -3 | CQ75: -3 | CR75: -3 | CS75: -3 | CT75: -3 | CU75: -3 | CV75: -3 | CW75: -3 | CX75: -3 | CY75: -3 | CZ75: -3 | DA75: -3 | DB75: -3 | DC75: -3 | DD75: -3 | DE75: -3 | DF75: -3 | DG75: -3 | DH75: -3 | DI75: -3 | DJ75: -3 | DK75: -3 | DL75: -3 | DM75: -3 | DN75: -3 | DO75: -3 | DP75: -3 | DQ75: -3 | DR75: -3 | DS75: -3 | DT75: -3 | DU75: -3 | DV75: -3 | DW75: -3 | DX75: -3 | DY75: -3 | DZ75: -3 | EA75: -3 | EB75: -3 | EC75: -3 | ED75: -3 | EE75: -3 | EF75: -3 | EG75: -3 | EH75: -3 | EI75: -3 | EJ75: -3 | EK75: -3 | EL75: -3 | EM75: -3 | EN75: -3 | EO75: -3 | EP75: -3 | EQ75: -3 | ER75: -3 | ES75: -3 | ET75: -3 | EU75: -3 | EV75: -3 | EW75: -3 | EX75: -3 | EY75: -3 | EZ75: -3 | FA75: -3 | FB75: -3 | FC75: -3 | FD75: -3 | FE75: -3 | FF75: -3 | FG75: -3 | FH75: -3 | FI75: -3 | FJ75: -3 | FK75: -3 | FL75: -3 | FM75: -3 | FN75: -3 | FO75: -3 | FP75: -3 | FQ75: -3 | FR75: -3 | FS75: -3 | FT75: -3 | FU75: -3 | FV75: -3 | FW75: -3 | FX75: -3 | FY75: -3 | FZ75: -3 | GA75: -3 | GB75: -3 | GC75: -3 | GD75: -3 | GE75: -3 | GF75: -3 | GG75: -3 | GH75: -3 | GI75: -3 | GJ75: -3 | GK75: -3 | GL75: -3 | GM75: -3 | GN75: -3 | GO75: -3 | GP75: -3 | GQ75: -3 | GR75: -3 | GS75: -3 | GT75: -3 | GU75: -3 | GV75: -3 | GW75: -3 | GX75: -3 | GY75: -3 | GZ75: -3 | HA75: -3 | HB75: -3 | HC75: -3 | HD75: -3 | HE75: -3 | HF75: -3 | HG75: -3 | HH75: -3 | HI75: -3 | HJ75: -3 | HK75: -3 | HL75: -3 | HM75: -3 | HN75: -3 | HO75: -3 | HP75: -3 | HQ75: -3 | HR75: -3 | HS75: -3 | HT75: -3 | HU75: -3 | HV75: -3 | HW75: -3 | HX75: -3 | HY75: -3 | HZ75: -3 | IA75: -3 | IB75: -3 | IC75: -3 | ID75: -3 | IE75: -3 | IF75: -3 | IG75: -3 | IH75: -3 | II75: -3 | IJ75: -3 | IK75: -3 | IL75: -3 | IM75: -3 | IN75: -3 | IO75: -3 | IP75: -3 | IQ75: -3 | IR75: -3 | IS75: -3 | IT75: -3 | IU75: -3 | IV75: -3 | IW75: -3 | IX75: -3 | IY75: -3 | IZ75: -3 | JA75: -3 | JB75: -3 | JC75: -3 | JD75: -3 | JE75: -3 | JF75: -3 | JG75: -3 | JH75: -3 | JI75: -3 | JJ75: -3 | JK75: -3 | JL75: -3 | JM75: -3 | JN75: -3 | JO75: -3 | JP75: -3 | JQ75: -3 | JR75: -3 | JS75: -3 | JT75: -3 | JU75: -3 | JV75: -3 | JW75: -3 | JX75: -3 | JY75: -3 | JZ75: -3 | KA75: -3 | KB75: -3 | KC75: -3 | KD75: -3 | KE75: -3 | KF75: -3
E76: USD, real | J76: Downside case | K76: -3.5 | L76: -3.5 | M76: -3.5 | N76: -3.5 | O76: -3.5 | P76: -3.5 | Q76: -3.5 | R76: -3.5 | S76: -3.5 | T76: -3.5 | U76: -3.5 | V76: -3.5 | W76: -3.5 | X76: -3.5 | Y76: -3.5 | Z76: -3.5 | AA76: -3.5 | AB76: -3.5 | AC76: -3.5 | AD76: -3.5 | AE76: -3.5 | AF76: -3.5 | AG76: -3.5 | AH76: -3.5 | AI76: -3.5 | AJ76: -3.5 | AK76: -3.5 | AL76: -3.5 | AM76: -3.5 | AN76: -3.5 | AO76: -3.5 | AP76: -3.5 | AQ76: -3.5 | AR76: -3.5 | AS76: -3.5 | AT76: -3.5 | AU76: -3.5 | AV76: -3.5 | AW76: -3.5 | AX76: -3.5 | AY76: -3.5 | AZ76: -3.5 | BA76: -3.5 | BB76: -3.5 | BC76: -3.5 | BD76: -3.5 | BE76: -3.5 | BF76: -3.5 | BG76: -3.5 | BH76: -3.5 | BI76: -3.5 | BJ76: -3.5 | BK76: -3.5 | BL76: -3.5 | BM76: -3.5 | BN76: -3.5 | BO76: -3.5 | BP76: -3.5 | BQ76: -3.5 | BR76: -3.5 | BS76: -3.5 | BT76: -3.5 | BU76: -3.5 | BV76: -3.5 | BW76: -3.5 | BX76: -3.5 | BY76: -3.5 | BZ76: -3.5 | CA76: -3.5 | CB76: -3.5 | CC76: -3.5 | CD76: -3.5 | CE76: -3.5 | CF76: -3.5 | CG76: -3.5 | CH76: -3.5 | CI76: -3.5 | CJ76: -3.5 | CK76: -3.5 | CL76: -3.5 | CM76: -3.5 | CN76: -3.5 | CO76: -3.5 | CP76: -3.5 | CQ76: -3.5 | CR76: -3.5 | CS76: -3.5 | CT76: -3.5 | CU76: -3.5 | CV76: -3.5 | CW76: -3.5 | CX76: -3.5 | CY76: -3.5 | CZ76: -3.5 | DA76: -3.5 | DB76: -3.5 | DC76: -3.5 | DD76: -3.5 | DE76: -3.5 | DF76: -3.5 | DG76: -3.5 | DH76: -3.5 | DI76: -3.5 | DJ76: -3.5 | DK76: -3.5 | DL76: -3.5 | DM76: -3.5 | DN76: -3.5 | DO76: -3.5 | DP76: -3.5 | DQ76: -3.5 | DR76: -3.5 | DS76: -3.5 | DT76: -3.5 | DU76: -3.5 | DV76: -3.5 | DW76: -3.5 | DX76: -3.5 | DY76: -3.5 | DZ76: -3.5 | EA76: -3.5 | EB76: -3.5 | EC76: -3.5 | ED76: -3.5 | EE76: -3.5 | EF76: -3.5 | EG76: -3.5 | EH76: -3.5 | EI76: -3.5 | EJ76: -3.5 | EK76: -3.5 | EL76: -3.5 | EM76: -3.5 | EN76: -3.5 | EO76: -3.5 | EP76: -3.5 | EQ76: -3.5 | ER76: -3.5 | ES76: -3.5 | ET76: -3.5 | EU76: -3.5 | EV76: -3.5 | EW76: -3.5 | EX76: -3.5 | EY76: -3.5 | EZ76: -3.5 | FA76: -3.5 | FB76: -3.5 | FC76: -3.5 | FD76: -3.5 | FE76: -3.5 | FF76: -3.5 | FG76: -3.5 | FH76: -3.5 | FI76: -3.5 | FJ76: -3.5 | FK76: -3.5 | FL76: -3.5 | FM76: -3.5 | FN76: -3.5 | FO76: -3.5 | FP76: -3.5 | FQ76: -3.5 | FR76: -3.5 | FS76: -3.5 | FT76: -3.5 | FU76: -3.5 | FV76: -3.5 | FW76: -3.5 | FX76: -3.5 | FY76: -3.5 | FZ76: -3.5 | GA76: -3.5 | GB76: -3.5 | GC76: -3.5 | GD76: -3.5 | GE76: -3.5 | GF76: -3.5 | GG76: -3.5 | GH76: -3.5 | GI76: -3.5 | GJ76: -3.5 | GK76: -3.5 | GL76: -3.5 | GM76: -3.5 | GN76: -3.5 | GO76: -3.5 | GP76: -3.5 | GQ76: -3.5 | GR76: -3.5 | GS76: -3.5 | GT76: -3.5 | GU76: -3.5 | GV76: -3.5 | GW76: -3.5 | GX76: -3.5 | GY76: -3.5 | GZ76: -3.5 | HA76: -3.5 | HB76: -3.5 | HC76: -3.5 | HD76: -3.5 | HE76: -3.5 | HF76: -3.5 | HG76: -3.5 | HH76: -3.5 | HI76: -3.5 | HJ76: -3.5 | HK76: -3.5 | HL76: -3.5 | HM76: -3.5 | HN76: -3.5 | HO76: -3.5 | HP76: -3.5 | HQ76: -3.5 | HR76: -3.5 | HS76: -3.5 | HT76: -3.5 | HU76: -3.5 | HV76: -3.5 | HW76: -3.5 | HX76: -3.5 | HY76: -3.5 | HZ76: -3.5 | IA76: -3.5 | IB76: -3.5 | IC76: -3.5 | ID76: -3.5 | IE76: -3.5 | IF76: -3.5 | IG76: -3.5 | IH76: -3.5 | II76: -3.5 | IJ76: -3.5 | IK76: -3.5 | IL76: -3.5 | IM76: -3.5 | IN76: -3.5 | IO76: -3.5 | IP76: -3.5 | IQ76: -3.5 | IR76: -3.5 | IS76: -3.5 | IT76: -3.5 | IU76: -3.5 | IV76: -3.5 | IW76: -3.5 | IX76: -3.5 | IY76: -3.5 | IZ76: -3.5 | JA76: -3.5 | JB76: -3.5 | JC76: -3.5 | JD76: -3.5 | JE76: -3.5 | JF76: -3.5 | JG76: -3.5 | JH76: -3.5 | JI76: -3.5 | JJ76: -3.5 | JK76: -3.5 | JL76: -3.5 | JM76: -3.5 | JN76: -3.5 | JO76: -3.5 | JP76: -3.5 | JQ76: -3.5 | JR76: -3.5 | JS76: -3.5 | JT76: -3.5 | JU76: -3.5 | JV76: -3.5 | JW76: -3.5 | JX76: -3.5 | JY76: -3.5 | JZ76: -3.5 | KA76: -3.5 | KB76: -3.5 | KC76: -3.5 | KD76: -3.5 | KE76: -3.5 | KF76: -3.5
E77: USD, real | J77: [Spare]
E78: USD, real | J78: [Spare]
E79: USD, real | J79: [Spare]
E80: USD, real | J80: [Spare]
E81: USD, real | J81: [Spare]
E82: USD, real | J82: [Spare]
H84: SG&A
J86: Chosen case | K86: =Control!H21 -> 1 | L86: {=INDEX(J90:J98,K86)} -> Base case
E87: USD, real | J87: Live | K87: {=INDEX(K90:K98,$K86)} -> -2.625 | L87: {=INDEX(L90:L98,$K86)} -> -2.625 | M87: {=INDEX(M90:M98,$K86)} -> -2.625 | N87: {=INDEX(N90:N98,$K86)} -> -2.625 | O87: {=INDEX(O90:O98,$K86)} -> -2.625 | P87: {=INDEX(P90:P98,$K86)} -> -2.625 | Q87: {=INDEX(Q90:Q98,$K86)} -> -2.625 | R87: {=INDEX(R90:R98,$K86)} -> -2.625 | ... KF87: {=INDEX(KF90:KF98,$K86)} -> -2.625
D88: 0 | E88: USD, real | J88: Bank Adjustment | K88: =K87*(1+$D88) -> -2.625 | L88: =L87*(1+$D88) -> -2.625 | M88: =M87*(1+$D88) -> -2.625 | N88: =N87*(1+$D88) -> -2.625 | O88: =O87*(1+$D88) -> -2.625 | P88: =P87*(1+$D88) -> -2.625 | Q88: =Q87*(1+$D88) -> -2.625 | R88: =R87*(1+$D88) -> -2.625 | ... KF88: =KF87*(1+$D88) -> -2.625
E90: USD, real | J90: Base case | K90: -2.625 | L90: -2.625 | M90: -2.625 | N90: -2.625 | O90: -2.625 | P90: -2.625 | Q90: -2.625 | R90: -2.625 | S90: -2.625 | T90: -2.625 | U90: -2.625 | V90: -2.625 | W90: -2.625 | X90: -2.625 | Y90: -2.625 | Z90: -2.625 | AA90: -2.625 | AB90: -2.625 | AC90: -2.625 | AD90: -2.625 | AE90: -2.625 | AF90: -2.625 | AG90: -2.625 | AH90: -2.625 | AI90: -2.625 | AJ90: -2.625 | AK90: -2.625 | AL90: -2.625 | AM90: -2.625 | AN90: -2.625 | AO90: -2.625 | AP90: -2.625 | AQ90: -2.625 | AR90: -2.625 | AS90: -2.625 | AT90: -2.625 | AU90: -2.625 | AV90: -2.625 | AW90: -2.625 | AX90: -2.625 | AY90: -2.625 | AZ90: -2.625 | BA90: -2.625 | BB90: -2.625 | BC90: -2.625 | BD90: -2.625 | BE90: -2.625 | BF90: -2.625 | BG90: -2.625 | BH90: -2.625 | BI90: -2.625 | BJ90: -2.625 | BK90: -2.625 | BL90: -2.625 | BM90: -2.625 | BN90: -2.625 | BO90: -2.625 | BP90: -2.625 | BQ90: -2.625 | BR90: -2.625 | BS90: -2.625 | BT90: -2.625 | BU90: -2.625 | BV90: -2.625 | BW90: -2.625 | BX90: -2.625 | BY90: -2.625 | BZ90: -2.625 | CA90: -2.625 | CB90: -2.625 | CC90: -2.625 | CD90: -2.625 | CE90: -2.625 | CF90: -2.625 | CG90: -2.625 | CH90: -2.625 | CI90: -2.625 | CJ90: -2.625 | CK90: -2.625 | CL90: -2.625 | CM90: -2.625 | CN90: -2.625 | CO90: -2.625 | CP90: -2.625 | CQ90: -2.625 | CR90: -2.625 | CS90: -2.625 | CT90: -2.625 | CU90: -2.625 | CV90: -2.625 | CW90: -2.625 | CX90: -2.625 | CY90: -2.625 | CZ90: -2.625 | DA90: -2.625 | DB90: -2.625 | DC90: -2.625 | DD90: -2.625 | DE90: -2.625 | DF90: -2.625 | DG90: -2.625 | DH90: -2.625 | DI90: -2.625 | DJ90: -2.625 | DK90: -2.625 | DL90: -2.625 | DM90: -2.625 | DN90: -2.625 | DO90: -2.625 | DP90: -2.625 | DQ90: -2.625 | DR90: -2.625 | DS90: -2.625 | DT90: -2.625 | DU90: -2.625 | DV90: -2.625 | DW90: -2.625 | DX90: -2.625 | DY90: -2.625 | DZ90: -2.625 | EA90: -2.625 | EB90: -2.625 | EC90: -2.625 | ED90: -2.625 | EE90: -2.625 | EF90: -2.625 | EG90: -2.625 | EH90: -2.625 | EI90: -2.625 | EJ90: -2.625 | EK90: -2.625 | EL90: -2.625 | EM90: -2.625 | EN90: -2.625 | EO90: -2.625 | EP90: -2.625 | EQ90: -2.625 | ER90: -2.625 | ES90: -2.625 | ET90: -2.625 | EU90: -2.625 | EV90: -2.625 | EW90: -2.625 | EX90: -2.625 | EY90: -2.625 | EZ90: -2.625 | FA90: -2.625 | FB90: -2.625 | FC90: -2.625 | FD90: -2.625 | FE90: -2.625 | FF90: -2.625 | FG90: -2.625 | FH90: -2.625 | FI90: -2.625 | FJ90: -2.625 | FK90: -2.625 | FL90: -2.625 | FM90: -2.625 | FN90: -2.625 | FO90: -2.625 | FP90: -2.625 | FQ90: -2.625 | FR90: -2.625 | FS90: -2.625 | FT90: -2.625 | FU90: -2.625 | FV90: -2.625 | FW90: -2.625 | FX90: -2.625 | FY90: -2.625 | FZ90: -2.625 | GA90: -2.625 | GB90: -2.625 | GC90: -2.625 | GD90: -2.625 | GE90: -2.625 | GF90: -2.625 | GG90: -2.625 | GH90: -2.625 | GI90: -2.625 | GJ90: -2.625 | GK90: -2.625 | GL90: -2.625 | GM90: -2.625 | GN90: -2.625 | GO90: -2.625 | GP90: -2.625 | GQ90: -2.625 | GR90: -2.625 | GS90: -2.625 | GT90: -2.625 | GU90: -2.625 | GV90: -2.625 | GW90: -2.625 | GX90: -2.625 | GY90: -2.625 | GZ90: -2.625 | HA90: -2.625 | HB90: -2.625 | HC90: -2.625 | HD90: -2.625 | HE90: -2.625 | HF90: -2.625 | HG90: -2.625 | HH90: -2.625 | HI90: -2.625 | HJ90: -2.625 | HK90: -2.625 | HL90: -2.625 | HM90: -2.625 | HN90: -2.625 | HO90: -2.625 | HP90: -2.625 | HQ90: -2.625 | HR90: -2.625 | HS90: -2.625 | HT90: -2.625 | HU90: -2.625 | HV90: -2.625 | HW90: -2.625 | HX90: -2.625 | HY90: -2.625 | HZ90: -2.625 | IA90: -2.625 | IB90: -2.625 | IC90: -2.625 | ID90: -2.625 | IE90: -2.625 | IF90: -2.625 | IG90: -2.625 | IH90: -2.625 | II90: -2.625 | IJ90: -2.625 | IK90: -2.625 | IL90: -2.625 | IM90: -2.625 | IN90: -2.625 | IO90: -2.625 | IP90: -2.625 | IQ90: -2.625 | IR90: -2.625 | IS90: -2.625 | IT90: -2.625 | IU90: -2.625 | IV90: -2.625 | IW90: -2.625 | IX90: -2.625 | IY90: -2.625 | IZ90: -2.625 | JA90: -2.625 | JB90: -2.625 | JC90: -2.625 | JD90: -2.625 | JE90: -2.625 | JF90: -2.625 | JG90: -2.625 | JH90: -2.625 | JI90: -2.625 | JJ90: -2.625 | JK90: -2.625 | JL90: -2.625 | JM90: -2.625 | JN90: -2.625 | JO90: -2.625 | JP90: -2.625 | JQ90: -2.625 | JR90: -2.625 | JS90: -2.625 | JT90: -2.625 | JU90: -2.625 | JV90: -2.625 | JW90: -2.625 | JX90: -2.625 | JY90: -2.625 | JZ90: -2.625 | KA90: -2.625 | KB90: -2.625 | KC90: -2.625 | KD90: -2.625 | KE90: -2.625 | KF90: -2.625
E91: USD, real | J91: Lender case | K91: -3.15 | L91: -3.15 | M91: -3.15 | N91: -3.15 | O91: -3.15 | P91: -3.15 | Q91: -3.15 | R91: -3.15 | S91: -3.15 | T91: -3.15 | U91: -3.15 | V91: -3.15 | W91: -3.15 | X91: -3.15 | Y91: -3.15 | Z91: -3.15 | AA91: -3.15 | AB91: -3.15 | AC91: -3.15 | AD91: -3.15 | AE91: -3.15 | AF91: -3.15 | AG91: -3.15 | AH91: -3.15 | AI91: -3.15 | AJ91: -3.15 | AK91: -3.15 | AL91: -3.15 | AM91: -3.15 | AN91: -3.15 | AO91: -3.15 | AP91: -3.15 | AQ91: -3.15 | AR91: -3.15 | AS91: -3.15 | AT91: -3.15 | AU91: -3.15 | AV91: -3.15 | AW91: -3.15 | AX91: -3.15 | AY91: -3.15 | AZ91: -3.15 | BA91: -3.15 | BB91: -3.15 | BC91: -3.15 | BD91: -3.15 | BE91: -3.15 | BF91: -3.15 | BG91: -3.15 | BH91: -3.15 | BI91: -3.15 | BJ91: -3.15 | BK91: -3.15 | BL91: -3.15 | BM91: -3.15 | BN91: -3.15 | BO91: -3.15 | BP91: -3.15 | BQ91: -3.15 | BR91: -3.15 | BS91: -3.15 | BT91: -3.15 | BU91: -3.15 | BV91: -3.15 | BW91: -3.15 | BX91: -3.15 | BY91: -3.15 | BZ91: -3.15 | CA91: -3.15 | CB91: -3.15 | CC91: -3.15 | CD91: -3.15 | CE91: -3.15 | CF91: -3.15 | CG91: -3.15 | CH91: -3.15 | CI91: -3.15 | CJ91: -3.15 | CK91: -3.15 | CL91: -3.15 | CM91: -3.15 | CN91: -3.15 | CO91: -3.15 | CP91: -3.15 | CQ91: -3.15 | CR91: -3.15 | CS91: -3.15 | CT91: -3.15 | CU91: -3.15 | CV91: -3.15 | CW91: -3.15 | CX91: -3.15 | CY91: -3.15 | CZ91: -3.15 | DA91: -3.15 | DB91: -3.15 | DC91: -3.15 | DD91: -3.15 | DE91: -3.15 | DF91: -3.15 | DG91: -3.15 | DH91: -3.15 | DI91: -3.15 | DJ91: -3.15 | DK91: -3.15 | DL91: -3.15 | DM91: -3.15 | DN91: -3.15 | DO91: -3.15 | DP91: -3.15 | DQ91: -3.15 | DR91: -3.15 | DS91: -3.15 | DT91: -3.15 | DU91: -3.15 | DV91: -3.15 | DW91: -3.15 | DX91: -3.15 | DY91: -3.15 | DZ91: -3.15 | EA91: -3.15 | EB91: -3.15 | EC91: -3.15 | ED91: -3.15 | EE91: -3.15 | EF91: -3.15 | EG91: -3.15 | EH91: -3.15 | EI91: -3.15 | EJ91: -3.15 | EK91: -3.15 | EL91: -3.15 | EM91: -3.15 | EN91: -3.15 | EO91: -3.15 | EP91: -3.15 | EQ91: -3.15 | ER91: -3.15 | ES91: -3.15 | ET91: -3.15 | EU91: -3.15 | EV91: -3.15 | EW91: -3.15 | EX91: -3.15 | EY91: -3.15 | EZ91: -3.15 | FA91: -3.15 | FB91: -3.15 | FC91: -3.15 | FD91: -3.15 | FE91: -3.15 | FF91: -3.15 | FG91: -3.15 | FH91: -3.15 | FI91: -3.15 | FJ91: -3.15 | FK91: -3.15 | FL91: -3.15 | FM91: -3.15 | FN91: -3.15 | FO91: -3.15 | FP91: -3.15 | FQ91: -3.15 | FR91: -3.15 | FS91: -3.15 | FT91: -3.15 | FU91: -3.15 | FV91: -3.15 | FW91: -3.15 | FX91: -3.15 | FY91: -3.15 | FZ91: -3.15 | GA91: -3.15 | GB91: -3.15 | GC91: -3.15 | GD91: -3.15 | GE91: -3.15 | GF91: -3.15 | GG91: -3.15 | GH91: -3.15 | GI91: -3.15 | GJ91: -3.15 | GK91: -3.15 | GL91: -3.15 | GM91: -3.15 | GN91: -3.15 | GO91: -3.15 | GP91: -3.15 | GQ91: -3.15 | GR91: -3.15 | GS91: -3.15 | GT91: -3.15 | GU91: -3.15 | GV91: -3.15 | GW91: -3.15 | GX91: -3.15 | GY91: -3.15 | GZ91: -3.15 | HA91: -3.15 | HB91: -3.15 | HC91: -3.15 | HD91: -3.15 | HE91: -3.15 | HF91: -3.15 | HG91: -3.15 | HH91: -3.15 | HI91: -3.15 | HJ91: -3.15 | HK91: -3.15 | HL91: -3.15 | HM91: -3.15 | HN91: -3.15 | HO91: -3.15 | HP91: -3.15 | HQ91: -3.15 | HR91: -3.15 | HS91: -3.15 | HT91: -3.15 | HU91: -3.15 | HV91: -3.15 | HW91: -3.15 | HX91: -3.15 | HY91: -3.15 | HZ91: -3.15 | IA91: -3.15 | IB91: -3.15 | IC91: -3.15 | ID91: -3.15 | IE91: -3.15 | IF91: -3.15 | IG91: -3.15 | IH91: -3.15 | II91: -3.15 | IJ91: -3.15 | IK91: -3.15 | IL91: -3.15 | IM91: -3.15 | IN91: -3.15 | IO91: -3.15 | IP91: -3.15 | IQ91: -3.15 | IR91: -3.15 | IS91: -3.15 | IT91: -3.15 | IU91: -3.15 | IV91: -3.15 | IW91: -3.15 | IX91: -3.15 | IY91: -3.15 | IZ91: -3.15 | JA91: -3.15 | JB91: -3.15 | JC91: -3.15 | JD91: -3.15 | JE91: -3.15 | JF91: -3.15 | JG91: -3.15 | JH91: -3.15 | JI91: -3.15 | JJ91: -3.15 | JK91: -3.15 | JL91: -3.15 | JM91: -3.15 | JN91: -3.15 | JO91: -3.15 | JP91: -3.15 | JQ91: -3.15 | JR91: -3.15 | JS91: -3.15 | JT91: -3.15 | JU91: -3.15 | JV91: -3.15 | JW91: -3.15 | JX91: -3.15 | JY91: -3.15 | JZ91: -3.15 | KA91: -3.15 | KB91: -3.15 | KC91: -3.15 | KD91: -3.15 | KE91: -3.15 | KF91: -3.15
E92: USD, real | J92: Downside case | K92: -3.675 | L92: -3.675 | M92: -3.675 | N92: -3.675 | O92: -3.675 | P92: -3.675 | Q92: -3.675 | R92: -3.675 | S92: -3.675 | T92: -3.675 | U92: -3.675 | V92: -3.675 | W92: -3.675 | X92: -3.675 | Y92: -3.675 | Z92: -3.675 | AA92: -3.675 | AB92: -3.675 | AC92: -3.675 | AD92: -3.675 | AE92: -3.675 | AF92: -3.675 | AG92: -3.675 | AH92: -3.675 | AI92: -3.675 | AJ92: -3.675 | AK92: -3.675 | AL92: -3.675 | AM92: -3.675 | AN92: -3.675 | AO92: -3.675 | AP92: -3.675 | AQ92: -3.675 | AR92: -3.675 | AS92: -3.675 | AT92: -3.675 | AU92: -3.675 | AV92: -3.675 | AW92: -3.675 | AX92: -3.675 | AY92: -3.675 | AZ92: -3.675 | BA92: -3.675 | BB92: -3.675 | BC92: -3.675 | BD92: -3.675 | BE92: -3.675 | BF92: -3.675 | BG92: -3.675 | BH92: -3.675 | BI92: -3.675 | BJ92: -3.675 | BK92: -3.675 | BL92: -3.675 | BM92: -3.675 | BN92: -3.675 | BO92: -3.675 | BP92: -3.675 | BQ92: -3.675 | BR92: -3.675 | BS92: -3.675 | BT92: -3.675 | BU92: -3.675 | BV92: -3.675 | BW92: -3.675 | BX92: -3.675 | BY92: -3.675 | BZ92: -3.675 | CA92: -3.675 | CB92: -3.675 | CC92: -3.675 | CD92: -3.675 | CE92: -3.675 | CF92: -3.675 | CG92: -3.675 | CH92: -3.675 | CI92: -3.675 | CJ92: -3.675 | CK92: -3.675 | CL92: -3.675 | CM92: -3.675 | CN92: -3.675 | CO92: -3.675 | CP92: -3.675 | CQ92: -3.675 | CR92: -3.675 | CS92: -3.675 | CT92: -3.675 | CU92: -3.675 | CV92: -3.675 | CW92: -3.675 | CX92: -3.675 | CY92: -3.675 | CZ92: -3.675 | DA92: -3.675 | DB92: -3.675 | DC92: -3.675 | DD92: -3.675 | DE92: -3.675 | DF92: -3.675 | DG92: -3.675 | DH92: -3.675 | DI92: -3.675 | DJ92: -3.675 | DK92: -3.675 | DL92: -3.675 | DM92: -3.675 | DN92: -3.675 | DO92: -3.675 | DP92: -3.675 | DQ92: -3.675 | DR92: -3.675 | DS92: -3.675 | DT92: -3.675 | DU92: -3.675 | DV92: -3.675 | DW92: -3.675 | DX92: -3.675 | DY92: -3.675 | DZ92: -3.675 | EA92: -3.675 | EB92: -3.675 | EC92: -3.675 | ED92: -3.675 | EE92: -3.675 | EF92: -3.675 | EG92: -3.675 | EH92: -3.675 | EI92: -3.675 | EJ92: -3.675 | EK92: -3.675 | EL92: -3.675 | EM92: -3.675 | EN92: -3.675 | EO92: -3.675 | EP92: -3.675 | EQ92: -3.675 | ER92: -3.675 | ES92: -3.675 | ET92: -3.675 | EU92: -3.675 | EV92: -3.675 | EW92: -3.675 | EX92: -3.675 | EY92: -3.675 | EZ92: -3.675 | FA92: -3.675 | FB92: -3.675 | FC92: -3.675 | FD92: -3.675 | FE92: -3.675 | FF92: -3.675 | FG92: -3.675 | FH92: -3.675 | FI92: -3.675 | FJ92: -3.675 | FK92: -3.675 | FL92: -3.675 | FM92: -3.675 | FN92: -3.675 | FO92: -3.675 | FP92: -3.675 | FQ92: -3.675 | FR92: -3.675 | FS92: -3.675 | FT92: -3.675 | FU92: -3.675 | FV92: -3.675 | FW92: -3.675 | FX92: -3.675 | FY92: -3.675 | FZ92: -3.675 | GA92: -3.675 | GB92: -3.675 | GC92: -3.675 | GD92: -3.675 | GE92: -3.675 | GF92: -3.675 | GG92: -3.675 | GH92: -3.675 | GI92: -3.675 | GJ92: -3.675 | GK92: -3.675 | GL92: -3.675 | GM92: -3.675 | GN92: -3.675 | GO92: -3.675 | GP92: -3.675 | GQ92: -3.675 | GR92: -3.675 | GS92: -3.675 | GT92: -3.675 | GU92: -3.675 | GV92: -3.675 | GW92: -3.675 | GX92: -3.675 | GY92: -3.675 | GZ92: -3.675 | HA92: -3.675 | HB92: -3.675 | HC92: -3.675 | HD92: -3.675 | HE92: -3.675 | HF92: -3.675 | HG92: -3.675 | HH92: -3.675 | HI92: -3.675 | HJ92: -3.675 | HK92: -3.675 | HL92: -3.675 | HM92: -3.675 | HN92: -3.675 | HO92: -3.675 | HP92: -3.675 | HQ92: -3.675 | HR92: -3.675 | HS92: -3.675 | HT92: -3.675 | HU92: -3.675 | HV92: -3.675 | HW92: -3.675 | HX92: -3.675 | HY92: -3.675 | HZ92: -3.675 | IA92: -3.675 | IB92: -3.675 | IC92: -3.675 | ID92: -3.675 | IE92: -3.675 | IF92: -3.675 | IG92: -3.675 | IH92: -3.675 | II92: -3.675 | IJ92: -3.675 | IK92: -3.675 | IL92: -3.675 | IM92: -3.675 | IN92: -3.675 | IO92: -3.675 | IP92: -3.675 | IQ92: -3.675 | IR92: -3.675 | IS92: -3.675 | IT92: -3.675 | IU92: -3.675 | IV92: -3.675 | IW92: -3.675 | IX92: -3.675 | IY92: -3.675 | IZ92: -3.675 | JA92: -3.675 | JB92: -3.675 | JC92: -3.675 | JD92: -3.675 | JE92: -3.675 | JF92: -3.675 | JG92: -3.675 | JH92: -3.675 | JI92: -3.675 | JJ92: -3.675 | JK92: -3.675 | JL92: -3.675 | JM92: -3.675 | JN92: -3.675 | JO92: -3.675 | JP92: -3.675 | JQ92: -3.675 | JR92: -3.675 | JS92: -3.675 | JT92: -3.675 | JU92: -3.675 | JV92: -3.675 | JW92: -3.675 | JX92: -3.675 | JY92: -3.675 | JZ92: -3.675 | KA92: -3.675 | KB92: -3.675 | KC92: -3.675 | KD92: -3.675 | KE92: -3.675 | KF92: -3.675
E93: USD, real | J93: [Spare]
E94: USD, real | J94: [Spare]
E95: USD, real | J95: [Spare]
E96: USD, real | J96: [Spare]
E97: USD, real | J97: [Spare]
E98: USD, real | J98: [Spare]
H100: Other Costs
J102: Chosen case | K102: =Control!H22 -> 1 | L102: {=INDEX(J106:J114,K102)} -> Base case
E103: USD, real | J103: Live | K103: {=INDEX(K106:K114,$K102)} -> -2.1 | L103: {=INDEX(L106:L114,$K102)} -> -2.1 | M103: {=INDEX(M106:M114,$K102)} -> -2.1 | N103: {=INDEX(N106:N114,$K102)} -> -2.1 | O103: {=INDEX(O106:O114,$K102)} -> -2.1 | P103: {=INDEX(P106:P114,$K102)} -> -2.1 | Q103: {=INDEX(Q106:Q114,$K102)} -> -2.1 | R103: {=INDEX(R106:R114,$K102)} -> -2.1 | ... KF103: {=INDEX(KF106:KF114,$K102)} -> -2.1
D104: 0 | E104: USD, real | J104: Bank Adjustment | K104: =K103*(1+$D104) -> -2.1 | L104: =L103*(1+$D104) -> -2.1 | M104: =M103*(1+$D104) -> -2.1 | N104: =N103*(1+$D104) -> -2.1 | O104: =O103*(1+$D104) -> -2.1 | P104: =P103*(1+$D104) -> -2.1 | Q104: =Q103*(1+$D104) -> -2.1 | R104: =R103*(1+$D104) -> -2.1 | ... KF104: =KF103*(1+$D104) -> -2.1
E106: USD, real | J106: Base case | K106: -2.1 | L106: -2.1 | M106: -2.1 | N106: -2.1 | O106: -2.1 | P106: -2.1 | Q106: -2.1 | R106: -2.1 | S106: -2.1 | T106: -2.1 | U106: -2.1 | V106: -2.1 | W106: -2.1 | X106: -2.1 | Y106: -2.1 | Z106: -2.1 | AA106: -2.1 | AB106: -2.1 | AC106: -2.1 | AD106: -2.1 | AE106: -2.1 | AF106: -2.1 | AG106: -2.1 | AH106: -2.1 | AI106: -2.1 | AJ106: -2.1 | AK106: -2.1 | AL106: -2.1 | AM106: -2.1 | AN106: -2.1 | AO106: -2.1 | AP106: -2.1 | AQ106: -2.1 | AR106: -2.1 | AS106: -2.1 | AT106: -2.1 | AU106: -2.1 | AV106: -2.1 | AW106: -2.1 | AX106: -2.1 | AY106: -2.1 | AZ106: -2.1 | BA106: -2.1 | BB106: -2.1 | BC106: -2.1 | BD106: -2.1 | BE106: -2.1 | BF106: -2.1 | BG106: -2.1 | BH106: -2.1 | BI106: -2.1 | BJ106: -2.1 | BK106: -2.1 | BL106: -2.1 | BM106: -2.1 | BN106: -2.1 | BO106: -2.1 | BP106: -2.1 | BQ106: -2.1 | BR106: -2.1 | BS106: -2.1 | BT106: -2.1 | BU106: -2.1 | BV106: -2.1 | BW106: -2.1 | BX106: -2.1 | BY106: -2.1 | BZ106: -2.1 | CA106: -2.1 | CB106: -2.1 | CC106: -2.1 | CD106: -2.1 | CE106: -2.1 | CF106: -2.1 | CG106: -2.1 | CH106: -2.1 | CI106: -2.1 | CJ106: -2.1 | CK106: -2.1 | CL106: -2.1 | CM106: -2.1 | CN106: -2.1 | CO106: -2.1 | CP106: -2.1 | CQ106: -2.1 | CR106: -2.1 | CS106: -2.1 | CT106: -2.1 | CU106: -2.1 | CV106: -2.1 | CW106: -2.1 | CX106: -2.1 | CY106: -2.1 | CZ106: -2.1 | DA106: -2.1 | DB106: -2.1 | DC106: -2.1 | DD106: -2.1 | DE106: -2.1 | DF106: -2.1 | DG106: -2.1 | DH106: -2.1 | DI106: -2.1 | DJ106: -2.1 | DK106: -2.1 | DL106: -2.1 | DM106: -2.1 | DN106: -2.1 | DO106: -2.1 | DP106: -2.1 | DQ106: -2.1 | DR106: -2.1 | DS106: -2.1 | DT106: -2.1 | DU106: -2.1 | DV106: -2.1 | DW106: -2.1 | DX106: -2.1 | DY106: -2.1 | DZ106: -2.1 | EA106: -2.1 | EB106: -2.1 | EC106: -2.1 | ED106: -2.1 | EE106: -2.1 | EF106: -2.1 | EG106: -2.1 | EH106: -2.1 | EI106: -2.1 | EJ106: -2.1 | EK106: -2.1 | EL106: -2.1 | EM106: -2.1 | EN106: -2.1 | EO106: -2.1 | EP106: -2.1 | EQ106: -2.1 | ER106: -2.1 | ES106: -2.1 | ET106: -2.1 | EU106: -2.1 | EV106: -2.1 | EW106: -2.1 | EX106: -2.1 | EY106: -2.1 | EZ106: -2.1 | FA106: -2.1 | FB106: -2.1 | FC106: -2.1 | FD106: -2.1 | FE106: -2.1 | FF106: -2.1 | FG106: -2.1 | FH106: -2.1 | FI106: -2.1 | FJ106: -2.1 | FK106: -2.1 | FL106: -2.1 | FM106: -2.1 | FN106: -2.1 | FO106: -2.1 | FP106: -2.1 | FQ106: -2.1 | FR106: -2.1 | FS106: -2.1 | FT106: -2.1 | FU106: -2.1 | FV106: -2.1 | FW106: -2.1 | FX106: -2.1 | FY106: -2.1 | FZ106: -2.1 | GA106: -2.1 | GB106: -2.1 | GC106: -2.1 | GD106: -2.1 | GE106: -2.1 | GF106: -2.1 | GG106: -2.1 | GH106: -2.1 | GI106: -2.1 | GJ106: -2.1 | GK106: -2.1 | GL106: -2.1 | GM106: -2.1 | GN106: -2.1 | GO106: -2.1 | GP106: -2.1 | GQ106: -2.1 | GR106: -2.1 | GS106: -2.1 | GT106: -2.1 | GU106: -2.1 | GV106: -2.1 | GW106: -2.1 | GX106: -2.1 | GY106: -2.1 | GZ106: -2.1 | HA106: -2.1 | HB106: -2.1 | HC106: -2.1 | HD106: -2.1 | HE106: -2.1 | HF106: -2.1 | HG106: -2.1 | HH106: -2.1 | HI106: -2.1 | HJ106: -2.1 | HK106: -2.1 | HL106: -2.1 | HM106: -2.1 | HN106: -2.1 | HO106: -2.1 | HP106: -2.1 | HQ106: -2.1 | HR106: -2.1 | HS106: -2.1 | HT106: -2.1 | HU106: -2.1 | HV106: -2.1 | HW106: -2.1 | HX106: -2.1 | HY106: -2.1 | HZ106: -2.1 | IA106: -2.1 | IB106: -2.1 | IC106: -2.1 | ID106: -2.1 | IE106: -2.1 | IF106: -2.1 | IG106: -2.1 | IH106: -2.1 | II106: -2.1 | IJ106: -2.1 | IK106: -2.1 | IL106: -2.1 | IM106: -2.1 | IN106: -2.1 | IO106: -2.1 | IP106: -2.1 | IQ106: -2.1 | IR106: -2.1 | IS106: -2.1 | IT106: -2.1 | IU106: -2.1 | IV106: -2.1 | IW106: -2.1 | IX106: -2.1 | IY106: -2.1 | IZ106: -2.1 | JA106: -2.1 | JB106: -2.1 | JC106: -2.1 | JD106: -2.1 | JE106: -2.1 | JF106: -2.1 | JG106: -2.1 | JH106: -2.1 | JI106: -2.1 | JJ106: -2.1 | JK106: -2.1 | JL106: -2.1 | JM106: -2.1 | JN106: -2.1 | JO106: -2.1 | JP106: -2.1 | JQ106: -2.1 | JR106: -2.1 | JS106: -2.1 | JT106: -2.1 | JU106: -2.1 | JV106: -2.1 | JW106: -2.1 | JX106: -2.1 | JY106: -2.1 | JZ106: -2.1 | KA106: -2.1 | KB106: -2.1 | KC106: -2.1 | KD106: -2.1 | KE106: -2.1 | KF106: -2.1
E107: USD, real | J107: Lender case | K107: -2.52 | L107: -2.52 | M107: -2.52 | N107: -2.52 | O107: -2.52 | P107: -2.52 | Q107: -2.52 | R107: -2.52 | S107: -2.52 | T107: -2.52 | U107: -2.52 | V107: -2.52 | W107: -2.52 | X107: -2.52 | Y107: -2.52 | Z107: -2.52 | AA107: -2.52 | AB107: -2.52 | AC107: -2.52 | AD107: -2.52 | AE107: -2.52 | AF107: -2.52 | AG107: -2.52 | AH107: -2.52 | AI107: -2.52 | AJ107: -2.52 | AK107: -2.52 | AL107: -2.52 | AM107: -2.52 | AN107: -2.52 | AO107: -2.52 | AP107: -2.52 | AQ107: -2.52 | AR107: -2.52 | AS107: -2.52 | AT107: -2.52 | AU107: -2.52 | AV107: -2.52 | AW107: -2.52 | AX107: -2.52 | AY107: -2.52 | AZ107: -2.52 | BA107: -2.52 | BB107: -2.52 | BC107: -2.52 | BD107: -2.52 | BE107: -2.52 | BF107: -2.52 | BG107: -2.52 | BH107: -2.52 | BI107: -2.52 | BJ107: -2.52 | BK107: -2.52 | BL107: -2.52 | BM107: -2.52 | BN107: -2.52 | BO107: -2.52 | BP107: -2.52 | BQ107: -2.52 | BR107: -2.52 | BS107: -2.52 | BT107: -2.52 | BU107: -2.52 | BV107: -2.52 | BW107: -2.52 | BX107: -2.52 | BY107: -2.52 | BZ107: -2.52 | CA107: -2.52 | CB107: -2.52 | CC107: -2.52 | CD107: -2.52 | CE107: -2.52 | CF107: -2.52 | CG107: -2.52 | CH107: -2.52 | CI107: -2.52 | CJ107: -2.52 | CK107: -2.52 | CL107: -2.52 | CM107: -2.52 | CN107: -2.52 | CO107: -2.52 | CP107: -2.52 | CQ107: -2.52 | CR107: -2.52 | CS107: -2.52 | CT107: -2.52 | CU107: -2.52 | CV107: -2.52 | CW107: -2.52 | CX107: -2.52 | CY107: -2.52 | CZ107: -2.52 | DA107: -2.52 | DB107: -2.52 | DC107: -2.52 | DD107: -2.52 | DE107: -2.52 | DF107: -2.52 | DG107: -2.52 | DH107: -2.52 | DI107: -2.52 | DJ107: -2.52 | DK107: -2.52 | DL107: -2.52 | DM107: -2.52 | DN107: -2.52 | DO107: -2.52 | DP107: -2.52 | DQ107: -2.52 | DR107: -2.52 | DS107: -2.52 | DT107: -2.52 | DU107: -2.52 | DV107: -2.52 | DW107: -2.52 | DX107: -2.52 | DY107: -2.52 | DZ107: -2.52 | EA107: -2.52 | EB107: -2.52 | EC107: -2.52 | ED107: -2.52 | EE107: -2.52 | EF107: -2.52 | EG107: -2.52 | EH107: -2.52 | EI107: -2.52 | EJ107: -2.52 | EK107: -2.52 | EL107: -2.52 | EM107: -2.52 | EN107: -2.52 | EO107: -2.52 | EP107: -2.52 | EQ107: -2.52 | ER107: -2.52 | ES107: -2.52 | ET107: -2.52 | EU107: -2.52 | EV107: -2.52 | EW107: -2.52 | EX107: -2.52 | EY107: -2.52 | EZ107: -2.52 | FA107: -2.52 | FB107: -2.52 | FC107: -2.52 | FD107: -2.52 | FE107: -2.52 | FF107: -2.52 | FG107: -2.52 | FH107: -2.52 | FI107: -2.52 | FJ107: -2.52 | FK107: -2.52 | FL107: -2.52 | FM107: -2.52 | FN107: -2.52 | FO107: -2.52 | FP107: -2.52 | FQ107: -2.52 | FR107: -2.52 | FS107: -2.52 | FT107: -2.52 | FU107: -2.52 | FV107: -2.52 | FW107: -2.52 | FX107: -2.52 | FY107: -2.52 | FZ107: -2.52 | GA107: -2.52 | GB107: -2.52 | GC107: -2.52 | GD107: -2.52 | GE107: -2.52 | GF107: -2.52 | GG107: -2.52 | GH107: -2.52 | GI107: -2.52 | GJ107: -2.52 | GK107: -2.52 | GL107: -2.52 | GM107: -2.52 | GN107: -2.52 | GO107: -2.52 | GP107: -2.52 | GQ107: -2.52 | GR107: -2.52 | GS107: -2.52 | GT107: -2.52 | GU107: -2.52 | GV107: -2.52 | GW107: -2.52 | GX107: -2.52 | GY107: -2.52 | GZ107: -2.52 | HA107: -2.52 | HB107: -2.52 | HC107: -2.52 | HD107: -2.52 | HE107: -2.52 | HF107: -2.52 | HG107: -2.52 | HH107: -2.52 | HI107: -2.52 | HJ107: -2.52 | HK107: -2.52 | HL107: -2.52 | HM107: -2.52 | HN107: -2.52 | HO107: -2.52 | HP107: -2.52 | HQ107: -2.52 | HR107: -2.52 | HS107: -2.52 | HT107: -2.52 | HU107: -2.52 | HV107: -2.52 | HW107: -2.52 | HX107: -2.52 | HY107: -2.52 | HZ107: -2.52 | IA107: -2.52 | IB107: -2.52 | IC107: -2.52 | ID107: -2.52 | IE107: -2.52 | IF107: -2.52 | IG107: -2.52 | IH107: -2.52 | II107: -2.52 | IJ107: -2.52 | IK107: -2.52 | IL107: -2.52 | IM107: -2.52 | IN107: -2.52 | IO107: -2.52 | IP107: -2.52 | IQ107: -2.52 | IR107: -2.52 | IS107: -2.52 | IT107: -2.52 | IU107: -2.52 | IV107: -2.52 | IW107: -2.52 | IX107: -2.52 | IY107: -2.52 | IZ107: -2.52 | JA107: -2.52 | JB107: -2.52 | JC107: -2.52 | JD107: -2.52 | JE107: -2.52 | JF107: -2.52 | JG107: -2.52 | JH107: -2.52 | JI107: -2.52 | JJ107: -2.52 | JK107: -2.52 | JL107: -2.52 | JM107: -2.52 | JN107: -2.52 | JO107: -2.52 | JP107: -2.52 | JQ107: -2.52 | JR107: -2.52 | JS107: -2.52 | JT107: -2.52 | JU107: -2.52 | JV107: -2.52 | JW107: -2.52 | JX107: -2.52 | JY107: -2.52 | JZ107: -2.52 | KA107: -2.52 | KB107: -2.52 | KC107: -2.52 | KD107: -2.52 | KE107: -2.52 | KF107: -2.52
E108: USD, real | J108: Downside case | K108: -2.94 | L108: -2.94 | M108: -2.94 | N108: -2.94 | O108: -2.94 | P108: -2.94 | Q108: -2.94 | R108: -2.94 | S108: -2.94 | T108: -2.94 | U108: -2.94 | V108: -2.94 | W108: -2.94 | X108: -2.94 | Y108: -2.94 | Z108: -2.94 | AA108: -2.94 | AB108: -2.94 | AC108: -2.94 | AD108: -2.94 | AE108: -2.94 | AF108: -2.94 | AG108: -2.94 | AH108: -2.94 | AI108: -2.94 | AJ108: -2.94 | AK108: -2.94 | AL108: -2.94 | AM108: -2.94 | AN108: -2.94 | AO108: -2.94 | AP108: -2.94 | AQ108: -2.94 | AR108: -2.94 | AS108: -2.94 | AT108: -2.94 | AU108: -2.94 | AV108: -2.94 | AW108: -2.94 | AX108: -2.94 | AY108: -2.94 | AZ108: -2.94 | BA108: -2.94 | BB108: -2.94 | BC108: -2.94 | BD108: -2.94 | BE108: -2.94 | BF108: -2.94 | BG108: -2.94 | BH108: -2.94 | BI108: -2.94 | BJ108: -2.94 | BK108: -2.94 | BL108: -2.94 | BM108: -2.94 | BN108: -2.94 | BO108: -2.94 | BP108: -2.94 | BQ108: -2.94 | BR108: -2.94 | BS108: -2.94 | BT108: -2.94 | BU108: -2.94 | BV108: -2.94 | BW108: -2.94 | BX108: -2.94 | BY108: -2.94 | BZ108: -2.94 | CA108: -2.94 | CB108: -2.94 | CC108: -2.94 | CD108: -2.94 | CE108: -2.94 | CF108: -2.94 | CG108: -2.94 | CH108: -2.94 | CI108: -2.94 | CJ108: -2.94 | CK108: -2.94 | CL108: -2.94 | CM108: -2.94 | CN108: -2.94 | CO108: -2.94 | CP108: -2.94 | CQ108: -2.94 | CR108: -2.94 | CS108: -2.94 | CT108: -2.94 | CU108: -2.94 | CV108: -2.94 | CW108: -2.94 | CX108: -2.94 | CY108: -2.94 | CZ108: -2.94 | DA108: -2.94 | DB108: -2.94 | DC108: -2.94 | DD108: -2.94 | DE108: -2.94 | DF108: -2.94 | DG108: -2.94 | DH108: -2.94 | DI108: -2.94 | DJ108: -2.94 | DK108: -2.94 | DL108: -2.94 | DM108: -2.94 | DN108: -2.94 | DO108: -2.94 | DP108: -2.94 | DQ108: -2.94 | DR108: -2.94 | DS108: -2.94 | DT108: -2.94 | DU108: -2.94 | DV108: -2.94 | DW108: -2.94 | DX108: -2.94 | DY108: -2.94 | DZ108: -2.94 | EA108: -2.94 | EB108: -2.94 | EC108: -2.94 | ED108: -2.94 | EE108: -2.94 | EF108: -2.94 | EG108: -2.94 | EH108: -2.94 | EI108: -2.94 | EJ108: -2.94 | EK108: -2.94 | EL108: -2.94 | EM108: -2.94 | EN108: -2.94 | EO108: -2.94 | EP108: -2.94 | EQ108: -2.94 | ER108: -2.94 | ES108: -2.94 | ET108: -2.94 | EU108: -2.94 | EV108: -2.94 | EW108: -2.94 | EX108: -2.94 | EY108: -2.94 | EZ108: -2.94 | FA108: -2.94 | FB108: -2.94 | FC108: -2.94 | FD108: -2.94 | FE108: -2.94 | FF108: -2.94 | FG108: -2.94 | FH108: -2.94 | FI108: -2.94 | FJ108: -2.94 | FK108: -2.94 | FL108: -2.94 | FM108: -2.94 | FN108: -2.94 | FO108: -2.94 | FP108: -2.94 | FQ108: -2.94 | FR108: -2.94 | FS108: -2.94 | FT108: -2.94 | FU108: -2.94 | FV108: -2.94 | FW108: -2.94 | FX108: -2.94 | FY108: -2.94 | FZ108: -2.94 | GA108: -2.94 | GB108: -2.94 | GC108: -2.94 | GD108: -2.94 | GE108: -2.94 | GF108: -2.94 | GG108: -2.94 | GH108: -2.94 | GI108: -2.94 | GJ108: -2.94 | GK108: -2.94 | GL108: -2.94 | GM108: -2.94 | GN108: -2.94 | GO108: -2.94 | GP108: -2.94 | GQ108: -2.94 | GR108: -2.94 | GS108: -2.94 | GT108: -2.94 | GU108: -2.94 | GV108: -2.94 | GW108: -2.94 | GX108: -2.94 | GY108: -2.94 | GZ108: -2.94 | HA108: -2.94 | HB108: -2.94 | HC108: -2.94 | HD108: -2.94 | HE108: -2.94 | HF108: -2.94 | HG108: -2.94 | HH108: -2.94 | HI108: -2.94 | HJ108: -2.94 | HK108: -2.94 | HL108: -2.94 | HM108: -2.94 | HN108: -2.94 | HO108: -2.94 | HP108: -2.94 | HQ108: -2.94 | HR108: -2.94 | HS108: -2.94 | HT108: -2.94 | HU108: -2.94 | HV108: -2.94 | HW108: -2.94 | HX108: -2.94 | HY108: -2.94 | HZ108: -2.94 | IA108: -2.94 | IB108: -2.94 | IC108: -2.94 | ID108: -2.94 | IE108: -2.94 | IF108: -2.94 | IG108: -2.94 | IH108: -2.94 | II108: -2.94 | IJ108: -2.94 | IK108: -2.94 | IL108: -2.94 | IM108: -2.94 | IN108: -2.94 | IO108: -2.94 | IP108: -2.94 | IQ108: -2.94 | IR108: -2.94 | IS108: -2.94 | IT108: -2.94 | IU108: -2.94 | IV108: -2.94 | IW108: -2.94 | IX108: -2.94 | IY108: -2.94 | IZ108: -2.94 | JA108: -2.94 | JB108: -2.94 | JC108: -2.94 | JD108: -2.94 | JE108: -2.94 | JF108: -2.94 | JG108: -2.94 | JH108: -2.94 | JI108: -2.94 | JJ108: -2.94 | JK108: -2.94 | JL108: -2.94 | JM108: -2.94 | JN108: -2.94 | JO108: -2.94 | JP108: -2.94 | JQ108: -2.94 | JR108: -2.94 | JS108: -2.94 | JT108: -2.94 | JU108: -2.94 | JV108: -2.94 | JW108: -2.94 | JX108: -2.94 | JY108: -2.94 | JZ108: -2.94 | KA108: -2.94 | KB108: -2.94 | KC108: -2.94 | KD108: -2.94 | KE108: -2.94 | KF108: -2.94
E109: USD, real | J109: [Spare]
E110: USD, real | J110: [Spare]
E111: USD, real | J111: [Spare]
E112: USD, real | J112: [Spare]
E113: USD, real | J113: [Spare]
E114: USD, real | J114: [Spare]
H116: Capex
J118: Chosen case | K118: =Control!H23 -> 1 | L118: {=INDEX(J122:J130,K118)} -> Base case
E119: USD, real | J119: Live | K119: {=INDEX(K122:K130,$K118)} -> 1 | L119: {=INDEX(L122:L130,$K118)} -> 1 | M119: {=INDEX(M122:M130,$K118)} -> 1 | N119: {=INDEX(N122:N130,$K118)} -> 1 | O119: {=INDEX(O122:O130,$K118)} -> 1 | P119: {=INDEX(P122:P130,$K118)} -> 1 | Q119: {=INDEX(Q122:Q130,$K118)} -> 1 | R119: {=INDEX(R122:R130,$K118)} -> 1 | ... KF119: {=INDEX(KF122:KF130,$K118)} -> 1
D120: 0 | E120: USD, real | J120: Bank Adjustment | K120: =K119*(1+$D120) -> 1 | L120: =L119*(1+$D120) -> 1 | M120: =M119*(1+$D120) -> 1 | N120: =N119*(1+$D120) -> 1 | O120: =O119*(1+$D120) -> 1 | P120: =P119*(1+$D120) -> 1 | Q120: =Q119*(1+$D120) -> 1 | R120: =R119*(1+$D120) -> 1 | ... KF120: =KF119*(1+$D120) -> 1
E122: USD, real | J122: Base case | K122: 1 | L122: 1 | M122: 1 | N122: 1 | O122: 1 | P122: 1 | Q122: 1 | R122: 1 | S122: 1 | T122: 1 | U122: 1 | V122: 1 | W122: 1 | X122: 1 | Y122: 1 | Z122: 1 | AA122: 1 | AB122: 1 | AC122: 1 | AD122: 1 | AE122: 1 | AF122: 1 | AG122: 1 | AH122: 1 | AI122: 1 | AJ122: 1 | AK122: 1 | AL122: 1 | AM122: 1 | AN122: 1 | AO122: 1 | AP122: 1 | AQ122: 1 | AR122: 1 | AS122: 1 | AT122: 1 | AU122: 1 | AV122: 1 | AW122: 1 | AX122: 1 | AY122: 1 | AZ122: 1 | BA122: 1 | BB122: 1 | BC122: 1 | BD122: 1 | BE122: 1 | BF122: 1 | BG122: 1 | BH122: 1 | BI122: 1 | BJ122: 1 | BK122: 1 | BL122: 1 | BM122: 1 | BN122: 1 | BO122: 1 | BP122: 1 | BQ122: 1 | BR122: 1 | BS122: 1 | BT122: 1 | BU122: 1 | BV122: 1 | BW122: 1 | BX122: 1 | BY122: 1 | BZ122: 1 | CA122: 1 | CB122: 1 | CC122: 1 | CD122: 1 | CE122: 1 | CF122: 1 | CG122: 1 | CH122: 1 | CI122: 1 | CJ122: 1 | CK122: 1 | CL122: 1 | CM122: 1 | CN122: 1 | CO122: 1 | CP122: 1 | CQ122: 1 | CR122: 1 | CS122: 1 | CT122: 1 | CU122: 1 | CV122: 1 | CW122: 1 | CX122: 1 | CY122: 1 | CZ122: 1 | DA122: 1 | DB122: 1 | DC122: 1 | DD122: 1 | DE122: 1 | DF122: 1 | DG122: 1 | DH122: 1 | DI122: 1 | DJ122: 1 | DK122: 1 | DL122: 1 | DM122: 1 | DN122: 1 | DO122: 1 | DP122: 1 | DQ122: 1 | DR122: 1 | DS122: 1 | DT122: 1 | DU122: 1 | DV122: 1 | DW122: 1 | DX122: 1 | DY122: 1 | DZ122: 1 | EA122: 1 | EB122: 1 | EC122: 1 | ED122: 1 | EE122: 1 | EF122: 1 | EG122: 1 | EH122: 1 | EI122: 1 | EJ122: 1 | EK122: 1 | EL122: 1 | EM122: 1 | EN122: 1 | EO122: 1 | EP122: 1 | EQ122: 1 | ER122: 1 | ES122: 1 | ET122: 1 | EU122: 1 | EV122: 1 | EW122: 1 | EX122: 1 | EY122: 1 | EZ122: 1 | FA122: 1 | FB122: 1 | FC122: 1 | FD122: 1 | FE122: 1 | FF122: 1 | FG122: 1 | FH122: 1 | FI122: 1 | FJ122: 1 | FK122: 1 | FL122: 1 | FM122: 1 | FN122: 1 | FO122: 1 | FP122: 1 | FQ122: 1 | FR122: 1 | FS122: 1 | FT122: 1 | FU122: 1 | FV122: 1 | FW122: 1 | FX122: 1 | FY122: 1 | FZ122: 1 | GA122: 1 | GB122: 1 | GC122: 1 | GD122: 1 | GE122: 1 | GF122: 1 | GG122: 1 | GH122: 1 | GI122: 1 | GJ122: 1 | GK122: 1 | GL122: 1 | GM122: 1 | GN122: 1 | GO122: 1 | GP122: 1 | GQ122: 1 | GR122: 1 | GS122: 1 | GT122: 1 | GU122: 1 | GV122: 1 | GW122: 1 | GX122: 1 | GY122: 1 | GZ122: 1 | HA122: 1 | HB122: 1 | HC122: 1 | HD122: 1 | HE122: 1 | HF122: 1 | HG122: 1 | HH122: 1 | HI122: 1 | HJ122: 1 | HK122: 1 | HL122: 1 | HM122: 1 | HN122: 1 | HO122: 1 | HP122: 1 | HQ122: 1 | HR122: 1 | HS122: 1 | HT122: 1 | HU122: 1 | HV122: 1 | HW122: 1 | HX122: 1 | HY122: 1 | HZ122: 1 | IA122: 1 | IB122: 1 | IC122: 1 | ID122: 1 | IE122: 1 | IF122: 1 | IG122: 1 | IH122: 1 | II122: 1 | IJ122: 1 | IK122: 1 | IL122: 1 | IM122: 1 | IN122: 1 | IO122: 1 | IP122: 1 | IQ122: 1 | IR122: 1 | IS122: 1 | IT122: 1 | IU122: 1 | IV122: 1 | IW122: 1 | IX122: 1 | IY122: 1 | IZ122: 1 | JA122: 1 | JB122: 1 | JC122: 1 | JD122: 1 | JE122: 1 | JF122: 1 | JG122: 1 | JH122: 1 | JI122: 1 | JJ122: 1 | JK122: 1 | JL122: 1 | JM122: 1 | JN122: 1 | JO122: 1 | JP122: 1 | JQ122: 1 | JR122: 1 | JS122: 1 | JT122: 1 | JU122: 1 | JV122: 1 | JW122: 1 | JX122: 1 | JY122: 1 | JZ122: 1 | KA122: 1 | KB122: 1 | KC122: 1 | KD122: 1 | KE122: 1 | KF122: 1
E123: USD, real | J123: Lender case | K123: 1.5 | L123: 1.5 | M123: 1.5 | N123: 1.5 | O123: 1.5 | P123: 1.5 | Q123: 1.5 | R123: 1.5 | S123: 1.5 | T123: 1.5 | U123: 1.5 | V123: 1.5 | W123: 1.5 | X123: 1.5 | Y123: 1.5 | Z123: 1.5 | AA123: 1.5 | AB123: 1.5 | AC123: 1.5 | AD123: 1.5 | AE123: 1.5 | AF123: 1.5 | AG123: 1.5 | AH123: 1.5 | AI123: 1.5 | AJ123: 1.5 | AK123: 1.5 | AL123: 1.5 | AM123: 1.5 | AN123: 1.5 | AO123: 1.5 | AP123: 1.5 | AQ123: 1.5 | AR123: 1.5 | AS123: 1.5 | AT123: 1.5 | AU123: 1.5 | AV123: 1.5 | AW123: 1.5 | AX123: 1.5 | AY123: 1.5 | AZ123: 1.5 | BA123: 1.5 | BB123: 1.5 | BC123: 1.5 | BD123: 1.5 | BE123: 1.5 | BF123: 1.5 | BG123: 1.5 | BH123: 1.5 | BI123: 1.5 | BJ123: 1.5 | BK123: 1.5 | BL123: 1.5 | BM123: 1.5 | BN123: 1.5 | BO123: 1.5 | BP123: 1.5 | BQ123: 1.5 | BR123: 1.5 | BS123: 1.5 | BT123: 1.5 | BU123: 1.5 | BV123: 1.5 | BW123: 1.5 | BX123: 1.5 | BY123: 1.5 | BZ123: 1.5 | CA123: 1.5 | CB123: 1.5 | CC123: 1.5 | CD123: 1.5 | CE123: 1.5 | CF123: 1.5 | CG123: 1.5 | CH123: 1.5 | CI123: 1.5 | CJ123: 1.5 | CK123: 1.5 | CL123: 1.5 | CM123: 1.5 | CN123: 1.5 | CO123: 1.5 | CP123: 1.5 | CQ123: 1.5 | CR123: 1.5 | CS123: 1.5 | CT123: 1.5 | CU123: 1.5 | CV123: 1.5 | CW123: 1.5 | CX123: 1.5 | CY123: 1.5 | CZ123: 1.5 | DA123: 1.5 | DB123: 1.5 | DC123: 1.5 | DD123: 1.5 | DE123: 1.5 | DF123: 1.5 | DG123: 1.5 | DH123: 1.5 | DI123: 1.5 | DJ123: 1.5 | DK123: 1.5 | DL123: 1.5 | DM123: 1.5 | DN123: 1.5 | DO123: 1.5 | DP123: 1.5 | DQ123: 1.5 | DR123: 1.5 | DS123: 1.5 | DT123: 1.5 | DU123: 1.5 | DV123: 1.5 | DW123: 1.5 | DX123: 1.5 | DY123: 1.5 | DZ123: 1.5 | EA123: 1.5 | EB123: 1.5 | EC123: 1.5 | ED123: 1.5 | EE123: 1.5 | EF123: 1.5 | EG123: 1.5 | EH123: 1.5 | EI123: 1.5 | EJ123: 1.5 | EK123: 1.5 | EL123: 1.5 | EM123: 1.5 | EN123: 1.5 | EO123: 1.5 | EP123: 1.5 | EQ123: 1.5 | ER123: 1.5 | ES123: 1.5 | ET123: 1.5 | EU123: 1.5 | EV123: 1.5 | EW123: 1.5 | EX123: 1.5 | EY123: 1.5 | EZ123: 1.5 | FA123: 1.5 | FB123: 1.5 | FC123: 1.5 | FD123: 1.5 | FE123: 1.5 | FF123: 1.5 | FG123: 1.5 | FH123: 1.5 | FI123: 1.5 | FJ123: 1.5 | FK123: 1.5 | FL123: 1.5 | FM123: 1.5 | FN123: 1.5 | FO123: 1.5 | FP123: 1.5 | FQ123: 1.5 | FR123: 1.5 | FS123: 1.5 | FT123: 1.5 | FU123: 1.5 | FV123: 1.5 | FW123: 1.5 | FX123: 1.5 | FY123: 1.5 | FZ123: 1.5 | GA123: 1.5 | GB123: 1.5 | GC123: 1.5 | GD123: 1.5 | GE123: 1.5 | GF123: 1.5 | GG123: 1.5 | GH123: 1.5 | GI123: 1.5 | GJ123: 1.5 | GK123: 1.5 | GL123: 1.5 | GM123: 1.5 | GN123: 1.5 | GO123: 1.5 | GP123: 1.5 | GQ123: 1.5 | GR123: 1.5 | GS123: 1.5 | GT123: 1.5 | GU123: 1.5 | GV123: 1.5 | GW123: 1.5 | GX123: 1.5 | GY123: 1.5 | GZ123: 1.5 | HA123: 1.5 | HB123: 1.5 | HC123: 1.5 | HD123: 1.5 | HE123: 1.5 | HF123: 1.5 | HG123: 1.5 | HH123: 1.5 | HI123: 1.5 | HJ123: 1.5 | HK123: 1.5 | HL123: 1.5 | HM123: 1.5 | HN123: 1.5 | HO123: 1.5 | HP123: 1.5 | HQ123: 1.5 | HR123: 1.5 | HS123: 1.5 | HT123: 1.5 | HU123: 1.5 | HV123: 1.5 | HW123: 1.5 | HX123: 1.5 | HY123: 1.5 | HZ123: 1.5 | IA123: 1.5 | IB123: 1.5 | IC123: 1.5 | ID123: 1.5 | IE123: 1.5 | IF123: 1.5 | IG123: 1.5 | IH123: 1.5 | II123: 1.5 | IJ123: 1.5 | IK123: 1.5 | IL123: 1.5 | IM123: 1.5 | IN123: 1.5 | IO123: 1.5 | IP123: 1.5 | IQ123: 1.5 | IR123: 1.5 | IS123: 1.5 | IT123: 1.5 | IU123: 1.5 | IV123: 1.5 | IW123: 1.5 | IX123: 1.5 | IY123: 1.5 | IZ123: 1.5 | JA123: 1.5 | JB123: 1.5 | JC123: 1.5 | JD123: 1.5 | JE123: 1.5 | JF123: 1.5 | JG123: 1.5 | JH123: 1.5 | JI123: 1.5 | JJ123: 1.5 | JK123: 1.5 | JL123: 1.5 | JM123: 1.5 | JN123: 1.5 | JO123: 1.5 | JP123: 1.5 | JQ123: 1.5 | JR123: 1.5 | JS123: 1.5 | JT123: 1.5 | JU123: 1.5 | JV123: 1.5 | JW123: 1.5 | JX123: 1.5 | JY123: 1.5 | JZ123: 1.5 | KA123: 1.5 | KB123: 1.5 | KC123: 1.5 | KD123: 1.5 | KE123: 1.5 | KF123: 1.5
E124: USD, real | J124: Downside case | K124: 2 | L124: 2 | M124: 2 | N124: 2 | O124: 2 | P124: 2 | Q124: 2 | R124: 2 | S124: 2 | T124: 2 | U124: 2 | V124: 2 | W124: 2 | X124: 2 | Y124: 2 | Z124: 2 | AA124: 2 | AB124: 2 | AC124: 2 | AD124: 2 | AE124: 2 | AF124: 2 | AG124: 2 | AH124: 2 | AI124: 2 | AJ124: 2 | AK124: 2 | AL124: 2 | AM124: 2 | AN124: 2 | AO124: 2 | AP124: 2 | AQ124: 2 | AR124: 2 | AS124: 2 | AT124: 2 | AU124: 2 | AV124: 2 | AW124: 2 | AX124: 2 | AY124: 2 | AZ124: 2 | BA124: 2 | BB124: 2 | BC124: 2 | BD124: 2 | BE124: 2 | BF124: 2 | BG124: 2 | BH124: 2 | BI124: 2 | BJ124: 2 | BK124: 2 | BL124: 2 | BM124: 2 | BN124: 2 | BO124: 2 | BP124: 2 | BQ124: 2 | BR124: 2 | BS124: 2 | BT124: 2 | BU124: 2 | BV124: 2 | BW124: 2 | BX124: 2 | BY124: 2 | BZ124: 2 | CA124: 2 | CB124: 2 | CC124: 2 | CD124: 2 | CE124: 2 | CF124: 2 | CG124: 2 | CH124: 2 | CI124: 2 | CJ124: 2 | CK124: 2 | CL124: 2 | CM124: 2 | CN124: 2 | CO124: 2 | CP124: 2 | CQ124: 2 | CR124: 2 | CS124: 2 | CT124: 2 | CU124: 2 | CV124: 2 | CW124: 2 | CX124: 2 | CY124: 2 | CZ124: 2 | DA124: 2 | DB124: 2 | DC124: 2 | DD124: 2 | DE124: 2 | DF124: 2 | DG124: 2 | DH124: 2 | DI124: 2 | DJ124: 2 | DK124: 2 | DL124: 2 | DM124: 2 | DN124: 2 | DO124: 2 | DP124: 2 | DQ124: 2 | DR124: 2 | DS124: 2 | DT124: 2 | DU124: 2 | DV124: 2 | DW124: 2 | DX124: 2 | DY124: 2 | DZ124: 2 | EA124: 2 | EB124: 2 | EC124: 2 | ED124: 2 | EE124: 2 | EF124: 2 | EG124: 2 | EH124: 2 | EI124: 2 | EJ124: 2 | EK124: 2 | EL124: 2 | EM124: 2 | EN124: 2 | EO124: 2 | EP124: 2 | EQ124: 2 | ER124: 2 | ES124: 2 | ET124: 2 | EU124: 2 | EV124: 2 | EW124: 2 | EX124: 2 | EY124: 2 | EZ124: 2 | FA124: 2 | FB124: 2 | FC124: 2 | FD124: 2 | FE124: 2 | FF124: 2 | FG124: 2 | FH124: 2 | FI124: 2 | FJ124: 2 | FK124: 2 | FL124: 2 | FM124: 2 | FN124: 2 | FO124: 2 | FP124: 2 | FQ124: 2 | FR124: 2 | FS124: 2 | FT124: 2 | FU124: 2 | FV124: 2 | FW124: 2 | FX124: 2 | FY124: 2 | FZ124: 2 | GA124: 2 | GB124: 2 | GC124: 2 | GD124: 2 | GE124: 2 | GF124: 2 | GG124: 2 | GH124: 2 | GI124: 2 | GJ124: 2 | GK124: 2 | GL124: 2 | GM124: 2 | GN124: 2 | GO124: 2 | GP124: 2 | GQ124: 2 | GR124: 2 | GS124: 2 | GT124: 2 | GU124: 2 | GV124: 2 | GW124: 2 | GX124: 2 | GY124: 2 | GZ124: 2 | HA124: 2 | HB124: 2 | HC124: 2 | HD124: 2 | HE124: 2 | HF124: 2 | HG124: 2 | HH124: 2 | HI124: 2 | HJ124: 2 | HK124: 2 | HL124: 2 | HM124: 2 | HN124: 2 | HO124: 2 | HP124: 2 | HQ124: 2 | HR124: 2 | HS124: 2 | HT124: 2 | HU124: 2 | HV124: 2 | HW124: 2 | HX124: 2 | HY124: 2 | HZ124: 2 | IA124: 2 | IB124: 2 | IC124: 2 | ID124: 2 | IE124: 2 | IF124: 2 | IG124: 2 | IH124: 2 | II124: 2 | IJ124: 2 | IK124: 2 | IL124: 2 | IM124: 2 | IN124: 2 | IO124: 2 | IP124: 2 | IQ124: 2 | IR124: 2 | IS124: 2 | IT124: 2 | IU124: 2 | IV124: 2 | IW124: 2 | IX124: 2 | IY124: 2 | IZ124: 2 | JA124: 2 | JB124: 2 | JC124: 2 | JD124: 2 | JE124: 2 | JF124: 2 | JG124: 2 | JH124: 2 | JI124: 2 | JJ124: 2 | JK124: 2 | JL124: 2 | JM124: 2 | JN124: 2 | JO124: 2 | JP124: 2 | JQ124: 2 | JR124: 2 | JS124: 2 | JT124: 2 | JU124: 2 | JV124: 2 | JW124: 2 | JX124: 2 | JY124: 2 | JZ124: 2 | KA124: 2 | KB124: 2 | KC124: 2 | KD124: 2 | KE124: 2 | KF124: 2
E125: USD, real | J125: [Spare]
...

Sheet Control
B2: Metrics | D2: Basic Financial Model
D3: =MID(CELL("filename",A1),FIND("]",CELL("filename",A1))+1,255) -> Control
B4: Units | D4: ="Financial Scenario: "&H10 -> Financial Scenario: Base Case
D7: Scenario Selection | H7: LIVE
G9: Case Number | H9: 1 | J9: 1 | K9: 2 | L9: 3 | M9: 4 | N9: 5 | O9: 6 | P9: 7 | Q9: 8 | R9: 9
G10: Case Name | H10: {=INDEX(J10:R10,,$H$9)} -> Base Case | J10: Base Case | K10: Modelled | L10: [Spare 3] | M10: [Spare 4] | N10: [Spare 5] | O10: [Spare 6] | P10: [Spare 7] | Q10: [Spare 8] | R10: [Spare 9]
D12: Model Assumptions
E14: Model Input Assumptions
F16: Input Assumptions
G17: Sales Volume | H17: {=INDEX(J17:R17,,$H$9)} -> 1 | J17: 1 | K17: 2 | L17: 3 | M17: 3 | N17: 1 | O17: 1 | P17: 1 | Q17: 1 | R17: 1
G18: Sales Price | H18: {=INDEX(J18:R18,,$H$9)} -> 1 | J18: 1 | K18: 2 | L18: 3 | M18: 3 | N18: 1 | O18: 1 | P18: 1 | Q18: 1 | R18: 1
G19: Unit Cost | H19: {=INDEX(J19:R19,,$H$9)} -> 1 | J19: 1 | K19: 2 | L19: 3 | M19: 3 | N19: 1 | O19: 1 | P19: 1 | Q19: 1 | R19: 1
G20: Fixed Costs | H20: {=INDEX(J20:R20,,$H$9)} -> 1 | J20: 1 | K20: 2 | L20: 3 | M20: 3 | N20: 1 | O20: 1 | P20: 1 | Q20: 1 | R20: 1
G21: SG&A | H21: {=INDEX(J21:R21,,$H$9)} -> 1 | J21: 1 | K21: 2 | L21: 3 | M21: 4 | N21: 1 | O21: 1 | P21: 1 | Q21: 1 | R21: 1
G22: Other Costs | H22: {=INDEX(J22:R22,,$H$9)} -> 1 | J22: 1 | K22: 2 | L22: 3 | M22: 4 | N22: 1 | O22: 1 | P22: 1 | Q22: 1 | R22: 1
G23: Capex | H23: {=INDEX(J23:R23,,$H$9)} -> 1 | J23: 1 | K23: 2 | L23: 3 | M23: 4 | N23: 1 | O23: 1 | P23: 1 | Q23: 1 | R23: 1
G24: Tax | H24: {=INDEX(J24:R24,,$H$9)} -> 1 | J24: 1 | K24: 2 | L24: 3 | M24: 4 | N24: 1 | O24: 1 | P24: 1 | Q24: 1 | R24: 1
G25: SOFR | H25: {=INDEX(J25:R25,,$H$9)} -> 1 | J25: 1 | K25: 2 | L25: 3 | M25: 4 | N25: 1 | O25: 1 | P25: 1 | Q25: 1 | R25: 1
D27: Financing
E29: Credit Metrics
F31: Financial Covenants
B32: #x | G32: DSCR Covenant | H32: {=INDEX(J32:R32,,$H$9)} -> 1.25 | J32: 1.25 | K32: 1.25 | L32: 1.25 | M32: 1.25 | N32: 1.25 | O32: 1.25 | P32: 1.25 | Q32: 1.25 | R32: 1.25
B33: % | G33: Gearing Covenant | H33: {=INDEX(J33:R33,,$H$9)} -> 0.4 | J33: 0.4 | K33: 0.4 | L33: 0.4 | M33: 0.4 | N33: 0.4 | O33: 0.4 | P33: 0.4 | Q33: 0.4 | R33: 0.4
B34: USDm | G34: Min Cash Balance | H34: {=INDEX(J34:R34,,$H$9)} -> 100 | J34: 100 | K34: 100 | L34: 100 | M34: 100 | N34: 100 | O34: 100 | P34: 100 | Q34: 100 | R34: 100
E36: Facility
F38: Existing Term Loan
B39: Date | G39: Establishment Date | H39: {=INDEX(J39:R39,,$H$9)} -> 45565 | J39: =DATE(2024,9,30) -> 45565 | K39: =DATE(2024,9,30) -> 45565 | L39: =DATE(2024,9,30) -> 45565 | M39: =DATE(2024,9,30) -> 45565 | N39: =DATE(2024,9,30) -> 45565 | O39: =DATE(2024,9,30) -> 45565 | P39: =DATE(2024,9,30) -> 45565 | Q39: =DATE(2024,9,30) -> 45565 | R39: =DATE(2024,9,30) -> 45565
B40: USDm | G40: Facility Size | H40: {=INDEX(J40:R40,,$H$9)} -> 350 | J40: 350 | K40: 350 | L40: 350 | M40: 350 | N40: 350 | O40: 350 | P40: 350 | Q40: 350 | R40: 350
B41: Date | G41: Facility Maturity Date | H41: {=INDEX(J41:R41,,$H$9)} -> 47391 | J41: =DATE(2029,9,30) -> 47391 | K41: =DATE(2029,9,30) -> 47391 | L41: =DATE(2029,9,30) -> 47391 | M41: =DATE(2029,9,30) -> 47391 | N41: =DATE(2029,9,30) -> 47391 | O41: =DATE(2029,9,30) -> 47391 | P41: =DATE(2029,9,30) -> 47391 | Q41: =DATE(2029,9,30) -> 47391 | R41: =DATE(2029,9,30) -> 47391
B42: Text | G42: Reference Rate | H42: {=INDEX(J42:R42,,$H$9)} -> SOFR | J42: SOFR | K42: SOFR | L42: SOFR | M42: SOFR | N42: SOFR | O42: SOFR | P42: SOFR | Q42: SOFR | R42: SOFR
B43: Perc | G43: Margin | H43: {=INDEX(J43:R43,,$H$9)} -> 0.045 | J43: 0.045 | K43: 0.045 | L43: 0.045 | M43: 0.045 | N43: 0.045 | O43: 0.045 | P43: 0.045 | Q43: 0.045 | R43: 0.045
B44: USDm | G44: Balance at 30 June 2026 | H44: {=INDEX(J44:R44,,$H$9)} -> 245 | J44: 245 | K44: 245 | L44: 245 | M44: 245 | N44: 245 | O44: 245 | P44: 245 | Q44: 245 | R44: 245
B45: USDm | G45: Establishment Fee | H45: {=INDEX(J45:R45,,$H$9)} -> 7 | J45: 7 | K45: 7 | L45: 7 | M45: 7 | N45: 7 | O45: 7 | P45: 7 | Q45: 7 | R45: 7
B46: USDm | G46: Fee Amortisation Balance 30 June 2026 | H46: {=INDEX(J46:R46,,$H$9)} -> 2.5 | J46: 2.5 | K46: 2.5 | L46: 2.5 | M46: 2.5 | N46: 2.5 | O46: 2.5 | P46: 2.5 | Q46: 2.5 | R46: 2.5
B47: Years | G47: Facility Term | H47: =YEARFRAC(H39,H41) -> 5
B48: Months | G48: Facility Term - months | H48: =(YEAR(H41)-YEAR(H39))*12+MONTH(H39)-MONTH(H41) -> 60
G49: Monthly Fee Amortisation | H49: =H45/H48 -> 0.11666667
F51: Existing Term Loan - Amortisation Schedule
G52: Month | H52: Amount
B53: USDm | G53: 3 | H53: {=INDEX(J53:R53,,$H$9)} -> 35 | J53: 35 | K53: 35 | L53: 35 | M53: 35 | N53: 35 | O53: 35 | P53: 35 | Q53: 35 | R53: 35
B54: USDm | G54: =G53+6 -> 9 | H54: {=INDEX(J54:R54,,$H$9)} -> 35 | J54: 35 | K54: 35 | L54: 35 | M54: 35 | N54: 35 | O54: 35 | P54: 35 | Q54: 35 | R54: 35
B55: USDm | G55: =G54+6 -> 15 | H55: {=INDEX(J55:R55,,$H$9)} -> 35 | J55: 35 | K55: 35 | L55: 35 | M55: 35 | N55: 35 | O55: 35 | P55: 35 | Q55: 35 | R55: 35
B56: USDm | G56: =G55+6 -> 21 | H56: {=INDEX(J56:R56,,$H$9)} -> 35 | J56: 35 | K56: 35 | L56: 35 | M56: 35 | N56: 35 | O56: 35 | P56: 35 | Q56: 35 | R56: 35
B57: USDm | G57: =G56+6 -> 27 | H57: {=INDEX(J57:R57,,$H$9)} -> 35 | J57: 35 | K57: 35 | L57: 35 | M57: 35 | N57: 35 | O57: 35 | P57: 35 | Q57: 35 | R57: 35
B58: USDm | G58: =G57+6 -> 33 | H58: {=INDEX(J58:R58,,$H$9)} -> 35 | J58: 35 | K58: 35 | L58: 35 | M58: 35 | N58: 35 | O58: 35 | P58: 35 | Q58: 35 | R58: 35
B59: USDm | G59: =G58+6 -> 39 | H59: {=INDEX(J59:R59,,$H$9)} -> 35 | J59: 35 | K59: 35 | L59: 35 | M59: 35 | N59: 35 | O59: 35 | P59: 35 | Q59: 35 | R59: 35
B60: USDm | G60: =G59+6 -> 45 | H60: {=INDEX(J60:R60,,$H$9)} -> 35 | J60: 35 | K60: 35 | L60: 35 | M60: 35 | N60: 35 | O60: 35 | P60: 35 | Q60: 35 | R60: 35
B61: USDm | G61: =G60+6 -> 51 | H61: {=INDEX(J61:R61,,$H$9)} -> 35 | J61: 35 | K61: 35 | L61: 35 | M61: 35 | N61: 35 | O61: 35 | P61: 35 | Q61: 35 | R61: 35
B62: USDm | G62: =G61+6 -> 57 | H62: {=INDEX(J62:R62,,$H$9)} -> 35 | J62: 35 | K62: 35 | L62: 35 | M62: 35 | N62: 35 | O62: 35 | P62: 35 | Q62: 35 | R62: 35
F64: New Term Loan
B65: Date | G65: Establishment Date | H65: {=INDEX(J65:R65,,$H$9)} -> 46418 | J65: =DATE(2027,1,31) -> 46418 | K65: =DATE(2027,1,31) -> 46418 | L65: =DATE(2027,1,31) -> 46418 | M65: =DATE(2027,1,31) -> 46418 | N65: =DATE(2027,1,31) -> 46418 | O65: =DATE(2027,1,31) -> 46418 | P65: =DATE(2027,1,31) -> 46418 | Q65: =DATE(2027,1,31) -> 46418 | R65: =DATE(2027,1,31) -> 46418
B66: USDm | G66: Facility Size | H66: {=INDEX(J66:R66,,$H$9)} -> 250 | J66: 250 | K66: 250 | L66: 250 | M66: 250 | N66: 250 | O66: 250 | P66: 250 | Q66: 250 | R66: 250
B67: Date | G67: Facility Maturity Date | H67: {=INDEX(J67:R67,,$H$9)} -> 48213 | J67: =DATE(2031,12,31) -> 48213 | K67: =DATE(2031,12,31) -> 48213 | L67: =DATE(2031,12,31) -> 48213 | M67: =DATE(2031,12,31) -> 48213 | N67: =DATE(2031,12,31) -> 48213 | O67: =DATE(2031,12,31) -> 48213 | P67: =DATE(2031,12,31) -> 48213 | Q67: =DATE(2031,12,31) -> 48213 | R67: =DATE(2031,12,31) -> 48213
B68: Text | G68: Reference Rate | H68: {=INDEX(J68:R68,,$H$9)} -> SOFR | J68: SOFR | K68: SOFR | L68: SOFR | M68: SOFR | N68: SOFR | O68: SOFR | P68: SOFR | Q68: SOFR | R68: SOFR
B69: Perc | G69: Margin | H69: {=INDEX(J69:R69,,$H$9)} -> 0.0375 | J69: 0.0375 | K69: 0.0375 | L69: 0.0375 | M69: 0.0375 | N69: 0.0375 | O69: 0.0375 | P69: 0.0375 | Q69: 0.0375 | R69: 0.0375
B70: Perc | G70: Establishment Fee | H70: {=INDEX(J70:R70,,$H$9)} -> 0.005 | J70: 0.005 | K70: 0.005 | L70: 0.005 | M70: 0.005 | N70: 0.005 | O70: 0.005 | P70: 0.005 | Q70: 0.005 | R70: 0.005
B71: USDm | G71: Amortised Establishment Fee | H71: {=INDEX(J71:R71,,$H$9)} -> 0.033783784 | J71: =(J66*$H$70)/$H$77 -> 0.033783784 | K71: =(K66*$H$70)/$H$77 -> 0.033783784 | L71: =(L66*$H$70)/$H$77 -> 0.033783784 | M71: =(M66*$H$70)/$H$77 -> 0.033783784 | N71: =(N66*$H$70)/$H$77 -> 0.033783784 | O71: =(O66*$H$70)/$H$77 -> 0.033783784 | P71: =(P66*$H$70)/$H$77 -> 0.033783784 | Q71: =(Q66*$H$70)/$H$77 -> 0.033783784 | R71: =(R66*$H$70)/$H$77 -> 0.033783784
G72: Facility Term - months | H72: =YEARFRAC(EOMONTH(H65,-1),H67)*12 -> 60
G73: Establishment Fee Total | H73: =H70*H66 -> 1.25
G74: Establishment Fee per month | H74: =H73/H72 -> 0.020833333
B76: Years | G76: Facility Term | H76: =YEARFRAC(H65,H67) -> 4.9166667
B77: Months | G77: Facility Term - months | H77: =(YEAR(H67)-YEAR(H65))*12+MONTH(H65)-MONTH(H67) -> 37
F79: New Term Loan - Amortisation Schedule
G80: Month | H80: Amount
B81: USDm | G81: 3 | H81: {=INDEX(J81:R81,,$H$9)} -> 25 | J81: 25 | K81: 25 | L81: 25 | M81: 25 | N81: 25 | O81: 25 | P81: 25 | Q81: 25 | R81: 25
B82: USDm | G82: =G81+6 -> 9 | H82: {=INDEX(J82:R82,,$H$9)} -> 25 | J82: 25 | K82: 25 | L82: 25 | M82: 25 | N82: 25 | O82: 25 | P82: 25 | Q82: 25 | R82: 25
B83: USDm | G83: =G82+6 -> 15 | H83: {=INDEX(J83:R83,,$H$9)} -> 25 | J83: 25 | K83: 25 | L83: 25 | M83: 25 | N83: 25 | O83: 25 | P83: 25 | Q83: 25 | R83: 25
B84: USDm | G84: =G83+6 -> 21 | H84: {=INDEX(J84:R84,,$H$9)} -> 25 | J84: 25 | K84: 25 | L84: 25 | M84: 25 | N84: 25 | O84: 25 | P84: 25 | Q84: 25 | R84: 25
B85: USDm | G85: =G84+6 -> 27 | H85: {=INDEX(J85:R85,,$H$9)} -> 25 | J85: 25 | K85: 25 | L85: 25 | M85: 25 | N85: 25 | O85: 25 | P85: 25 | Q85: 25 | R85: 25
B86: USDm | G86: =G85+6 -> 33 | H86: {=INDEX(J86:R86,,$H$9)} -> 25 | J86: 25 | K86: 25 | L86: 25 | M86: 25 | N86: 25 | O86: 25 | P86: 25 | Q86: 25 | R86: 25
B87: USDm | G87: =G86+6 -> 39 | H87: {=INDEX(J87:R87,,$H$9)} -> 25 | J87: 25 | K87: 25 | L87: 25 | M87: 25 | N87: 25 | O87: 25 | P87: 25 | Q87: 25 | R87: 25
B88: USDm | G88: =G87+6 -> 45 | H88: {=INDEX(J88:R88,,$H$9)} -> 25 | J88: 25 | K88: 25 | L88: 25 | M88: 25 | N88: 25 | O88: 25 | P88: 25 | Q88: 25 | R88: 25
B89: USDm | G89: =G88+6 -> 51 | H89: {=INDEX(J89:R89,,$H$9)} -> 25 | J89: 25 | K89: 25 | L89: 25 | M89: 25 | N89: 25 | O89: 25 | P89: 25 | Q89: 25 | R89: 25
B90: USDm | G90: =G89+6 -> 57 | H90: {=INDEX(J90:R90,,$H$9)} -> 25 | J90: 25 | K90: 25 | L90: 25 | M90: 25 | N90: 25 | O90: 25 | P90: 25 | Q90: 25 | R90: 25
F92: Working Capital Facility
B93: Date | G93: WCF Establishment Date | H93: {=INDEX(J93:R93,,$H$9)} -> 46234 | J93: =DATE(2026,7,31) -> 46234 | K93: =DATE(2026,7,31) -> 46234 | L93: =DATE(2026,7,31) -> 46234 | M93: =DATE(2026,7,31) -> 46234 | N93: =DATE(2026,7,31) -> 46234 | O93: =DATE(2026,7,31) -> 46234 | P93: =DATE(2026,7,31) -> 46234 | Q93: =DATE(2026,7,31) -> 46234 | R93: =DATE(2026,7,31) -> 46234
B94: USDm | G94: WCF Facility Size | H94: {=INDEX(J94:R94,,$H$9)} -> 200 | J94: 200 | K94: 200 | L94: 200 | M94: 200 | N94: 200 | O94: 200 | P94: 200 | Q94: 200 | R94: 200
B95: Date | G95: WCF Facility Maturity Date | H95: {=INDEX(J95:R95,,$H$9)} -> 47299 | J95: =DATE(2029,6,30) -> 47299 | K95: =DATE(2029,6,30) -> 47299 | L95: =DATE(2029,6,30) -> 47299 | M95: =DATE(2029,6,30) -> 47299 | N95: =DATE(2029,6,30) -> 47299 | O95: =DATE(2029,6,30) -> 47299 | P95: =DATE(2029,6,30) -> 47299 | Q95: =DATE(2029,6,30) -> 47299 | R95: =DATE(2029,6,30) -> 47299
B96: Text | G96: WCF Reference Rate | H96: {=INDEX(J96:R96,,$H$9)} -> SOFR | J96: SOFR | K96: SOFR | L96: SOFR | M96: SOFR | N96: SOFR | O96: SOFR | P96: SOFR | Q96: SOFR | R96: SOFR
B97: Perc | G97: WCF Margin | H97: {=INDEX(J97:R97,,$H$9)} -> 0.045 | J97: 0.045 | K97: 0.045 | L97: 0.045 | M97: 0.045 | N97: 0.045 | O97: 0.045 | P97: 0.045 | Q97: 0.045 | R97: 0.045
B98: Perc | G98: WCF Establishment Fee (%) | H98: {=INDEX(J98:R98,,$H$9)} -> 0.02 | J98: 0.02 | K98: 0.02 | L98: 0.02 | M98: 0.02 | N98: 0.02 | O98: 0.02 | P98: 0.02 | Q98: 0.02 | R98: 0.02
B99: Perc | G99: Commitment Fee (% margin) | H99: {=INDEX(J99:R99,,$H$9)} -> 0.4 | J99: 0.4 | K99: 0.4 | L99: 0.4 | M99: 0.4 | N99: 0.4 | O99: 0.4 | P99: 0.4 | Q99: 0.4 | R99: 0.4
B100: USDm | G100: WCF Establishment Fee - Total | H100: =H98*H94 -> 4
G101: WCF Establishment Fee per Month | H101: =H100/(YEARFRAC(EOMONTH(H93,-1),H95)*12) -> 0.11111111
F103: Working Capital Facility - Parent
B104: Date | G104: WCF-P Establishment Date | H104: {=INDEX(J104:R104,,$H$9)} -> 46234 | J104: =DATE(2026,7,31) -> 46234 | K104: =DATE(2026,7,31) -> 46234 | L104: =DATE(2026,7,31) -> 46234 | M104: =DATE(2026,7,31) -> 46234 | N104: =DATE(2026,7,31) -> 46234 | O104: =DATE(2026,7,31) -> 46234 | P104: =DATE(2026,7,31) -> 46234 | Q104: =DATE(2026,7,31) -> 46234 | R104: =DATE(2026,7,31) -> 46234
B105: USDm | G105: WCF-P Facility Size | H105: {=INDEX(J105:R105,,$H$9)} -> 70 | J105: 70 | K105: 70 | L105: 70 | M105: 70 | N105: 70 | O105: 70 | P105: 70 | Q105: 70 | R105: 70
B106: Date | G106: WCF-P Facility Maturity Date | H106: {=INDEX(J106:R106,,$H$9)} -> 47299 | J106: =DATE(2029,6,30) -> 47299 | K106: =DATE(2029,6,30) -> 47299 | L106: =DATE(2029,6,30) -> 47299 | M106: =DATE(2029,6,30) -> 47299 | N106: =DATE(2029,6,30) -> 47299 | O106: =DATE(2029,6,30) -> 47299 | P106: =DATE(2029,6,30) -> 47299 | Q106: =DATE(2029,6,30) -> 47299 | R106: =DATE(2029,6,30) -> 47299
B107: Text | G107: WCF-P Reference Rate | H107: {=INDEX(J107:R107,,$H$9)} -> SOFR | J107: SOFR | K107: SOFR | L107: SOFR | M107: SOFR | N107: SOFR | O107: SOFR | P107: SOFR | Q107: SOFR | R107: SOFR
B108: Perc | G108: WCF-P Margin | H108: {=INDEX(J108:R108,,$H$9)} -> 0.12 | J108: 0.12 | K108: 0.12 | L108: 0.12 | M108: 0.12 | N108: 0.12 | O108: 0.12 | P108: 0.12 | Q108: 0.12 | R108: 0.12
B109: Perc | G109: WCF-P Establishment Fee | H109: {=INDEX(J109:R109,,$H$9)} -> 0.005 | J109: 0.005 | K109: 0.005 | L109: 0.005 | M109: 0.005 | N109: 0.005 | O109: 0.005 | P109: 0.005 | Q109: 0.005 | R109: 0.005
B110: Perc | G110: WCF-P Establishment Date | H110: {=INDEX(J110:R110,,$H$9)} -> 0.03 | J110: 0.03 | K110: 0.03 | L110: 0.03 | M110: 0.03 | N110: 0.03 | O110: 0.03 | P110: 0.03 | Q110: 0.03 | R110: 0.03
E112: Corporate Items
F114: Bank Account
B115: USDm | G115: Starting Balance | H115: {=INDEX(J115:R115,,$H$9)} -> 212 | J115: 212 | K115: 212 | L115: 212 | M115: 212 | N115: 212 | O115: 212 | P115: 212 | Q115: 212 | R115: 212
B116: Text | G116: Interest Reference | H116: {=INDEX(J116:R116,,$H$9)} -> SOFR | J116: SOFR | K116: SOFR | L116: SOFR | M116: SOFR | N116: SOFR | O116: SOFR | P116: SOFR | Q116: SOFR | R116: SOFR
B117: 1/0 (On/Off) | G117: Interest income on/off | H117: {=INDEX(J117:R117,,$H$9)} -> 1 | J117: 1 | K117: 1 | L117: 1 | M117: 1 | N117: 1 | O117: 1 | P117: 1 | Q117: 1 | R117: 1
F119: Corporate Depreciation
B120: USDm | G120: Corporate Depreciation | H120: {=INDEX(J120:R120,,$H$9)} -> 1 | J120: 1 | K120: 2 | L120: 3 | M120: 1 | N120: 1 | O120: 1 | P120: 1 | Q120: 1 | R120: 1
D122: Equity Items
...

Sheet TRAINING >>

Sheet Dates
B1: =Control!$D$2 -> Basic Financial Model
B2: =MID(CELL("filename",$B$1),FIND("]",CELL("filename",$B$1))+1,255) -> Dates
B3: =Control!$D$4 -> Financial Scenario: Base Case
B4: Calendar Year | F4: =F12 -> CY26 | G4: =G12 -> CY26 | H4: =H12 -> CY26 | I4: =I12 -> CY26 | J4: =J12 -> CY26 | K4: =K12 -> CY26 | L4: =L12 -> CY27 | M4: =M12 -> CY27 | ... KA4: =KA12 -> CY49
B5: Financial Year | F5: =F13 -> FY27 | G5: =G13 -> FY27 | H5: =H13 -> FY27 | I5: =I13 -> FY27 | J5: =J13 -> FY27 | K5: =K13 -> FY27 | L5: =L13 -> FY27 | M5: =M13 -> FY27 | ... KA5: =KA13 -> FY50
B6: Date | F6: =TEXT(F11,"mmm-yy") -> Jul-26 | G6: =TEXT(G11,"mmm-yy") -> Aug-26 | H6: =TEXT(H11,"mmm-yy") -> Sep-26 | I6: =TEXT(I11,"mmm-yy") -> Oct-26 | J6: =TEXT(J11,"mmm-yy") -> Nov-26 | K6: =TEXT(K11,"mmm-yy") -> Dec-26 | L6: =TEXT(L11,"mmm-yy") -> Jan-27 | M6: =TEXT(M11,"mmm-yy") -> Feb-27 | ... KA6: =TEXT(KA11,"mmm-yy") -> Dec-49
B8: Periods
E10: Start of period | F10: =DATE(2026,7,1) -> 46204 | G10: =F11+1 -> 46235 | H10: =G11+1 -> 46266 | I10: =H11+1 -> 46296 | J10: =I11+1 -> 46327 | K10: =J11+1 -> 46357 | L10: =K11+1 -> 46388 | M10: =L11+1 -> 46419 | N10: =M11+1 -> 46447 | ... KA10: =JZ11+1 -> 54758
E11: End of period | F11: =EOMONTH(F10,0) -> 46234 | G11: =EOMONTH(G10,0) -> 46265 | H11: =EOMONTH(H10,0) -> 46295 | I11: =EOMONTH(I10,0) -> 46326 | J11: =EOMONTH(J10,0) -> 46356 | K11: =EOMONTH(K10,0) -> 46387 | L11: =EOMONTH(L10,0) -> 46418 | M11: =EOMONTH(M10,0) -> 46446 | ... KA11: =EOMONTH(KA10,0) -> 54788
E12: Calendar year | F12: ="CY"&RIGHT(YEAR(F10),2) -> CY26 | G12: ="CY"&RIGHT(YEAR(G10),2) -> CY26 | H12: ="CY"&RIGHT(YEAR(H10),2) -> CY26 | I12: ="CY"&RIGHT(YEAR(I10),2) -> CY26 | J12: ="CY"&RIGHT(YEAR(J10),2) -> CY26 | K12: ="CY"&RIGHT(YEAR(K10),2) -> CY26 | L12: ="CY"&RIGHT(YEAR(L10),2) -> CY27 | M12: ="CY"&RIGHT(YEAR(M10),2) -> CY27 | ... KA12: ="CY"&RIGHT(YEAR(KA10),2) -> CY49
E13: Financial Year | F13: ="FY"&IF(MONTH(F10)>6,RIGHT(YEAR(F10)+1,2),RIGHT(YEAR(F10),2)) -> FY27 | G13: ="FY"&IF(MONTH(G10)>6,RIGHT(YEAR(G10)+1,2),RIGHT(YEAR(G10),2)) -> FY27 | H13: ="FY"&IF(MONTH(H10)>6,RIGHT(YEAR(H10)+1,2),RIGHT(YEAR(H10),2)) -> FY27 | I13: ="FY"&IF(MONTH(I10)>6,RIGHT(YEAR(I10)+1,2),RIGHT(YEAR(I10),2)) -> FY27 | J13: ="FY"&IF(MONTH(J10)>6,RIGHT(YEAR(J10)+1,2),RIGHT(YEAR(J10),2)) -> FY27 | K13: ="FY"&IF(MONTH(K10)>6,RIGHT(YEAR(K10)+1,2),RIGHT(YEAR(K10),2)) -> FY27 | L13: ="FY"&IF(MONTH(L10)>6,RIGHT(YEAR(L10)+1,2),RIGHT(YEAR(L10),2)) -> FY27 | M13: ="FY"&IF(MONTH(M10)>6,RIGHT(YEAR(M10)+1,2),RIGHT(YEAR(M10),2)) -> FY27 | ... KA13: ="FY"&IF(MONTH(KA10)>6,RIGHT(YEAR(KA10)+1,2),RIGHT(YEAR(KA10),2)) -> FY50
E14: Days in Period | F14: =F11-F10+1 -> 31 | G14: =G11-G10+1 -> 31 | H14: =H11-H10+1 -> 30 | I14: =I11-I10+1 -> 31 | J14: =J11-J10+1 -> 30 | K14: =K11-K10+1 -> 31 | L14: =L11-L10+1 -> 31 | M14: =M11-M10+1 -> 28 | ... KA14: =KA11-KA10+1 -> 31
E15: Inflation index
B17: Dates Training
B36: Date Timelines
E53: The main project timeline is provided at the top of this sheet. We are using monthly periods.
E54: The first date uses the DATE function, then all other dates use EOMONTH or the prior month plus 1.
E56: Example:
E57: Start of period | F57: =DATE(2026,7,1) -> 46204 | G57: =F58+1 -> 46235 | H57: =G58+1 -> 46266 | I57: =H58+1 -> 46296
E58: End of period | F58: =EOMONTH(F57,0) -> 46234 | G58: =EOMONTH(G57,0) -> 46265 | H58: =EOMONTH(H57,0) -> 46295 | I58: =EOMONTH(I57,0) -> 46326
E60: Formulas:
E61: Start of period | F61: =_xlfn.FORMULATEXT(F57) -> =DATE(2026,7,1) | G61: =_xlfn.FORMULATEXT(G57) -> =F58+1 | H61: =_xlfn.FORMULATEXT(H57) -> =G58+1 | I61: =_xlfn.FORMULATEXT(I57) -> =H58+1
E62: End of period | F62: =_xlfn.FORMULATEXT(F58) -> =EOMONTH(F57,0) | G62: =_xlfn.FORMULATEXT(G58) -> =EOMONTH(G57,0) | H62: =_xlfn.FORMULATEXT(H58) -> =EOMONTH(H57,0) | I62: =_xlfn.FORMULATEXT(I58) -> =EOMONTH(I57,0)
D64: EOMONTH
E65: EOMONTH also becomes useful if you want to offset by quarter, years, and also if you want to go backwards in time.
E66: The EOMONTH formula always gives the end of the month, so you will need to adjust for any other date as required
E68: Item | F68: Example | G68: FORMULA TEXT
E69: Reference Date | F69: =DATE(2026,7,15) -> 46218 | G69: =_xlfn.FORMULATEXT(F69) -> =DATE(2026,7,15) | H69: =DATE(2026,7,15)
E70: End of current month | F70: =EOMONTH(F69,0) -> 46234 | G70: =_xlfn.FORMULATEXT(F70) -> =EOMONTH(F69,0)
E71: End of quarter | F71: =EOMONTH(F69,2) -> 46295 | G71: =_xlfn.FORMULATEXT(F71) -> =EOMONTH(F69,2) | H71: * assuming reference month is always the start of the quarter
E72: End of quarter (any month) | F72: =EOMONTH(F69,MOD(3-MONTH(F69),3)) -> 46295 | G72: =_xlfn.FORMULATEXT(F72) -> =EOMONTH(F69,MOD(3-MONTH(F69),3)) | H72: * any date within the quarter
E73: Next year | F73: =EOMONTH(F69,12) -> 46599 | G73: =_xlfn.FORMULATEXT(F73) -> =EOMONTH(F69,12)
E74: Start of month | F74: =EOMONTH(F69,-1)+1 -> 46204 | G74: =_xlfn.FORMULATEXT(F74) -> =EOMONTH(F69,-1)+1
D76: DATE
E77: You can also use DATE to achieve similar outcomes, but this can have more complex or longer forumlas.
E78: Item | F78: Example | G78: FORMULA TEXT
E79: Date | F79: =DATE(2026,7,15) -> 46218 | G79: =_xlfn.FORMULATEXT(F79) -> =DATE(2026,7,15)
E80: End of current month | F80: =DATE(YEAR(F79),MONTH(F79)+1,1)-1 -> 46234 | G80: =_xlfn.FORMULATEXT(F80) -> =DATE(YEAR(F79),MONTH(F79)+1,1)-1
E81: End of quarter | F81: =DATE(YEAR(F80),MONTH(F80)+3,1)-1 -> 46295 | G81: =_xlfn.FORMULATEXT(F81) -> =DATE(YEAR(F80),MONTH(F80)+3,1)-1 | H81: * assuming reference month is always the start of the quarter
E82: End of quarter (any month) | F82: =DATE(YEAR(F69),CEILING(MONTH(F69),3)+1,0) -> 46295 | G82: =_xlfn.FORMULATEXT(F82) -> =DATE(YEAR(F69),CEILING(MONTH(F69),3)+1,0) | H82: * any date within the quarter
E83: Next year | F83: =EOMONTH(F79,12) -> 46599 | G83: =_xlfn.FORMULATEXT(F83) -> =EOMONTH(F79,12)
E84: Start of month | F84: =EOMONTH(F79,-1)+1 -> 46204 | G84: =_xlfn.FORMULATEXT(F84) -> =EOMONTH(F79,-1)+1
D87: OTHER
E88: Item | F88: Example | G88: FORMULA TEXT
E89: End of quarter using LET | F89: =_xlfn.LET( _xlpm.RefDate,F69, _xlpm.QuarterEndMonth,CEILING(MONTH(_xlpm.RefDate),3), DATE(YEAR(_xlpm.RefDate),_xlpm.QuarterEndMonth+1,0) ) -> 46295 | G89: =_xlfn.FORMULATEXT(F89) -> =LET( RefDate,F69, QuarterEndMonth,CEILING(MONTH(RefDate),3), DATE(YEAR(RefDate),QuarterEndMonth+1,0) ) | H89: * longer formula, refer to formula bar
D91: Calendar and Financial Years
E92: In order to sum up quarters, financial or calendar years you will need a flag to identify where a specific date lies as shown below.
E94: Item | F94: Example | G94: FORMULA TEXT
E95: Reference Date | F95: =DATE(2026,7,15) -> 46218 | G95: =_xlfn.FORMULATEXT(F95) -> =DATE(2026,7,15) | H95: =DATE(2026,7,15)
E96: Calendar year | F96: ="CY"&RIGHT(YEAR(F95),2) -> CY26 | G96: =_xlfn.FORMULATEXT(F96) -> ="CY"&RIGHT(YEAR(F95),2)
E97: Financial Year | F97: ="FY"&IF(MONTH(F95)>6,RIGHT(YEAR(F95)+1,2),RIGHT(YEAR(F95),2)) -> FY27 | G97: =_xlfn.FORMULATEXT(F97) -> ="FY"&IF(MONTH(F95)>6,RIGHT(YEAR(F95)+1,2),RIGHT(YEAR(F95),2)) | H97: * assumes June YE
E99: Any month end
E100: Item | F100: Example | G100: FORMULA TEXT
E101: Reference Date | F101: =DATE(2026,7,15) -> 46218 | G101: =_xlfn.FORMULATEXT(F101) -> =DATE(2026,7,15)
E102: Month End | F102: 3
E103: Financial Year | F103: ="FY"&RIGHT(TEXT(YEAR(EDATE(F101,12-F102)),"00"),2) -> FY27 | G103: =_xlfn.FORMULATEXT(F103) -> ="FY"&RIGHT(TEXT(YEAR(EDATE(F101,12-F102)),"00"),2)
E104: * This allows you to have any month as the financial year end, it uses the EDATE formula, which pushes the current date out by x months.
E106: Components of the above EDATE Formula:
E107: Reference Date | F107: =DATE(2026,7,15) -> 46218
E108: Month End | F108: 3 | G108: << change this
E109: EDATE | F109: =EDATE(F107,12-F108) -> 46492 | G109: << impacts this (gets relative date in the callendar year for the financial year month end date)
E110: Financial Year | F110: ="FY "&YEAR(F109) -> FY 2027
D113: Dates in period
E114: Item | F114: Example
E115: Start Date | F115: =DATE(2026,7,1) -> 46204
E116: End Date | F116: =EOMONTH(F115,0) -> 46234
E117: Days in Period | F117: =F116-F115+1 -> 31 | G117: =_xlfn.FORMULATEXT(F117) -> =F116-F115+1
E118: Error version | F118: =F116-F115 -> 30 | G118: =_xlfn.FORMULATEXT(F118) -> =F116-F115 | H118: * don’t forget to add 1 if you refer to the start and end date
E120: Item | F120: Example
E121: End of prior period | F121: =DATE(2026,6,30) -> 46203
E122: End Date | F122: =EOMONTH(F121,1) -> 46234
E123: Error version | F123: =F122-F121+1 -> 32 | G123: =_xlfn.FORMULATEXT(F123) -> =F122-F121+1 | H123: * don’t add 1 if you use end of prior period as a reference
E124: Days in Period | F124: =F122-F121 -> 31 | G124: =_xlfn.FORMULATEXT(F124) -> =F122-F121 | H124: * don’t forget to add 1 if you refer to the start and end date

Sheet NPV
B1: Yearly
B2: Period | C2: 0 | D2: =C2+1 -> 1 | E2: =D2+1 -> 2 | F2: =E2+1 -> 3 | G2: =F2+1 -> 4 | H2: =G2+1 -> 5 | I2: =H2+1 -> 6 | J2: =I2+1 -> 7 | K2: =J2+1 -> 8 | ... AA2: =Z2+1 -> 24
B3: Date | C3: =DATE(2026,12,31) -> 46387 | D3: =EOMONTH(C3,12) -> 46752 | E3: =EOMONTH(D3,12) -> 47118 | F3: =EOMONTH(E3,12) -> 47483 | G3: =EOMONTH(F3,12) -> 47848 | H3: =EOMONTH(G3,12) -> 48213 | I3: =EOMONTH(H3,12) -> 48579 | J3: =EOMONTH(I3,12) -> 48944 | K3: =EOMONTH(J3,12) -> 49309 | ... AA3: =EOMONTH(Z3,12) -> 55153
B4: FCF | C4: -1000 | D4: -250 | E4: -100 | F4: 100 | G4: 175 | H4: 250 | I4: 325 | J4: 400 | K4: 400 | L4: 400 | M4: 400 | N4: 400 | O4: 400 | P4: 400 | Q4: 400 | R4: 400 | S4: 400 | T4: 400 | U4: 400 | V4: 400 | W4: 400 | X4: 400 | Y4: 400 | Z4: 400 | AA4: 400
B5: Rate | C5: 0.1
B6: XNPV | C6: =XNPV($C$5,C4:$AA4,C3:$AA3) -> 1073.4182 | D6: =XNPV($C$5,D4:$AA4,D3:$AA3) -> 2280.76 | E6: =XNPV($C$5,E4:$AA4,E3:$AA3) -> 2784.563 | F6: =XNPV($C$5,F4:$AA4,F3:$AA3) -> 3173.0193 | G6: =XNPV($C$5,G4:$AA4,G3:$AA3) -> 3380.3213 | H6: =XNPV($C$5,H4:$AA4,H3:$AA3) -> 3525.8534 | I6: =XNPV($C$5,I4:$AA4,I3:$AA3) -> 3604.3798 | J6: =XNPV($C$5,J4:$AA4,J3:$AA3) -> 3607.3178 | ... AA6: =XNPV($C$5,AA4:$AA4,AA3:$AA3) -> 400
B7: NPV | C7: =NPV($C$5,D4:$AA4)+C4 -> 1075.2192 | D7: =NPV($C$5,E4:$AA4)+D4 -> 2282.7411 | E7: =NPV($C$5,F4:$AA4)+E4 -> 2786.0152 | F7: =NPV($C$5,G4:$AA4)+F4 -> 3174.6167 | G7: =NPV($C$5,H4:$AA4)+G4 -> 3382.0784 | H7: =NPV($C$5,I4:$AA4)+H4 -> 3527.7862 | I7: =NPV($C$5,J4:$AA4)+I4 -> 3605.5648 | J7: =NPV($C$5,K4:$AA4)+J4 -> 3608.6213 | ... Z7: =NPV($C$5,AA4:$AA4)+Z4 -> 763.63636
B9: Manual (days) - PV | C9: =C4 -> -1000 | D9: =D4/(1+$C$5)^((D3-$C$3)/365) -> -227.27273 | E9: =E4/(1+$C$5)^((E3-$C$3)/365) -> -82.62305 | F9: =F4/(1+$C$5)^((F3-$C$3)/365) -> 75.111864 | G9: =G4/(1+$C$5)^((G3-$C$3)/365) -> 119.49615 | H9: =H4/(1+$C$5)^((H3-$C$3)/365) -> 155.1898 | I9: =I4/(1+$C$5)^((I3-$C$3)/365) -> 183.35824 | J9: =J4/(1+$C$5)^((J3-$C$3)/365) -> 205.15608 | K9: =K4/(1+$C$5)^((K3-$C$3)/365) -> 186.50552 | ... AA9: =AA4/(1+$C$5)^((AA3-$C$3)/365) -> 40.546663
B10: Manual (days) - NPV | C10: =SUM(C9:AA9) -> 1073.4182
B11: Check | C11: =C10-C6 -> 0
B12: Manual (periods) - PV | C12: =C4/(1+$C$5)^C2 -> -1000 | D12: =D4/(1+$C$5)^D2 -> -227.27273 | E12: =E4/(1+$C$5)^E2 -> -82.644628 | F12: =F4/(1+$C$5)^F2 -> 75.13148 | G12: =G4/(1+$C$5)^G2 -> 119.52735 | H12: =H4/(1+$C$5)^H2 -> 155.23033 | I12: =I4/(1+$C$5)^I2 -> 183.45403 | J12: =J4/(1+$C$5)^J2 -> 205.26325 | ... AA12: =AA4/(1+$C$5)^AA2 -> 40.610239
B13: Manual (periods) - NPV | C13: =SUM(C12:$AA12) -> 1075.2192
B14: Check | C14: =C13-C7 -> 0
B19: Quarterly
